Workbook

Sheet Recap
A1: ROLLING THREE MONTHS
A2: Agent | B2: Total Policies | C2: Manager | D2: Founded | E2: Partially Founded | F2: Unfounded | G2: Unfounded, coaching opportunities present | H2: Total | I2: Complaint Percentage
A3: Kylie DeMarino | B3: =COUNTIFS(policies[[Effective Date ]],">="&EOMONTH(TODAY(),-3)+1,policies[[Effective Date ]],"<="&EOMONTH(TODAY(),0),policies[Column3],Summary[[#This Row],[Agent]]) -> 133 | C3: John Tellez | D3: =COUNTIFS(Results[Agent],Summary[[#This Row],[Agent]],Results[Reviewed Date],">="&EOMONTH(TODAY(),-3)+1,Results[Reviewed Date],"<="&EOMONTH(TODAY(),0),Results[Determination],"Founded") -> 3 | E3: =COUNTIFS(Results[Agent],Summary[[#This Row],[Agent]],Results[Reviewed Date],">="&EOMONTH(TODAY(),-3)+1,Results[Reviewed Date],"<="&EOMONTH(TODAY(),0),Results[Determination],"Partially Founded") -> 2 | F3: =COUNTIFS(Results[Agent],Summary[[#This Row],[Agent]],Results[Reviewed Date],">="&EOMONTH(TODAY(),-3)+1,Results[Reviewed Date],"<="&EOMONTH(TODAY(),0),Results[Determination],"Unfounded") -> 0 | G3: =COUNTIFS(Results[Agent],Summary[[#This Row],[Agent]],Results[Reviewed Date],">="&EOMONTH(TODAY(),-3)+1,Results[Reviewed Date],"<="&EOMONTH(TODAY(),0),Results[Determination],"Unfounded, coaching opportunities present") -> 1 | H3: =COUNTIFS(Results[Agent],Summary[[#This Row],[Agent]],Results[Reviewed Date],">="&EOMONTH(TODAY(),-3)+1,Results[Reviewed Date],"<="&EOMONTH(TODAY(),0)) -> 6 | I3: =IFERROR(Summary[[#This Row],[Total]]/Summary[[#This Row],[Total Policies]],"") -> 0.045112782
A4: Gabriela Rivera | B4: =COUNTIFS(policies[[Effective Date ]],">="&EOMONTH(TODAY(),-3)+1,policies[[Effective Date ]],"<="&EOMONTH(TODAY(),0),policies[Column3],Summary[[#This Row],[Agent]]) -> 86 | C4: Nesia Jefferies | D4: =COUNTIFS(Results[Agent],Summary[[#This Row],[Agent]],Results[Reviewed Date],">="&EOMONTH(TODAY(),-3)+1,Results[Reviewed Date],"<="&EOMONTH(TODAY(),0),Results[Determination],"Founded") -> 3 | E4: =COUNTIFS(Results[Agent],Summary[[#This Row],[Agent]],Results[Reviewed Date],">="&EOMONTH(TODAY(),-3)+1,Results[Reviewed Date],"<="&EOMONTH(TODAY(),0),Results[Determination],"Partially Founded") -> 1 | F4: =COUNTIFS(Results[Agent],Summary[[#This Row],[Agent]],Results[Reviewed Date],">="&EOMONTH(TODAY(),-3)+1,Results[Reviewed Date],"<="&EOMONTH(TODAY(),0),Results[Determination],"Unfounded") -> 0 | G4: =COUNTIFS(Results[Agent],Summary[[#This Row],[Agent]],Results[Reviewed Date],">="&EOMONTH(TODAY(),-3)+1,Results[Reviewed Date],"<="&EOMONTH(TODAY(),0),Results[Determination],"Unfounded, coaching opportunities present") -> 0 | H4: =COUNTIFS(Results[Agent],Summary[[#This Row],[Agent]],Results[Reviewed Date],">="&EOMONTH(TODAY(),-3)+1,Results[Reviewed Date],"<="&EOMONTH(TODAY(),0)) -> 4 | I4: =IFERROR(Summary[[#This Row],[Total]]/Summary[[#This Row],[Total Policies]],"") -> 0.046511628
A5: Robert Lang | B5: =COUNTIFS(policies[[Effective Date ]],">="&EOMONTH(TODAY(),-3)+1,policies[[Effective Date ]],"<="&EOMONTH(TODAY(),0),policies[Column3],Summary[[#This Row],[Agent]]) -> 94 | C5: Nesia Jefferies | D5: =COUNTIFS(Results[Agent],Summary[[#This Row],[Agent]],Results[Reviewed Date],">="&EOMONTH(TODAY(),-3)+1,Results[Reviewed Date],"<="&EOMONTH(TODAY(),0),Results[Determination],"Founded") -> 3 | E5: =COUNTIFS(Results[Agent],Summary[[#This Row],[Agent]],Results[Reviewed Date],">="&EOMONTH(TODAY(),-3)+1,Results[Reviewed Date],"<="&EOMONTH(TODAY(),0),Results[Determination],"Partially Founded") -> 0 | F5: =COUNTIFS(Results[Agent],Summary[[#This Row],[Agent]],Results[Reviewed Date],">="&EOMONTH(TODAY(),-3)+1,Results[Reviewed Date],"<="&EOMONTH(TODAY(),0),Results[Determination],"Unfounded") -> 0 | G5: =COUNTIFS(Results[Agent],Summary[[#This Row],[Agent]],Results[Reviewed Date],">="&EOMONTH(TODAY(),-3)+1,Results[Reviewed Date],"<="&EOMONTH(TODAY(),0),Results[Determination],"Unfounded, coaching opportunities present") -> 0 | H5: =COUNTIFS(Results[Agent],Summary[[#This Row],[Agent]],Results[Reviewed Date],">="&EOMONTH(TODAY(),-3)+1,Results[Reviewed Date],"<="&EOMONTH(TODAY(),0)) -> 3 | I5: =IFERROR(Summary[[#This Row],[Total]]/Summary[[#This Row],[Total Policies]],"") -> 0.031914894
A6: Tonja Howard | B6: =COUNTIFS(policies[[Effective Date ]],">="&EOMONTH(TODAY(),-3)+1,policies[[Effective Date ]],"<="&EOMONTH(TODAY(),0),policies[Column3],Summary[[#This Row],[Agent]]) -> 115 | C6: Brian Henderson | D6: =COUNTIFS(Results[Agent],Summary[[#This Row],[Agent]],Results[Reviewed Date],">="&EOMONTH(TODAY(),-3)+1,Results[Reviewed Date],"<="&EOMONTH(TODAY(),0),Results[Determination],"Founded") -> 2 | E6: =COUNTIFS(Results[Agent],Summary[[#This Row],[Agent]],Results[Reviewed Date],">="&EOMONTH(TODAY(),-3)+1,Results[Reviewed Date],"<="&EOMONTH(TODAY(),0),Results[Determination],"Partially Founded") -> 1 | F6: =COUNTIFS(Results[Agent],Summary[[#This Row],[Agent]],Results[Reviewed Date],">="&EOMONTH(TODAY(),-3)+1,Results[Reviewed Date],"<="&EOMONTH(TODAY(),0),Results[Determination],"Unfounded") -> 0 | G6: =COUNTIFS(Results[Agent],Summary[[#This Row],[Agent]],Results[Reviewed Date],">="&EOMONTH(TODAY(),-3)+1,Results[Reviewed Date],"<="&EOMONTH(TODAY(),0),Results[Determination],"Unfounded, coaching opportunities present") -> 1 | H6: =COUNTIFS(Results[Agent],Summary[[#This Row],[Agent]],Results[Reviewed Date],">="&EOMONTH(TODAY(),-3)+1,Results[Reviewed Date],"<="&EOMONTH(TODAY(),0)) -> 4 | I6: =IFERROR(Summary[[#This Row],[Total]]/Summary[[#This Row],[Total Policies]],"") -> 0.034782609
A7: Whitney Benoit | B7: =COUNTIFS(policies[[Effective Date ]],">="&EOMONTH(TODAY(),-3)+1,policies[[Effective Date ]],"<="&EOMONTH(TODAY(),0),policies[Column3],Summary[[#This Row],[Agent]]) -> 97 | C7: Brian Henderson | D7: =COUNTIFS(Results[Agent],Summary[[#This Row],[Agent]],Results[Reviewed Date],">="&EOMONTH(TODAY(),-3)+1,Results[Reviewed Date],"<="&EOMONTH(TODAY(),0),Results[Determination],"Founded") -> 2 | E7: =COUNTIFS(Results[Agent],Summary[[#This Row],[Agent]],Results[Reviewed Date],">="&EOMONTH(TODAY(),-3)+1,Results[Reviewed Date],"<="&EOMONTH(TODAY(),0),Results[Determination],"Partially Founded") -> 1 | F7: =COUNTIFS(Results[Agent],Summary[[#This Row],[Agent]],Results[Reviewed Date],">="&EOMONTH(TODAY(),-3)+1,Results[Reviewed Date],"<="&EOMONTH(TODAY(),0),Results[Determination],"Unfounded") -> 0 | G7: =COUNTIFS(Results[Agent],Summary[[#This Row],[Agent]],Results[Reviewed Date],">="&EOMONTH(TODAY(),-3)+1,Results[Reviewed Date],"<="&EOMONTH(TODAY(),0),Results[Determination],"Unfounded, coaching opportunities present") -> 0 | H7: =COUNTIFS(Results[Agent],Summary[[#This Row],[Agent]],Results[Reviewed Date],">="&EOMONTH(TODAY(),-3)+1,Results[Reviewed Date],"<="&EOMONTH(TODAY(),0)) -> 3 | I7: =IFERROR(Summary[[#This Row],[Total]]/Summary[[#This Row],[Total Policies]],"") -> 0.030927835
A8: Christina Nguyen | B8: =COUNTIFS(policies[[Effective Date ]],">="&EOMONTH(TODAY(),-3)+1,policies[[Effective Date ]],"<="&EOMONTH(TODAY(),0),policies[Column3],Summary[[#This Row],[Agent]]) -> 90 | C8: Nesia Jefferies | D8: =COUNTIFS(Results[Agent],Summary[[#This Row],[Agent]],Results[Reviewed Date],">="&EOMONTH(TODAY(),-3)+1,Results[Reviewed Date],"<="&EOMONTH(TODAY(),0),Results[Determination],"Founded") -> 2 | E8: =COUNTIFS(Results[Agent],Summary[[#This Row],[Agent]],Results[Reviewed Date],">="&EOMONTH(TODAY(),-3)+1,Results[Reviewed Date],"<="&EOMONTH(TODAY(),0),Results[Determination],"Partially Founded") -> 0 | F8: =COUNTIFS(Results[Agent],Summary[[#This Row],[Agent]],Results[Reviewed Date],">="&EOMONTH(TODAY(),-3)+1,Results[Reviewed Date],"<="&EOMONTH(TODAY(),0),Results[Determination],"Unfounded") -> 0 | G8: =COUNTIFS(Results[Agent],Summary[[#This Row],[Agent]],Results[Reviewed Date],">="&EOMONTH(TODAY(),-3)+1,Results[Reviewed Date],"<="&EOMONTH(TODAY(),0),Results[Determination],"Unfounded, coaching opportunities present") -> 1 | H8: =COUNTIFS(Results[Agent],Summary[[#This Row],[Agent]],Results[Reviewed Date],">="&EOMONTH(TODAY(),-3)+1,Results[Reviewed Date],"<="&EOMONTH(TODAY(),0)) -> 3 | I8: =IFERROR(Summary[[#This Row],[Total]]/Summary[[#This Row],[Total Policies]],"") -> 0.033333333
A9: Robin O'Quin | B9: =COUNTIFS(policies[[Effective Date ]],">="&EOMONTH(TODAY(),-3)+1,policies[[Effective Date ]],"<="&EOMONTH(TODAY(),0),policies[Column3],Summary[[#This Row],[Agent]]) -> 0 | C9: Brian Henderson | D9: =COUNTIFS(Results[Agent],Summary[[#This Row],[Agent]],Results[Reviewed Date],">="&EOMONTH(TODAY(),-3)+1,Results[Reviewed Date],"<="&EOMONTH(TODAY(),0),Results[Determination],"Founded") -> 2 | E9: =COUNTIFS(Results[Agent],Summary[[#This Row],[Agent]],Results[Reviewed Date],">="&EOMONTH(TODAY(),-3)+1,Results[Reviewed Date],"<="&EOMONTH(TODAY(),0),Results[Determination],"Partially Founded") -> 0 | F9: =COUNTIFS(Results[Agent],Summary[[#This Row],[Agent]],Results[Reviewed Date],">="&EOMONTH(TODAY(),-3)+1,Results[Reviewed Date],"<="&EOMONTH(TODAY(),0),Results[Determination],"Unfounded") -> 0 | G9: =COUNTIFS(Results[Agent],Summary[[#This Row],[Agent]],Results[Reviewed Date],">="&EOMONTH(TODAY(),-3)+1,Results[Reviewed Date],"<="&EOMONTH(TODAY(),0),Results[Determination],"Unfounded, coaching opportunities present") -> 0 | H9: =COUNTIFS(Results[Agent],Summary[[#This Row],[Agent]],Results[Reviewed Date],">="&EOMONTH(TODAY(),-3)+1,Results[Reviewed Date],"<="&EOMONTH(TODAY(),0)) -> 2 | I9: =IFERROR(Summary[[#This Row],[Total]]/Summary[[#This Row],[Total Policies]],"")
A10: Ryan Lefler | B10: =COUNTIFS(policies[[Effective Date ]],">="&EOMONTH(TODAY(),-3)+1,policies[[Effective Date ]],"<="&EOMONTH(TODAY(),0),policies[Column3],Summary[[#This Row],[Agent]]) -> 83 | C10: Brian Henderson | D10: =COUNTIFS(Results[Agent],Summary[[#This Row],[Agent]],Results[Reviewed Date],">="&EOMONTH(TODAY(),-3)+1,Results[Reviewed Date],"<="&EOMONTH(TODAY(),0),Results[Determination],"Founded") -> 2 | E10: =COUNTIFS(Results[Agent],Summary[[#This Row],[Agent]],Results[Reviewed Date],">="&EOMONTH(TODAY(),-3)+1,Results[Reviewed Date],"<="&EOMONTH(TODAY(),0),Results[Determination],"Partially Founded") -> 0 | F10: =COUNTIFS(Results[Agent],Summary[[#This Row],[Agent]],Results[Reviewed Date],">="&EOMONTH(TODAY(),-3)+1,Results[Reviewed Date],"<="&EOMONTH(TODAY(),0),Results[Determination],"Unfounded") -> 0 | G10: =COUNTIFS(Results[Agent],Summary[[#This Row],[Agent]],Results[Reviewed Date],">="&EOMONTH(TODAY(),-3)+1,Results[Reviewed Date],"<="&EOMONTH(TODAY(),0),Results[Determination],"Unfounded, coaching opportunities present") -> 0 | H10: =COUNTIFS(Results[Agent],Summary[[#This Row],[Agent]],Results[Reviewed Date],">="&EOMONTH(TODAY(),-3)+1,Results[Reviewed Date],"<="&EOMONTH(TODAY(),0)) -> 2 | I10: =IFERROR(Summary[[#This Row],[Total]]/Summary[[#This Row],[Total Policies]],"") -> 0.024096386
A11: Victor Filimonchuk | B11: =COUNTIFS(policies[[Effective Date ]],">="&EOMONTH(TODAY(),-3)+1,policies[[Effective Date ]],"<="&EOMONTH(TODAY(),0),policies[Column3],Summary[[#This Row],[Agent]]) -> 67 | C11: John Tellez | D11: =COUNTIFS(Results[Agent],Summary[[#This Row],[Agent]],Results[Reviewed Date],">="&EOMONTH(TODAY(),-3)+1,Results[Reviewed Date],"<="&EOMONTH(TODAY(),0),Results[Determination],"Founded") -> 2 | E11: =COUNTIFS(Results[Agent],Summary[[#This Row],[Agent]],Results[Reviewed Date],">="&EOMONTH(TODAY(),-3)+1,Results[Reviewed Date],"<="&EOMONTH(TODAY(),0),Results[Determination],"Partially Founded") -> 0 | F11: =COUNTIFS(Results[Agent],Summary[[#This Row],[Agent]],Results[Reviewed Date],">="&EOMONTH(TODAY(),-3)+1,Results[Reviewed Date],"<="&EOMONTH(TODAY(),0),Results[Determination],"Unfounded") -> 0 | G11: =COUNTIFS(Results[Agent],Summary[[#This Row],[Agent]],Results[Reviewed Date],">="&EOMONTH(TODAY(),-3)+1,Results[Reviewed Date],"<="&EOMONTH(TODAY(),0),Results[Determination],"Unfounded, coaching opportunities present") -> 0 | H11: =COUNTIFS(Results[Agent],Summary[[#This Row],[Agent]],Results[Reviewed Date],">="&EOMONTH(TODAY(),-3)+1,Results[Reviewed Date],"<="&EOMONTH(TODAY(),0)) -> 2 | I11: =IFERROR(Summary[[#This Row],[Total]]/Summary[[#This Row],[Total Policies]],"") -> 0.029850746
A12: Vidal Fakondo | B12: =COUNTIFS(policies[[Effective Date ]],">="&EOMONTH(TODAY(),-3)+1,policies[[Effective Date ]],"<="&EOMONTH(TODAY(),0),policies[Column3],Summary[[#This Row],[Agent]]) -> 53 | C12: Brian Henderson | D12: =COUNTIFS(Results[Agent],Summary[[#This Row],[Agent]],Results[Reviewed Date],">="&EOMONTH(TODAY(),-3)+1,Results[Reviewed Date],"<="&EOMONTH(TODAY(),0),Results[Determination],"Founded") -> 2 | E12: =COUNTIFS(Results[Agent],Summary[[#This Row],[Agent]],Results[Reviewed Date],">="&EOMONTH(TODAY(),-3)+1,Results[Reviewed Date],"<="&EOMONTH(TODAY(),0),Results[Determination],"Partially Founded") -> 0 | F12: =COUNTIFS(Results[Agent],Summary[[#This Row],[Agent]],Results[Reviewed Date],">="&EOMONTH(TODAY(),-3)+1,Results[Reviewed Date],"<="&EOMONTH(TODAY(),0),Results[Determination],"Unfounded") -> 0 | G12: =COUNTIFS(Results[Agent],Summary[[#This Row],[Agent]],Results[Reviewed Date],">="&EOMONTH(TODAY(),-3)+1,Results[Reviewed Date],"<="&EOMONTH(TODAY(),0),Results[Determination],"Unfounded, coaching opportunities present") -> 0 | H12: =COUNTIFS(Results[Agent],Summary[[#This Row],[Agent]],Results[Reviewed Date],">="&EOMONTH(TODAY(),-3)+1,Results[Reviewed Date],"<="&EOMONTH(TODAY(),0)) -> 2 | I12: =IFERROR(Summary[[#This Row],[Total]]/Summary[[#This Row],[Total Policies]],"") -> 0.037735849
A13: Gary Johnson | B13: =COUNTIFS(policies[[Effective Date ]],">="&EOMONTH(TODAY(),-3)+1,policies[[Effective Date ]],"<="&EOMONTH(TODAY(),0),policies[Column3],Summary[[#This Row],[Agent]]) -> 53 | C13: Nesia Jefferies | D13: =COUNTIFS(Results[Agent],Summary[[#This Row],[Agent]],Results[Reviewed Date],">="&EOMONTH(TODAY(),-3)+1,Results[Reviewed Date],"<="&EOMONTH(TODAY(),0),Results[Determination],"Founded") -> 1 | E13: =COUNTIFS(Results[Agent],Summary[[#This Row],[Agent]],Results[Reviewed Date],">="&EOMONTH(TODAY(),-3)+1,Results[Reviewed Date],"<="&EOMONTH(TODAY(),0),Results[Determination],"Partially Founded") -> 0 | F13: =COUNTIFS(Results[Agent],Summary[[#This Row],[Agent]],Results[Reviewed Date],">="&EOMONTH(TODAY(),-3)+1,Results[Reviewed Date],"<="&EOMONTH(TODAY(),0),Results[Determination],"Unfounded") -> 1 | G13: =COUNTIFS(Results[Agent],Summary[[#This Row],[Agent]],Results[Reviewed Date],">="&EOMONTH(TODAY(),-3)+1,Results[Reviewed Date],"<="&EOMONTH(TODAY(),0),Results[Determination],"Unfounded, coaching opportunities present") -> 0 | H13: =COUNTIFS(Results[Agent],Summary[[#This Row],[Agent]],Results[Reviewed Date],">="&EOMONTH(TODAY(),-3)+1,Results[Reviewed Date],"<="&EOMONTH(TODAY(),0)) -> 2 | I13: =IFERROR(Summary[[#This Row],[Total]]/Summary[[#This Row],[Total Policies]],"") -> 0.037735849
A14: Aleccia Wright | B14: =COUNTIFS(policies[[Effective Date ]],">="&EOMONTH(TODAY(),-3)+1,policies[[Effective Date ]],"<="&EOMONTH(TODAY(),0),policies[Column3],Summary[[#This Row],[Agent]]) -> 67 | C14: Brian Henderson | D14: =COUNTIFS(Results[Agent],Summary[[#This Row],[Agent]],Results[Reviewed Date],">="&EOMONTH(TODAY(),-3)+1,Results[Reviewed Date],"<="&EOMONTH(TODAY(),0),Results[Determination],"Founded") -> 1 | E14: =COUNTIFS(Results[Agent],Summary[[#This Row],[Agent]],Results[Reviewed Date],">="&EOMONTH(TODAY(),-3)+1,Results[Reviewed Date],"<="&EOMONTH(TODAY(),0),Results[Determination],"Partially Founded") -> 0 | F14: =COUNTIFS(Results[Agent],Summary[[#This Row],[Agent]],Results[Reviewed Date],">="&EOMONTH(TODAY(),-3)+1,Results[Reviewed Date],"<="&EOMONTH(TODAY(),0),Results[Determination],"Unfounded") -> 0 | G14: =COUNTIFS(Results[Agent],Summary[[#This Row],[Agent]],Results[Reviewed Date],">="&EOMONTH(TODAY(),-3)+1,Results[Reviewed Date],"<="&EOMONTH(TODAY(),0),Results[Determination],"Unfounded, coaching opportunities present") -> 0 | H14: =COUNTIFS(Results[Agent],Summary[[#This Row],[Agent]],Results[Reviewed Date],">="&EOMONTH(TODAY(),-3)+1,Results[Reviewed Date],"<="&EOMONTH(TODAY(),0)) -> 1 | I14: =IFERROR(Summary[[#This Row],[Total]]/Summary[[#This Row],[Total Policies]],"") -> 0.014925373
... A22: Andrea Morris | B22: =COUNTIFS(policies[[Effective Date ]],">="&EOMONTH(TODAY(),-3)+1,policies[[Effective Date ]],"<="&EOMONTH(TODAY(),0),policies[Column3],Summary[[#This Row],[Agent]]) -> 105 | C22: John Tellez | D22: =COUNTIFS(Results[Agent],Summary[[#This Row],[Agent]],Results[Reviewed Date],">="&EOMONTH(TODAY(),-3)+1,Results[Reviewed Date],"<="&EOMONTH(TODAY(),0),Results[Determination],"Founded") -> 0 | E22: =COUNTIFS(Results[Agent],Summary[[#This Row],[Agent]],Results[Reviewed Date],">="&EOMONTH(TODAY(),-3)+1,Results[Reviewed Date],"<="&EOMONTH(TODAY(),0),Results[Determination],"Partially Founded") -> 0 | F22: =COUNTIFS(Results[Agent],Summary[[#This Row],[Agent]],Results[Reviewed Date],">="&EOMONTH(TODAY(),-3)+1,Results[Reviewed Date],"<="&EOMONTH(TODAY(),0),Results[Determination],"Unfounded") -> 0 | G22: =COUNTIFS(Results[Agent],Summary[[#This Row],[Agent]],Results[Reviewed Date],">="&EOMONTH(TODAY(),-3)+1,Results[Reviewed Date],"<="&EOMONTH(TODAY(),0),Results[Determination],"Unfounded, coaching opportunities present") -> 0 | H22: =COUNTIFS(Results[Agent],Summary[[#This Row],[Agent]],Results[Reviewed Date],">="&EOMONTH(TODAY(),-3)+1,Results[Reviewed Date],"<="&EOMONTH(TODAY(),0)) -> 0 | I22: =IFERROR(Summary[[#This Row],[Total]]/Summary[[#This Row],[Total Policies]],"") -> 0
A23: Asia Vann | B23: =COUNTIFS(policies[[Effective Date ]],">="&EOMONTH(TODAY(),-3)+1,policies[[Effective Date ]],"<="&EOMONTH(TODAY(),0),policies[Column3],Summary[[#This Row],[Agent]]) -> 64 | C23: Brian Henderson | D23: =COUNTIFS(Results[Agent],Summary[[#This Row],[Agent]],Results[Reviewed Date],">="&EOMONTH(TODAY(),-3)+1,Results[Reviewed Date],"<="&EOMONTH(TODAY(),0),Results[Determination],"Founded") -> 0 | E23: =COUNTIFS(Results[Agent],Summary[[#This Row],[Agent]],Results[Reviewed Date],">="&EOMONTH(TODAY(),-3)+1,Results[Reviewed Date],"<="&EOMONTH(TODAY(),0),Results[Determination],"Partially Founded") -> 0 | F23: =COUNTIFS(Results[Agent],Summary[[#This Row],[Agent]],Results[Reviewed Date],">="&EOMONTH(TODAY(),-3)+1,Results[Reviewed Date],"<="&EOMONTH(TODAY(),0),Results[Determination],"Unfounded") -> 0 | G23: =COUNTIFS(Results[Agent],Summary[[#This Row],[Agent]],Results[Reviewed Date],">="&EOMONTH(TODAY(),-3)+1,Results[Reviewed Date],"<="&EOMONTH(TODAY(),0),Results[Determination],"Unfounded, coaching opportunities present") -> 0 | H23: =COUNTIFS(Results[Agent],Summary[[#This Row],[Agent]],Results[Reviewed Date],">="&EOMONTH(TODAY(),-3)+1,Results[Reviewed Date],"<="&EOMONTH(TODAY(),0)) -> 0
A24: Bernie Livingston | B24: =COUNTIFS(policies[[Effective Date ]],">="&EOMONTH(TODAY(),-3)+1,policies[[Effective Date ]],"<="&EOMONTH(TODAY(),0),policies[Column3],Summary[[#This Row],[Agent]]) -> 76 | C24: Brian Henderson | D24: =COUNTIFS(Results[Agent],Summary[[#This Row],[Agent]],Results[Reviewed Date],">="&EOMONTH(TODAY(),-3)+1,Results[Reviewed Date],"<="&EOMONTH(TODAY(),0),Results[Determination],"Founded") -> 0 | E24: =COUNTIFS(Results[Agent],Summary[[#This Row],[Agent]],Results[Reviewed Date],">="&EOMONTH(TODAY(),-3)+1,Results[Reviewed Date],"<="&EOMONTH(TODAY(),0),Results[Determination],"Partially Founded") -> 0 | F24: =COUNTIFS(Results[Agent],Summary[[#This Row],[Agent]],Results[Reviewed Date],">="&EOMONTH(TODAY(),-3)+1,Results[Reviewed Date],"<="&EOMONTH(TODAY(),0),Results[Determination],"Unfounded") -> 0 | G24: =COUNTIFS(Results[Agent],Summary[[#This Row],[Agent]],Results[Reviewed Date],">="&EOMONTH(TODAY(),-3)+1,Results[Reviewed Date],"<="&EOMONTH(TODAY(),0),Results[Determination],"Unfounded, coaching opportunities present") -> 0 | H24: =COUNTIFS(Results[Agent],Summary[[#This Row],[Agent]],Results[Reviewed Date],">="&EOMONTH(TODAY(),-3)+1,Results[Reviewed Date],"<="&EOMONTH(TODAY(),0)) -> 0 | I24: =IFERROR(Summary[[#This Row],[Total]]/Summary[[#This Row],[Total Policies]],"") -> 0
A25: Carlos Vintimilla | B25: =COUNTIFS(policies[[Effective Date ]],">="&EOMONTH(TODAY(),-3)+1,policies[[Effective Date ]],"<="&EOMONTH(TODAY(),0),policies[Column3],Summary[[#This Row],[Agent]]) -> 0 | C25: Training | D25: =COUNTIFS(Results[Agent],Summary[[#This Row],[Agent]],Results[Reviewed Date],">="&EOMONTH(TODAY(),-3)+1,Results[Reviewed Date],"<="&EOMONTH(TODAY(),0),Results[Determination],"Founded") -> 0 | E25: =COUNTIFS(Results[Agent],Summary[[#This Row],[Agent]],Results[Reviewed Date],">="&EOMONTH(TODAY(),-3)+1,Results[Reviewed Date],"<="&EOMONTH(TODAY(),0),Results[Determination],"Partially Founded") -> 0 | F25: =COUNTIFS(Results[Agent],Summary[[#This Row],[Agent]],Results[Reviewed Date],">="&EOMONTH(TODAY(),-3)+1,Results[Reviewed Date],"<="&EOMONTH(TODAY(),0),Results[Determination],"Unfounded") -> 0 | G25: =COUNTIFS(Results[Agent],Summary[[#This Row],[Agent]],Results[Reviewed Date],">="&EOMONTH(TODAY(),-3)+1,Results[Reviewed Date],"<="&EOMONTH(TODAY(),0),Results[Determination],"Unfounded, coaching opportunities present") -> 0 | H25: =COUNTIFS(Results[Agent],Summary[[#This Row],[Agent]],Results[Reviewed Date],">="&EOMONTH(TODAY(),-3)+1,Results[Reviewed Date],"<="&EOMONTH(TODAY(),0)) -> 0 | I25: =IFERROR(Summary[[#This Row],[Total]]/Summary[[#This Row],[Total Policies]],"")
A26: Davis Khauka | B26: =COUNTIFS(policies[[Effective Date ]],">="&EOMONTH(TODAY(),-3)+1,policies[[Effective Date ]],"<="&EOMONTH(TODAY(),0),policies[Column3],Summary[[#This Row],[Agent]]) -> 80 | C26: John Tellez | D26: =COUNTIFS(Results[Agent],Summary[[#This Row],[Agent]],Results[Reviewed Date],">="&EOMONTH(TODAY(),-3)+1,Results[Reviewed Date],"<="&EOMONTH(TODAY(),0),Results[Determination],"Founded") -> 0 | E26: =COUNTIFS(Results[Agent],Summary[[#This Row],[Agent]],Results[Reviewed Date],">="&EOMONTH(TODAY(),-3)+1,Results[Reviewed Date],"<="&EOMONTH(TODAY(),0),Results[Determination],"Partially Founded") -> 0 | F26: =COUNTIFS(Results[Agent],Summary[[#This Row],[Agent]],Results[Reviewed Date],">="&EOMONTH(TODAY(),-3)+1,Results[Reviewed Date],"<="&EOMONTH(TODAY(),0),Results[Determination],"Unfounded") -> 0 | G26: =COUNTIFS(Results[Agent],Summary[[#This Row],[Agent]],Results[Reviewed Date],">="&EOMONTH(TODAY(),-3)+1,Results[Reviewed Date],"<="&EOMONTH(TODAY(),0),Results[Determination],"Unfounded, coaching opportunities present") -> 0 | H26: =COUNTIFS(Results[Agent],Summary[[#This Row],[Agent]],Results[Reviewed Date],">="&EOMONTH(TODAY(),-3)+1,Results[Reviewed Date],"<="&EOMONTH(TODAY(),0)) -> 0 | I26: =IFERROR(Summary[[#This Row],[Total]]/Summary[[#This Row],[Total Policies]],"") -> 0
A27: Earnestein Holton | B27: =COUNTIFS(policies[[Effective Date ]],">="&EOMONTH(TODAY(),-3)+1,policies[[Effective Date ]],"<="&EOMONTH(TODAY(),0),policies[Column3],Summary[[#This Row],[Agent]]) -> 19 | C27: John Tellez | D27: =COUNTIFS(Results[Agent],Summary[[#This Row],[Agent]],Results[Reviewed Date],">="&EOMONTH(TODAY(),-3)+1,Results[Reviewed Date],"<="&EOMONTH(TODAY(),0),Results[Determination],"Founded") -> 0 | E27: =COUNTIFS(Results[Agent],Summary[[#This Row],[Agent]],Results[Reviewed Date],">="&EOMONTH(TODAY(),-3)+1,Results[Reviewed Date],"<="&EOMONTH(TODAY(),0),Results[Determination],"Partially Founded") -> 0 | F27: =COUNTIFS(Results[Agent],Summary[[#This Row],[Agent]],Results[Reviewed Date],">="&EOMONTH(TODAY(),-3)+1,Results[Reviewed Date],"<="&EOMONTH(TODAY(),0),Results[Determination],"Unfounded") -> 0 | G27: =COUNTIFS(Results[Agent],Summary[[#This Row],[Agent]],Results[Reviewed Date],">="&EOMONTH(TODAY(),-3)+1,Results[Reviewed Date],"<="&EOMONTH(TODAY(),0),Results[Determination],"Unfounded, coaching opportunities present") -> 0 | H27: =COUNTIFS(Results[Agent],Summary[[#This Row],[Agent]],Results[Reviewed Date],">="&EOMONTH(TODAY(),-3)+1,Results[Reviewed Date],"<="&EOMONTH(TODAY(),0)) -> 0 | I27: =IFERROR(Summary[[#This Row],[Total]]/Summary[[#This Row],[Total Policies]],"") -> 0
A28: Jacob Michael Luffman | B28: =COUNTIFS(policies[[Effective Date ]],">="&EOMONTH(TODAY(),-3)+1,policies[[Effective Date ]],"<="&EOMONTH(TODAY(),0),policies[Column3],Summary[[#This Row],[Agent]]) -> 0 | C28: Training | D28: =COUNTIFS(Results[Agent],Summary[[#This Row],[Agent]],Results[Reviewed Date],">="&EOMONTH(TODAY(),-3)+1,Results[Reviewed Date],"<="&EOMONTH(TODAY(),0),Results[Determination],"Founded") -> 0 | E28: =COUNTIFS(Results[Agent],Summary[[#This Row],[Agent]],Results[Reviewed Date],">="&EOMONTH(TODAY(),-3)+1,Results[Reviewed Date],"<="&EOMONTH(TODAY(),0),Results[Determination],"Partially Founded") -> 0 | F28: =COUNTIFS(Results[Agent],Summary[[#This Row],[Agent]],Results[Reviewed Date],">="&EOMONTH(TODAY(),-3)+1,Results[Reviewed Date],"<="&EOMONTH(TODAY(),0),Results[Determination],"Unfounded") -> 0 | G28: =COUNTIFS(Results[Agent],Summary[[#This Row],[Agent]],Results[Reviewed Date],">="&EOMONTH(TODAY(),-3)+1,Results[Reviewed Date],"<="&EOMONTH(TODAY(),0),Results[Determination],"Unfounded, coaching opportunities present") -> 0 | H28: =COUNTIFS(Results[Agent],Summary[[#This Row],[Agent]],Results[Reviewed Date],">="&EOMONTH(TODAY(),-3)+1,Results[Reviewed Date],"<="&EOMONTH(TODAY(),0)) -> 0 | I28: =IFERROR(Summary[[#This Row],[Total]]/Summary[[#This Row],[Total Policies]],"")
A29: Jaeden Collins | B29: =COUNTIFS(policies[[Effective Date ]],">="&EOMONTH(TODAY(),-3)+1,policies[[Effective Date ]],"<="&EOMONTH(TODAY(),0),policies[Column3],Summary[[#This Row],[Agent]]) -> 17 | C29: Brian Henderson | D29: =COUNTIFS(Results[Agent],Summary[[#This Row],[Agent]],Results[Reviewed Date],">="&EOMONTH(TODAY(),-3)+1,Results[Reviewed Date],"<="&EOMONTH(TODAY(),0),Results[Determination],"Founded") -> 0 | E29: =COUNTIFS(Results[Agent],Summary[[#This Row],[Agent]],Results[Reviewed Date],">="&EOMONTH(TODAY(),-3)+1,Results[Reviewed Date],"<="&EOMONTH(TODAY(),0),Results[Determination],"Partially Founded") -> 0 | F29: =COUNTIFS(Results[Agent],Summary[[#This Row],[Agent]],Results[Reviewed Date],">="&EOMONTH(TODAY(),-3)+1,Results[Reviewed Date],"<="&EOMONTH(TODAY(),0),Results[Determination],"Unfounded") -> 0 | G29: =COUNTIFS(Results[Agent],Summary[[#This Row],[Agent]],Results[Reviewed Date],">="&EOMONTH(TODAY(),-3)+1,Results[Reviewed Date],"<="&EOMONTH(TODAY(),0),Results[Determination],"Unfounded, coaching opportunities present") -> 0 | H29: =COUNTIFS(Results[Agent],Summary[[#This Row],[Agent]],Results[Reviewed Date],">="&EOMONTH(TODAY(),-3)+1,Results[Reviewed Date],"<="&EOMONTH(TODAY(),0)) -> 0 | I29: =IFERROR(Summary[[#This Row],[Total]]/Summary[[#This Row],[Total Policies]],"") -> 0
A30: Jasmin Johnson | B30: =COUNTIFS(policies[[Effective Date ]],">="&EOMONTH(TODAY(),-3)+1,policies[[Effective Date ]],"<="&EOMONTH(TODAY(),0),policies[Column3],Summary[[#This Row],[Agent]]) -> 28 | C30: Nesia Jefferies | D30: =COUNTIFS(Results[Agent],Summary[[#This Row],[Agent]],Results[Reviewed Date],">="&EOMONTH(TODAY(),-3)+1,Results[Reviewed Date],"<="&EOMONTH(TODAY(),0),Results[Determination],"Founded") -> 0 | E30: =COUNTIFS(Results[Agent],Summary[[#This Row],[Agent]],Results[Reviewed Date],">="&EOMONTH(TODAY(),-3)+1,Results[Reviewed Date],"<="&EOMONTH(TODAY(),0),Results[Determination],"Partially Founded") -> 0 | F30: =COUNTIFS(Results[Agent],Summary[[#This Row],[Agent]],Results[Reviewed Date],">="&EOMONTH(TODAY(),-3)+1,Results[Reviewed Date],"<="&EOMONTH(TODAY(),0),Results[Determination],"Unfounded") -> 0 | G30: =COUNTIFS(Results[Agent],Summary[[#This Row],[Agent]],Results[Reviewed Date],">="&EOMONTH(TODAY(),-3)+1,Results[Reviewed Date],"<="&EOMONTH(TODAY(),0),Results[Determination],"Unfounded, coaching opportunities present") -> 0 | H30: =COUNTIFS(Results[Agent],Summary[[#This Row],[Agent]],Results[Reviewed Date],">="&EOMONTH(TODAY(),-3)+1,Results[Reviewed Date],"<="&EOMONTH(TODAY(),0)) -> 0 | I30: =IFERROR(Summary[[#This Row],[Total]]/Summary[[#This Row],[Total Policies]],"") -> 0
A31: Jeremiah Napper | B31: =COUNTIFS(policies[[Effective Date ]],">="&EOMONTH(TODAY(),-3)+1,policies[[Effective Date ]],"<="&EOMONTH(TODAY(),0),policies[Column3],Summary[[#This Row],[Agent]]) -> 0 | C31: Training | D31: =COUNTIFS(Results[Agent],Summary[[#This Row],[Agent]],Results[Reviewed Date],">="&EOMONTH(TODAY(),-3)+1,Results[Reviewed Date],"<="&EOMONTH(TODAY(),0),Results[Determination],"Founded") -> 0 | E31: =COUNTIFS(Results[Agent],Summary[[#This Row],[Agent]],Results[Reviewed Date],">="&EOMONTH(TODAY(),-3)+1,Results[Reviewed Date],"<="&EOMONTH(TODAY(),0),Results[Determination],"Partially Founded") -> 0 | F31: =COUNTIFS(Results[Agent],Summary[[#This Row],[Agent]],Results[Reviewed Date],">="&EOMONTH(TODAY(),-3)+1,Results[Reviewed Date],"<="&EOMONTH(TODAY(),0),Results[Determination],"Unfounded") -> 0 | G31: =COUNTIFS(Results[Agent],Summary[[#This Row],[Agent]],Results[Reviewed Date],">="&EOMONTH(TODAY(),-3)+1,Results[Reviewed Date],"<="&EOMONTH(TODAY(),0),Results[Determination],"Unfounded, coaching opportunities present") -> 0 | H31: =COUNTIFS(Results[Agent],Summary[[#This Row],[Agent]],Results[Reviewed Date],">="&EOMONTH(TODAY(),-3)+1,Results[Reviewed Date],"<="&EOMONTH(TODAY(),0)) -> 0 | I31: =IFERROR(Summary[[#This Row],[Total]]/Summary[[#This Row],[Total Policies]],"")
A32: Jessica Laster | B32: =COUNTIFS(policies[[Effective Date ]],">="&EOMONTH(TODAY(),-3)+1,policies[[Effective Date ]],"<="&EOMONTH(TODAY(),0),policies[Column3],Summary[[#This Row],[Agent]]) -> 31 | C32: Nesia Jefferies | D32: =COUNTIFS(Results[Agent],Summary[[#This Row],[Agent]],Results[Reviewed Date],">="&EOMONTH(TODAY(),-3)+1,Results[Reviewed Date],"<="&EOMONTH(TODAY(),0),Results[Determination],"Founded") -> 0 | E32: =COUNTIFS(Results[Agent],Summary[[#This Row],[Agent]],Results[Reviewed Date],">="&EOMONTH(TODAY(),-3)+1,Results[Reviewed Date],"<="&EOMONTH(TODAY(),0),Results[Determination],"Partially Founded") -> 0 | F32: =COUNTIFS(Results[Agent],Summary[[#This Row],[Agent]],Results[Reviewed Date],">="&EOMONTH(TODAY(),-3)+1,Results[Reviewed Date],"<="&EOMONTH(TODAY(),0),Results[Determination],"Unfounded") -> 0 | G32: =COUNTIFS(Results[Agent],Summary[[#This Row],[Agent]],Results[Reviewed Date],">="&EOMONTH(TODAY(),-3)+1,Results[Reviewed Date],"<="&EOMONTH(TODAY(),0),Results[Determination],"Unfounded, coaching opportunities present") -> 0 | H32: =COUNTIFS(Results[Agent],Summary[[#This Row],[Agent]],Results[Reviewed Date],">="&EOMONTH(TODAY(),-3)+1,Results[Reviewed Date],"<="&EOMONTH(TODAY(),0)) -> 0 | I32: =IFERROR(Summary[[#This Row],[Total]]/Summary[[#This Row],[Total Policies]],"") -> 0
A33: Jonathan Weary | B33: =COUNTIFS(policies[[Effective Date ]],">="&EOMONTH(TODAY(),-3)+1,policies[[Effective Date ]],"<="&EOMONTH(TODAY(),0),policies[Column3],Summary[[#This Row],[Agent]]) -> 0 | C33: Training | D33: =COUNTIFS(Results[Agent],Summary[[#This Row],[Agent]],Results[Reviewed Date],">="&EOMONTH(TODAY(),-3)+1,Results[Reviewed Date],"<="&EOMONTH(TODAY(),0),Results[Determination],"Founded") -> 0 | E33: =COUNTIFS(Results[Agent],Summary[[#This Row],[Agent]],Results[Reviewed Date],">="&EOMONTH(TODAY(),-3)+1,Results[Reviewed Date],"<="&EOMONTH(TODAY(),0),Results[Determination],"Partially Founded") -> 0 | F33: =COUNTIFS(Results[Agent],Summary[[#This Row],[Agent]],Results[Reviewed Date],">="&EOMONTH(TODAY(),-3)+1,Results[Reviewed Date],"<="&EOMONTH(TODAY(),0),Results[Determination],"Unfounded") -> 0 | G33: =COUNTIFS(Results[Agent],Summary[[#This Row],[Agent]],Results[Reviewed Date],">="&EOMONTH(TODAY(),-3)+1,Results[Reviewed Date],"<="&EOMONTH(TODAY(),0),Results[Determination],"Unfounded, coaching opportunities present") -> 0 | H33: =COUNTIFS(Results[Agent],Summary[[#This Row],[Agent]],Results[Reviewed Date],">="&EOMONTH(TODAY(),-3)+1,Results[Reviewed Date],"<="&EOMONTH(TODAY(),0)) -> 0 | I33: =IFERROR(Summary[[#This Row],[Total]]/Summary[[#This Row],[Total Policies]],"")
A34: Mandi Jones | B34: =COUNTIFS(policies[[Effective Date ]],">="&EOMONTH(TODAY(),-3)+1,policies[[Effective Date ]],"<="&EOMONTH(TODAY(),0),policies[Column3],Summary[[#This Row],[Agent]]) -> 1 | C34: Training | D34: =COUNTIFS(Results[Agent],Summary[[#This Row],[Agent]],Results[Reviewed Date],">="&EOMONTH(TODAY(),-3)+1,Results[Reviewed Date],"<="&EOMONTH(TODAY(),0),Results[Determination],"Founded") -> 0 | E34: =COUNTIFS(Results[Agent],Summary[[#This Row],[Agent]],Results[Reviewed Date],">="&EOMONTH(TODAY(),-3)+1,Results[Reviewed Date],"<="&EOMONTH(TODAY(),0),Results[Determination],"Partially Founded") -> 0 | F34: =COUNTIFS(Results[Agent],Summary[[#This Row],[Agent]],Results[Reviewed Date],">="&EOMONTH(TODAY(),-3)+1,Results[Reviewed Date],"<="&EOMONTH(TODAY(),0),Results[Determination],"Unfounded") -> 0 | G34: =COUNTIFS(Results[Agent],Summary[[#This Row],[Agent]],Results[Reviewed Date],">="&EOMONTH(TODAY(),-3)+1,Results[Reviewed Date],"<="&EOMONTH(TODAY(),0),Results[Determination],"Unfounded, coaching opportunities present") -> 0 | H34: =COUNTIFS(Results[Agent],Summary[[#This Row],[Agent]],Results[Reviewed Date],">="&EOMONTH(TODAY(),-3)+1,Results[Reviewed Date],"<="&EOMONTH(TODAY(),0)) -> 0 | I34: =IFERROR(Summary[[#This Row],[Total]]/Summary[[#This Row],[Total Policies]],"") -> 0
A35: Marvonique Watts-Golden | B35: =COUNTIFS(policies[[Effective Date ]],">="&EOMONTH(TODAY(),-3)+1,policies[[Effective Date ]],"<="&EOMONTH(TODAY(),0),policies[Column3],Summary[[#This Row],[Agent]]) -> 0 | C35: Training | D35: =COUNTIFS(Results[Agent],Summary[[#This Row],[Agent]],Results[Reviewed Date],">="&EOMONTH(TODAY(),-3)+1,Results[Reviewed Date],"<="&EOMONTH(TODAY(),0),Results[Determination],"Founded") -> 0 | E35: =COUNTIFS(Results[Agent],Summary[[#This Row],[Agent]],Results[Reviewed Date],">="&EOMONTH(TODAY(),-3)+1,Results[Reviewed Date],"<="&EOMONTH(TODAY(),0),Results[Determination],"Partially Founded") -> 0 | F35: =COUNTIFS(Results[Agent],Summary[[#This Row],[Agent]],Results[Reviewed Date],">="&EOMONTH(TODAY(),-3)+1,Results[Reviewed Date],"<="&EOMONTH(TODAY(),0),Results[Determination],"Unfounded") -> 0 | G35: =COUNTIFS(Results[Agent],Summary[[#This Row],[Agent]],Results[Reviewed Date],">="&EOMONTH(TODAY(),-3)+1,Results[Reviewed Date],"<="&EOMONTH(TODAY(),0),Results[Determination],"Unfounded, coaching opportunities present") -> 0 | H35: =COUNTIFS(Results[Agent],Summary[[#This Row],[Agent]],Results[Reviewed Date],">="&EOMONTH(TODAY(),-3)+1,Results[Reviewed Date],"<="&EOMONTH(TODAY(),0)) -> 0 | I35: =IFERROR(Summary[[#This Row],[Total]]/Summary[[#This Row],[Total Policies]],"")
... A48: Zachary Copley | B48: =COUNTIFS(policies[[Effective Date ]],">="&EOMONTH(TODAY(),-3)+1,policies[[Effective Date ]],"<="&EOMONTH(TODAY(),0),policies[Column3],Summary[[#This Row],[Agent]]) -> 0 | C48: Training | D48: =COUNTIFS(Results[Agent],Summary[[#This Row],[Agent]],Results[Reviewed Date],">="&EOMONTH(TODAY(),-3)+1,Results[Reviewed Date],"<="&EOMONTH(TODAY(),0),Results[Determination],"Founded") -> 0 | E48: =COUNTIFS(Results[Agent],Summary[[#This Row],[Agent]],Results[Reviewed Date],">="&EOMONTH(TODAY(),-3)+1,Results[Reviewed Date],"<="&EOMONTH(TODAY(),0),Results[Determination],"Partially Founded") -> 0 | F48: =COUNTIFS(Results[Agent],Summary[[#This Row],[Agent]],Results[Reviewed Date],">="&EOMONTH(TODAY(),-3)+1,Results[Reviewed Date],"<="&EOMONTH(TODAY(),0),Results[Determination],"Unfounded") -> 0 | G48: =COUNTIFS(Results[Agent],Summary[[#This Row],[Agent]],Results[Reviewed Date],">="&EOMONTH(TODAY(),-3)+1,Results[Reviewed Date],"<="&EOMONTH(TODAY(),0),Results[Determination],"Unfounded, coaching opportunities present") -> 0 | H48: =COUNTIFS(Results[Agent],Summary[[#This Row],[Agent]],Results[Reviewed Date],">="&EOMONTH(TODAY(),-3)+1,Results[Reviewed Date],"<="&EOMONTH(TODAY(),0)) -> 0 | I48: =IFERROR(Summary[[#This Row],[Total]]/Summary[[#This Row],[Total Policies]],"")
A49: Total | B49: =SUBTOTAL(109,Summary[Total Policies]) -> 2035 | D49: =SUBTOTAL(109,Summary[Founded]) -> 27 | E49: =SUBTOTAL(109,Summary[Partially Founded]) -> 7 | F49: =SUBTOTAL(109,Summary[Unfounded]) -> 1 | G49: =SUBTOTAL(109,Summary[Unfounded, coaching opportunities present]) -> 6 | H49: =SUBTOTAL(109,Summary[Total]) -> 41 | I49: =Summary[[#Totals],[Total]]/SUM(Summary[Total Policies]) -> 0.02014742
A52: Source | B52: Founded | C52: Partially Founded | D52: Unfounded | E52: Unfounded, coaching opportunities present | F52: Total
A53: Carrier | B53: =COUNTIFS(Results[Complaint Source],Table6[[#This Row],[Source]],Results[Reviewed Date],">="&EOMONTH(TODAY(),-3)+1,Results[Reviewed Date],"<="&EOMONTH(TODAY(),0),Results[Determination],"Founded") -> 9 | C53: =COUNTIFS(Results[Complaint Source],Table6[[#This Row],[Source]],Results[Reviewed Date],">="&EOMONTH(TODAY(),-3)+1,Results[Reviewed Date],"<="&EOMONTH(TODAY(),0),Results[Determination],"Partially Founded") -> 3 | D53: =COUNTIFS(Results[Complaint Source],Table6[[#This Row],[Source]],Results[Reviewed Date],">="&EOMONTH(TODAY(),-3)+1,Results[Reviewed Date],"<="&EOMONTH(TODAY(),0),Results[Determination],"Unfounded") -> 1 | E53: =COUNTIFS(Results[Complaint Source],Table6[[#This Row],[Source]],Results[Reviewed Date],">="&EOMONTH(TODAY(),-3)+1,Results[Reviewed Date],"<="&EOMONTH(TODAY(),0),Results[Determination],"Unfounded, coaching opportunities present") -> 3 | F53: =SUM(Table6[[#This Row],[Founded]:[Unfounded, coaching opportunities present]]) -> 16
A54: CTM | B54: =COUNTIFS(Results[Complaint Source],Table6[[#This Row],[Source]],Results[Reviewed Date],">="&EOMONTH(TODAY(),-3)+1,Results[Reviewed Date],"<="&EOMONTH(TODAY(),0),Results[Determination],"Founded") -> 3 | C54: =COUNTIFS(Results[Complaint Source],Table6[[#This Row],[Source]],Results[Reviewed Date],">="&EOMONTH(TODAY(),-3)+1,Results[Reviewed Date],"<="&EOMONTH(TODAY(),0),Results[Determination],"Partially Founded") -> 2 | D54: =COUNTIFS(Results[Complaint Source],Table6[[#This Row],[Source]],Results[Reviewed Date],">="&EOMONTH(TODAY(),-3)+1,Results[Reviewed Date],"<="&EOMONTH(TODAY(),0),Results[Determination],"Unfounded") -> 0 | E54: =COUNTIFS(Results[Complaint Source],Table6[[#This Row],[Source]],Results[Reviewed Date],">="&EOMONTH(TODAY(),-3)+1,Results[Reviewed Date],"<="&EOMONTH(TODAY(),0),Results[Determination],"Unfounded, coaching opportunities present") -> 0 | F54: =SUM(Table6[[#This Row],[Founded]:[Unfounded, coaching opportunities present]]) -> 5
A55: Member Services | B55: =COUNTIFS(Results[Complaint Source],Table6[[#This Row],[Source]],Results[Reviewed Date],">="&EOMONTH(TODAY(),-3)+1,Results[Reviewed Date],"<="&EOMONTH(TODAY(),0),Results[Determination],"Founded") -> 17 | C55: =COUNTIFS(Results[Complaint Source],Table6[[#This Row],[Source]],Results[Reviewed Date],">="&EOMONTH(TODAY(),-3)+1,Results[Reviewed Date],"<="&EOMONTH(TODAY(),0),Results[Determination],"Partially Founded") -> 2 | D55: =COUNTIFS(Results[Complaint Source],Table6[[#This Row],[Source]],Results[Reviewed Date],">="&EOMONTH(TODAY(),-3)+1,Results[Reviewed Date],"<="&EOMONTH(TODAY(),0),Results[Determination],"Unfounded") -> 1 | E55: =COUNTIFS(Results[Complaint Source],Table6[[#This Row],[Source]],Results[Reviewed Date],">="&EOMONTH(TODAY(),-3)+1,Results[Reviewed Date],"<="&EOMONTH(TODAY(),0),Results[Determination],"Unfounded, coaching opportunities present") -> 3 | F55: =SUM(Table6[[#This Row],[Founded]:[Unfounded, coaching opportunities present]]) -> 23
A56: Total | B56: =SUBTOTAL(109,Table6[Founded]) -> 29 | C56: =SUBTOTAL(109,Table6[Partially Founded]) -> 7 | D56: =SUBTOTAL(109,Table6[Unfounded]) -> 2 | E56: =SUBTOTAL(109,Table6[Unfounded, coaching opportunities present]) -> 6 | F56: =SUBTOTAL(109,Table6[Total]) -> 44
A59: Carrier | B59: Founded | C59: Partially Founded | D59: Unfounded | E59: Unfounded, coaching opportunities present | F59: Total
A60: Gold Kidney Health Plan | B60: =COUNTIFS(Results[Name of Carrier Enrolled],Recap!A63,Results[Reviewed Date],">="&EOMONTH(TODAY(),-3)+1,Results[Reviewed Date],"<="&EOMONTH(TODAY(),0),Results[Determination],"Founded") -> 4 | C60: =COUNTIFS(Results[Name of Carrier Enrolled],[1]Recap!A52,Results[Reviewed Date],">="&EOMONTH(TODAY(),-3)+1,Results[Reviewed Date],"<="&EOMONTH(TODAY(),0),Results[Determination],"Partially Founded") -> 5 | D60: =COUNTIFS(Results[Name of Carrier Enrolled],[1]Recap!A52,Results[Reviewed Date],">="&EOMONTH(TODAY(),-3)+1,Results[Reviewed Date],"<="&EOMONTH(TODAY(),0),Results[Determination],"Unfounded") -> 1 | E60: =COUNTIFS(Results[Name of Carrier Enrolled],[1]Recap!A52,Results[Reviewed Date],">="&EOMONTH(TODAY(),-3)+1,Results[Reviewed Date],"<="&EOMONTH(TODAY(),0),Results[Determination],"Unfounded, coaching opportunities present") -> 1 | F60: =SUM(B60:E60) -> 11
A61: Zing Health | B61: =COUNTIFS(Results[Name of Carrier Enrolled],Recap!A68,Results[Reviewed Date],">="&EOMONTH(TODAY(),-3)+1,Results[Reviewed Date],"<="&EOMONTH(TODAY(),0),Results[Determination],"Founded") -> 4 | C61: =COUNTIFS(Results[Name of Carrier Enrolled],[1]Recap!A57,Results[Reviewed Date],">="&EOMONTH(TODAY(),-3)+1,Results[Reviewed Date],"<="&EOMONTH(TODAY(),0),Results[Determination],"Partially Founded") -> 0 | D61: =COUNTIFS(Results[Name of Carrier Enrolled],[1]Recap!A57,Results[Reviewed Date],">="&EOMONTH(TODAY(),-3)+1,Results[Reviewed Date],"<="&EOMONTH(TODAY(),0),Results[Determination],"Unfounded") -> 0 | E61: =COUNTIFS(Results[Name of Carrier Enrolled],[1]Recap!A57,Results[Reviewed Date],">="&EOMONTH(TODAY(),-3)+1,Results[Reviewed Date],"<="&EOMONTH(TODAY(),0),Results[Determination],"Unfounded, coaching opportunities present") -> 0 | F61: =SUM(B61:E61) -> 4
A62: Cigna | B62: =COUNTIFS(Results[Name of Carrier Enrolled],Recap!A61,Results[Reviewed Date],">="&EOMONTH(TODAY(),-3)+1,Results[Reviewed Date],"<="&EOMONTH(TODAY(),0),Results[Determination],"Founded") -> 3 | C62: =COUNTIFS(Results[Name of Carrier Enrolled],[1]Recap!A50,Results[Reviewed Date],">="&EOMONTH(TODAY(),-3)+1,Results[Reviewed Date],"<="&EOMONTH(TODAY(),0),Results[Determination],"Partially Founded") -> 0 | D62: =COUNTIFS(Results[Name of Carrier Enrolled],[1]Recap!A50,Results[Reviewed Date],">="&EOMONTH(TODAY(),-3)+1,Results[Reviewed Date],"<="&EOMONTH(TODAY(),0),Results[Determination],"Unfounded") -> 1 | E62: =COUNTIFS(Results[Name of Carrier Enrolled],[1]Recap!A50,Results[Reviewed Date],">="&EOMONTH(TODAY(),-3)+1,Results[Reviewed Date],"<="&EOMONTH(TODAY(),0),Results[Determination],"Unfounded, coaching opportunities present") -> 2 | F62: =SUM(B62:E62) -> 6
A63: Devoted Health | B63: =COUNTIFS(Results[Name of Carrier Enrolled],Recap!A62,Results[Reviewed Date],">="&EOMONTH(TODAY(),-3)+1,Results[Reviewed Date],"<="&EOMONTH(TODAY(),0),Results[Determination],"Founded") -> 1 | C63: =COUNTIFS(Results[Name of Carrier Enrolled],[1]Recap!A51,Results[Reviewed Date],">="&EOMONTH(TODAY(),-3)+1,Results[Reviewed Date],"<="&EOMONTH(TODAY(),0),Results[Determination],"Partially Founded") -> 1 | D63: =COUNTIFS(Results[Name of Carrier Enrolled],[1]Recap!A51,Results[Reviewed Date],">="&EOMONTH(TODAY(),-3)+1,Results[Reviewed Date],"<="&EOMONTH(TODAY(),0),Results[Determination],"Unfounded") -> 0 | E63: =COUNTIFS(Results[Name of Carrier Enrolled],[1]Recap!A51,Results[Reviewed Date],">="&EOMONTH(TODAY(),-3)+1,Results[Reviewed Date],"<="&EOMONTH(TODAY(),0),Results[Determination],"Unfounded, coaching opportunities present") -> 1 | F63: =SUM(B63:E63) -> 3
A64: United Healthcare | B64: =COUNTIFS(Results[Name of Carrier Enrolled],Recap!A66,Results[Reviewed Date],">="&EOMONTH(TODAY(),-3)+1,Results[Reviewed Date],"<="&EOMONTH(TODAY(),0),Results[Determination],"Founded") -> 8 | C64: =COUNTIFS(Results[Name of Carrier Enrolled],[1]Recap!A55,Results[Reviewed Date],">="&EOMONTH(TODAY(),-3)+1,Results[Reviewed Date],"<="&EOMONTH(TODAY(),0),Results[Determination],"Partially Founded") -> 0 | D64: =COUNTIFS(Results[Name of Carrier Enrolled],[1]Recap!A55,Results[Reviewed Date],">="&EOMONTH(TODAY(),-3)+1,Results[Reviewed Date],"<="&EOMONTH(TODAY(),0),Results[Determination],"Unfounded") -> 0 | E64: =COUNTIFS(Results[Name of Carrier Enrolled],[1]Recap!A55,Results[Reviewed Date],">="&EOMONTH(TODAY(),-3)+1,Results[Reviewed Date],"<="&EOMONTH(TODAY(),0),Results[Determination],"Unfounded, coaching opportunities present") -> 1 | F64: =SUM(B64:E64) -> 9
A65: WellCare | B65: =COUNTIFS(Results[Name of Carrier Enrolled],Recap!A67,Results[Reviewed Date],">="&EOMONTH(TODAY(),-3)+1,Results[Reviewed Date],"<="&EOMONTH(TODAY(),0),Results[Determination],"Founded") -> 1 | C65: =COUNTIFS(Results[Name of Carrier Enrolled],[1]Recap!A56,Results[Reviewed Date],">="&EOMONTH(TODAY(),-3)+1,Results[Reviewed Date],"<="&EOMONTH(TODAY(),0),Results[Determination],"Partially Founded") -> 1 | D65: =COUNTIFS(Results[Name of Carrier Enrolled],[1]Recap!A56,Results[Reviewed Date],">="&EOMONTH(TODAY(),-3)+1,Results[Reviewed Date],"<="&EOMONTH(TODAY(),0),Results[Determination],"Unfounded") -> 0 | E65: =COUNTIFS(Results[Name of Carrier Enrolled],[1]Recap!A56,Results[Reviewed Date],">="&EOMONTH(TODAY(),-3)+1,Results[Reviewed Date],"<="&EOMONTH(TODAY(),0),Results[Determination],"Unfounded, coaching opportunities present") -> 0 | F65: =SUM(B65:E65) -> 2
A66: Humana | B66: =COUNTIFS(Results[Name of Carrier Enrolled],Recap!A64,Results[Reviewed Date],">="&EOMONTH(TODAY(),-3)+1,Results[Reviewed Date],"<="&EOMONTH(TODAY(),0),Results[Determination],"Founded") -> 4 | C66: =COUNTIFS(Results[Name of Carrier Enrolled],[1]Recap!A53,Results[Reviewed Date],">="&EOMONTH(TODAY(),-3)+1,Results[Reviewed Date],"<="&EOMONTH(TODAY(),0),Results[Determination],"Partially Founded") -> 0 | D66: =COUNTIFS(Results[Name of Carrier Enrolled],[1]Recap!A53,Results[Reviewed Date],">="&EOMONTH(TODAY(),-3)+1,Results[Reviewed Date],"<="&EOMONTH(TODAY(),0),Results[Determination],"Unfounded") -> 0 | E66: =COUNTIFS(Results[Name of Carrier Enrolled],[1]Recap!A53,Results[Reviewed Date],">="&EOMONTH(TODAY(),-3)+1,Results[Reviewed Date],"<="&EOMONTH(TODAY(),0),Results[Determination],"Unfounded, coaching opportunities present") -> 0 | F66: =SUM(B66:E66) -> 4
A67: Member Services Call | B67: =COUNTIFS(Results[Name of Carrier Enrolled],Recap!A65,Results[Reviewed Date],">="&EOMONTH(TODAY(),-3)+1,Results[Reviewed Date],"<="&EOMONTH(TODAY(),0),Results[Determination],"Founded") -> 0 | C67: =COUNTIFS(Results[Name of Carrier Enrolled],[1]Recap!A54,Results[Reviewed Date],">="&EOMONTH(TODAY(),-3)+1,Results[Reviewed Date],"<="&EOMONTH(TODAY(),0),Results[Determination],"Partially Founded") -> 0 | D67: =COUNTIFS(Results[Name of Carrier Enrolled],[1]Recap!A54,Results[Reviewed Date],">="&EOMONTH(TODAY(),-3)+1,Results[Reviewed Date],"<="&EOMONTH(TODAY(),0),Results[Determination],"Unfounded") -> 0 | E67: =COUNTIFS(Results[Name of Carrier Enrolled],[1]Recap!A54,Results[Reviewed Date],">="&EOMONTH(TODAY(),-3)+1,Results[Reviewed Date],"<="&EOMONTH(TODAY(),0),Results[Determination],"Unfounded, coaching opportunities present") -> 1 | F67: =SUM(B67:E67) -> 1
A68: Aetna Inc. | B68: =COUNTIFS(Results[Name of Carrier Enrolled],Recap!A60,Results[Reviewed Date],">="&EOMONTH(TODAY(),-3)+1,Results[Reviewed Date],"<="&EOMONTH(TODAY(),0),Results[Determination],"Founded") -> 4 | C68: =COUNTIFS(Results[Name of Carrier Enrolled],[1]Recap!A49,Results[Reviewed Date],">="&EOMONTH(TODAY(),-3)+1,Results[Reviewed Date],"<="&EOMONTH(TODAY(),0),Results[Determination],"Partially Founded") -> 0 | D68: =COUNTIFS(Results[Name of Carrier Enrolled],[1]Recap!A49,Results[Reviewed Date],">="&EOMONTH(TODAY(),-3)+1,Results[Reviewed Date],"<="&EOMONTH(TODAY(),0),Results[Determination],"Unfounded") -> 0 | E68: =COUNTIFS(Results[Name of Carrier Enrolled],[1]Recap!A49,Results[Reviewed Date],">="&EOMONTH(TODAY(),-3)+1,Results[Reviewed Date],"<="&EOMONTH(TODAY(),0),Results[Determination],"Unfounded, coaching opportunities present") -> 0 | F68: =SUM(B68:E68) -> 4
A69: Total | B69: =SUBTOTAL(109,Table9[Founded]) -> 29 | C69: =SUBTOTAL(109,Table9[Partially Founded]) -> 7 | D69: =SUBTOTAL(109,Table9[Unfounded]) -> 2 | E69: =SUBTOTAL(109,Table9[Unfounded, coaching opportunities present]) -> 6 | F69: =SUBTOTAL(109,Table9[Total]) -> 44
A72: Allegation Topic | B72: Founded | C72: Partially Founded | D72: Unfounded | E72: Unfounded, coaching opportunities present | F72: Total
A73: Benefit Misinformation | B73: =COUNTIFS(Results[Allegation Topic],"*Benefit Misinformation*",Results[Reviewed Date],">="&EOMONTH(TODAY(),-3)+1,Results[Reviewed Date],"<="&EOMONTH(TODAY(),0),Results[Determination],"Founded") -> 15 | C73: =COUNTIFS(Results[Allegation Topic],"*Benefit Misinformation*",Results[Reviewed Date],">="&EOMONTH(TODAY(),-3)+1,Results[Reviewed Date],"<="&EOMONTH(TODAY(),0),Results[Determination],"Partially Founded") -> 4 | D73: =COUNTIFS(Results[Allegation Topic],"*Benefit Misinformation*",Results[Reviewed Date],">="&EOMONTH(TODAY(),-3)+1,Results[Reviewed Date],"<="&EOMONTH(TODAY(),0),Results[Determination],"Unfounded") -> 1 | E73: =COUNTIFS(Results[Allegation Topic],"*Benefit Misinformation*",Results[Reviewed Date],">="&EOMONTH(TODAY(),-3)+1,Results[Reviewed Date],"<="&EOMONTH(TODAY(),0),Results[Determination],"Unfounded, coaching opportunities present") -> 3 | F73: =SUM(B73:E73) -> 23
A74: Providers - Medical | B74: =COUNTIFS(Results[Allegation Topic],"*Providers - Medical*",Results[Reviewed Date],">="&EOMONTH(TODAY(),-3)+1,Results[Reviewed Date],"<="&EOMONTH(TODAY(),0),Results[Determination],"Founded") -> 14 | C74: =COUNTIFS(Results[Allegation Topic],"*Providers - Medical*",Results[Reviewed Date],">="&EOMONTH(TODAY(),-3)+1,Results[Reviewed Date],"<="&EOMONTH(TODAY(),0),Results[Determination],"Partially Founded") -> 5 | D74: =COUNTIFS(Results[Allegation Topic],"*Providers - Medical*",Results[Reviewed Date],">="&EOMONTH(TODAY(),-3)+1,Results[Reviewed Date],"<="&EOMONTH(TODAY(),0),Results[Determination],"Unfounded") -> 0 | E74: =COUNTIFS(Results[Allegation Topic],"*Providers - Medical*",Results[Reviewed Date],">="&EOMONTH(TODAY(),-3)+1,Results[Reviewed Date],"<="&EOMONTH(TODAY(),0),Results[Determination],"Unfounded, coaching opportunities present") -> 0 | F74: =SUM(B74:E74) -> 19
A75: Enrollment Consent | B75: =COUNTIFS(Results[Allegation Topic],"*Enrollment Consent*",Results[Reviewed Date],">="&EOMONTH(TODAY(),-3)+1,Results[Reviewed Date],"<="&EOMONTH(TODAY(),0),Results[Determination],"Founded") -> 6 | C75: =COUNTIFS(Results[Allegation Topic],"*Enrollment Consent*",Results[Reviewed Date],">="&EOMONTH(TODAY(),-3)+1,Results[Reviewed Date],"<="&EOMONTH(TODAY(),0),Results[Determination],"Partially Founded") -> 1 | D75: =COUNTIFS(Results[Allegation Topic],"*Enrollment Consent*",Results[Reviewed Date],">="&EOMONTH(TODAY(),-3)+1,Results[Reviewed Date],"<="&EOMONTH(TODAY(),0),Results[Determination],"Unfounded") -> 2 | E75: =COUNTIFS(Results[Allegation Topic],"*Enrollment Consent*",Results[Reviewed Date],">="&EOMONTH(TODAY(),-3)+1,Results[Reviewed Date],"<="&EOMONTH(TODAY(),0),Results[Determination],"Unfounded, coaching opportunities present") -> 3 | F75: =SUM(B75:E75) -> 12
A76: Providers - Ancillary | B76: =COUNTIFS(Results[Allegation Topic],"*Providers - Ancillary*",Results[Reviewed Date],">="&EOMONTH(TODAY(),-3)+1,Results[Reviewed Date],"<="&EOMONTH(TODAY(),0),Results[Determination],"Founded") -> 5 | C76: =COUNTIFS(Results[Allegation Topic],"*Providers - Ancillary*",Results[Reviewed Date],">="&EOMONTH(TODAY(),-3)+1,Results[Reviewed Date],"<="&EOMONTH(TODAY(),0),Results[Determination],"Partially Founded") -> 3 | D76: =COUNTIFS(Results[Allegation Topic],"*Providers - Ancillary*",Results[Reviewed Date],">="&EOMONTH(TODAY(),-3)+1,Results[Reviewed Date],"<="&EOMONTH(TODAY(),0),Results[Determination],"Unfounded") -> 0 | E76: =COUNTIFS(Results[Allegation Topic],"*Providers - Ancillary*",Results[Reviewed Date],">="&EOMONTH(TODAY(),-3)+1,Results[Reviewed Date],"<="&EOMONTH(TODAY(),0),Results[Determination],"Unfounded, coaching opportunities present") -> 1 | F76: =SUM(B76:E76) -> 9
A77: Drugs - Cost or Coverage | B77: =COUNTIFS(Results[Allegation Topic],"*Drugs - Cost or Coverage*",Results[Reviewed Date],">="&EOMONTH(TODAY(),-3)+1,Results[Reviewed Date],"<="&EOMONTH(TODAY(),0),Results[Determination],"Founded") -> 8 | C77: =COUNTIFS(Results[Allegation Topic],"*Drugs - Cost or Coverage*",Results[Reviewed Date],">="&EOMONTH(TODAY(),-3)+1,Results[Reviewed Date],"<="&EOMONTH(TODAY(),0),Results[Determination],"Partially Founded") -> 0 | D77: =COUNTIFS(Results[Allegation Topic],"*Drugs - Cost or Coverage*",Results[Reviewed Date],">="&EOMONTH(TODAY(),-3)+1,Results[Reviewed Date],"<="&EOMONTH(TODAY(),0),Results[Determination],"Unfounded") -> 0 | E77: =COUNTIFS(Results[Allegation Topic],"*Drugs - Cost or Coverage*",Results[Reviewed Date],">="&EOMONTH(TODAY(),-3)+1,Results[Reviewed Date],"<="&EOMONTH(TODAY(),0),Results[Determination],"Unfounded, coaching opportunities present") -> 0 | F77: =SUM(B77:E77) -> 8
A78: Agent Behavior | B78: =COUNTIFS(Results[Allegation Topic],"*Agent Behavior*",Results[Reviewed Date],">="&EOMONTH(TODAY(),-3)+1,Results[Reviewed Date],"<="&EOMONTH(TODAY(),0),Results[Determination],"Founded") -> 3 | C78: =COUNTIFS(Results[Allegation Topic],"*Agent Behavior*",Results[Reviewed Date],">="&EOMONTH(TODAY(),-3)+1,Results[Reviewed Date],"<="&EOMONTH(TODAY(),0),Results[Determination],"Partially Founded") -> 1 | D78: =COUNTIFS(Results[Allegation Topic],"*Agent Behavior*",Results[Reviewed Date],">="&EOMONTH(TODAY(),-3)+1,Results[Reviewed Date],"<="&EOMONTH(TODAY(),0),Results[Determination],"Unfounded") -> 1 | E78: =COUNTIFS(Results[Allegation Topic],"*Agent Behavior*",Results[Reviewed Date],">="&EOMONTH(TODAY(),-3)+1,Results[Reviewed Date],"<="&EOMONTH(TODAY(),0),Results[Determination],"Unfounded, coaching opportunities present") -> 0 | F78: =SUM(B78:E78) -> 5
A79: SSBCI Benefits | B79: =COUNTIFS(Results[Allegation Topic],"*SSBCI Benefits*",Results[Reviewed Date],">="&EOMONTH(TODAY(),-3)+1,Results[Reviewed Date],"<="&EOMONTH(TODAY(),0),Results[Determination],"Founded") -> 3 | C79: =COUNTIFS(Results[Allegation Topic],"*SSBCI Benefits*",Results[Reviewed Date],">="&EOMONTH(TODAY(),-3)+1,Results[Reviewed Date],"<="&EOMONTH(TODAY(),0),Results[Determination],"Partially Founded") -> 1 | D79: =COUNTIFS(Results[Allegation Topic],"*SSBCI Benefits*",Results[Reviewed Date],">="&EOMONTH(TODAY(),-3)+1,Results[Reviewed Date],"<="&EOMONTH(TODAY(),0),Results[Determination],"Unfounded") -> 0 | E79: =COUNTIFS(Results[Allegation Topic],"*SSBCI Benefits*",Results[Reviewed Date],">="&EOMONTH(TODAY(),-3)+1,Results[Reviewed Date],"<="&EOMONTH(TODAY(),0),Results[Determination],"Unfounded, coaching opportunities present") -> 1 | F79: =SUM(B79:E79) -> 5
A80: Medicaid Coverage | B80: =COUNTIFS(Results[Allegation Topic],"*Medicaid Coverage*",Results[Reviewed Date],">="&EOMONTH(TODAY(),-3)+1,Results[Reviewed Date],"<="&EOMONTH(TODAY(),0),Results[Determination],"Founded") -> 1 | C80: =COUNTIFS(Results[Allegation Topic],"*Medicaid Coverage*",Results[Reviewed Date],">="&EOMONTH(TODAY(),-3)+1,Results[Reviewed Date],"<="&EOMONTH(TODAY(),0),Results[Determination],"Partially Founded") -> 1 | D80: =COUNTIFS(Results[Allegation Topic],"*Medicaid Coverage*",Results[Reviewed Date],">="&EOMONTH(TODAY(),-3)+1,Results[Reviewed Date],"<="&EOMONTH(TODAY(),0),Results[Determination],"Unfounded") -> 0 | E80: =COUNTIFS(Results[Allegation Topic],"*Medicaid Coverage*",Results[Reviewed Date],">="&EOMONTH(TODAY(),-3)+1,Results[Reviewed Date],"<="&EOMONTH(TODAY(),0),Results[Determination],"Unfounded, coaching opportunities present") -> 1 | F80: =SUM(B80:E80) -> 3
A81: Plan Eligibility | B81: =COUNTIFS(Results[Allegation Topic],"*Plan Eligibility*",Results[Reviewed Date],">="&EOMONTH(TODAY(),-3)+1,Results[Reviewed Date],"<="&EOMONTH(TODAY(),0),Results[Determination],"Founded") -> 1 | C81: =COUNTIFS(Results[Allegation Topic],"*Plan Eligibility*",Results[Reviewed Date],">="&EOMONTH(TODAY(),-3)+1,Results[Reviewed Date],"<="&EOMONTH(TODAY(),0),Results[Determination],"Partially Founded") -> 0 | D81: =COUNTIFS(Results[Allegation Topic],"*Plan Eligibility*",Results[Reviewed Date],">="&EOMONTH(TODAY(),-3)+1,Results[Reviewed Date],"<="&EOMONTH(TODAY(),0),Results[Determination],"Unfounded") -> 0 | E81: =COUNTIFS(Results[Allegation Topic],"*Plan Eligibility*",Results[Reviewed Date],">="&EOMONTH(TODAY(),-3)+1,Results[Reviewed Date],"<="&EOMONTH(TODAY(),0),Results[Determination],"Unfounded, coaching opportunities present") -> 0 | F81: =SUM(B81:E81) -> 1
A82: Total | B82: =SUBTOTAL(109,Table13[Founded]) -> 56 | C82: =SUBTOTAL(109,Table13[Partially Founded]) -> 16 | D82: =SUBTOTAL(109,Table13[Unfounded]) -> 4 | E82: =SUBTOTAL(109,Table13[Unfounded, coaching opportunities present]) -> 9 | F82: =SUBTOTAL(109,Table13[Total]) -> 85
A85: AOI | B85: Founded | C85: Partially Founded | D85: Unfounded | E85: Unfounded, coaching opportunities present | F85: Total
A86: Benefit Misinformation | B86: =COUNTIFS(Results[AOIs],"*Benefit Misinformation*",Results[Reviewed Date],">="&EOMONTH(TODAY(),-3)+1,Results[Reviewed Date],"<="&EOMONTH(TODAY(),0),Results[Determination],"Founded") -> 26 | C86: =COUNTIFS(Results[AOIs],"*Benefit Misinformation*",Results[Reviewed Date],">="&EOMONTH(TODAY(),-3)+1,Results[Reviewed Date],"<="&EOMONTH(TODAY(),0),Results[Determination],"Partially Founded") -> 6 | D86: =COUNTIFS(Results[AOIs],"*Benefit Misinformation*",Results[Reviewed Date],">="&EOMONTH(TODAY(),-3)+1,Results[Reviewed Date],"<="&EOMONTH(TODAY(),0),Results[Determination],"Unfounded") -> 0 | E86: =COUNTIFS(Results[AOIs],"*Benefit Misinformation*",Results[Reviewed Date],">="&EOMONTH(TODAY(),-3)+1,Results[Reviewed Date],"<="&EOMONTH(TODAY(),0),Results[Determination],"Unfounded, coaching opportunities present") -> 6 | F86: =SUM(B86:E86) -> 38
A87: Providers - Medical | B87: =COUNTIFS(Results[AOIs],"*Providers - Medical*",Results[Reviewed Date],">="&EOMONTH(TODAY(),-3)+1,Results[Reviewed Date],"<="&EOMONTH(TODAY(),0),Results[Determination],"Founded") -> 15 | C87: =COUNTIFS(Results[AOIs],"*Providers - Medical*",Results[Reviewed Date],">="&EOMONTH(TODAY(),-3)+1,Results[Reviewed Date],"<="&EOMONTH(TODAY(),0),Results[Determination],"Partially Founded") -> 6 | D87: =COUNTIFS(Results[AOIs],"*Providers - Medical*",Results[Reviewed Date],">="&EOMONTH(TODAY(),-3)+1,Results[Reviewed Date],"<="&EOMONTH(TODAY(),0),Results[Determination],"Unfounded") -> 1 | E87: =COUNTIFS(Results[AOIs],"*Providers - Medical*",Results[Reviewed Date],">="&EOMONTH(TODAY(),-3)+1,Results[Reviewed Date],"<="&EOMONTH(TODAY(),0),Results[Determination],"Unfounded, coaching opportunities present") -> 0 | F87: =SUM(B87:E87) -> 22
A88: Drugs - Cost or Coverage | B88: =COUNTIFS(Results[AOIs],"*Drugs - Cost or Coverage*",Results[Reviewed Date],">="&EOMONTH(TODAY(),-3)+1,Results[Reviewed Date],"<="&EOMONTH(TODAY(),0),Results[Determination],"Founded") -> 14 | C88: =COUNTIFS(Results[AOIs],"*Drugs - Cost or Coverage*",Results[Reviewed Date],">="&EOMONTH(TODAY(),-3)+1,Results[Reviewed Date],"<="&EOMONTH(TODAY(),0),Results[Determination],"Partially Founded") -> 3 | D88: =COUNTIFS(Results[AOIs],"*Drugs - Cost or Coverage*",Results[Reviewed Date],">="&EOMONTH(TODAY(),-3)+1,Results[Reviewed Date],"<="&EOMONTH(TODAY(),0),Results[Determination],"Unfounded") -> 0 | E88: =COUNTIFS(Results[AOIs],"*Drugs - Cost or Coverage*",Results[Reviewed Date],">="&EOMONTH(TODAY(),-3)+1,Results[Reviewed Date],"<="&EOMONTH(TODAY(),0),Results[Determination],"Unfounded, coaching opportunities present") -> 4 | F88: =SUM(B88:E88) -> 21
A89: Providers - Ancillary | B89: =COUNTIFS(Results[AOIs],"*Providers - Ancillary*",Results[Reviewed Date],">="&EOMONTH(TODAY(),-3)+1,Results[Reviewed Date],"<="&EOMONTH(TODAY(),0),Results[Determination],"Founded") -> 14 | C89: =COUNTIFS(Results[AOIs],"*Providers - Ancillary*",Results[Reviewed Date],">="&EOMONTH(TODAY(),-3)+1,Results[Reviewed Date],"<="&EOMONTH(TODAY(),0),Results[Determination],"Partially Founded") -> 4 | D89: =COUNTIFS(Results[AOIs],"*Providers - Ancillary*",Results[Reviewed Date],">="&EOMONTH(TODAY(),-3)+1,Results[Reviewed Date],"<="&EOMONTH(TODAY(),0),Results[Determination],"Unfounded") -> 0 | E89: =COUNTIFS(Results[AOIs],"*Providers - Ancillary*",Results[Reviewed Date],">="&EOMONTH(TODAY(),-3)+1,Results[Reviewed Date],"<="&EOMONTH(TODAY(),0),Results[Determination],"Unfounded, coaching opportunities present") -> 1 | F89: =SUM(B89:E89) -> 19
A90: Enrollment Consent | B90: =COUNTIFS(Results[AOIs],"*Enrollment Consent*",Results[Reviewed Date],">="&EOMONTH(TODAY(),-3)+1,Results[Reviewed Date],"<="&EOMONTH(TODAY(),0),Results[Determination],"Founded") -> 7 | C90: =COUNTIFS(Results[AOIs],"*Enrollment Consent*",Results[Reviewed Date],">="&EOMONTH(TODAY(),-3)+1,Results[Reviewed Date],"<="&EOMONTH(TODAY(),0),Results[Determination],"Partially Founded") -> 1 | D90: =COUNTIFS(Results[AOIs],"*Enrollment Consent*",Results[Reviewed Date],">="&EOMONTH(TODAY(),-3)+1,Results[Reviewed Date],"<="&EOMONTH(TODAY(),0),Results[Determination],"Unfounded") -> 2 | E90: =COUNTIFS(Results[AOIs],"*Enrollment Consent*",Results[Reviewed Date],">="&EOMONTH(TODAY(),-3)+1,Results[Reviewed Date],"<="&EOMONTH(TODAY(),0),Results[Determination],"Unfounded, coaching opportunities present") -> 4 | F90: =SUM(B90:E90) -> 14
A91: SSBCI Benefits | B91: =COUNTIFS(Results[AOIs],"*SSBCI Benefits*",Results[Reviewed Date],">="&EOMONTH(TODAY(),-3)+1,Results[Reviewed Date],"<="&EOMONTH(TODAY(),0),Results[Determination],"Founded") -> 5 | C91: =COUNTIFS(Results[AOIs],"*SSBCI Benefits*",Results[Reviewed Date],">="&EOMONTH(TODAY(),-3)+1,Results[Reviewed Date],"<="&EOMONTH(TODAY(),0),Results[Determination],"Partially Founded") -> 3 | D91: =COUNTIFS(Results[AOIs],"*SSBCI Benefits*",Results[Reviewed Date],">="&EOMONTH(TODAY(),-3)+1,Results[Reviewed Date],"<="&EOMONTH(TODAY(),0),Results[Determination],"Unfounded") -> 0 | E91: =COUNTIFS(Results[AOIs],"*SSBCI Benefits*",Results[Reviewed Date],">="&EOMONTH(TODAY(),-3)+1,Results[Reviewed Date],"<="&EOMONTH(TODAY(),0),Results[Determination],"Unfounded, coaching opportunities present") -> 3 | F91: =SUM(B91:E91) -> 11
A92: Agent Behavior | B92: =COUNTIFS(Results[AOIs],"*Agent Behavior*",Results[Reviewed Date],">="&EOMONTH(TODAY(),-3)+1,Results[Reviewed Date],"<="&EOMONTH(TODAY(),0),Results[Determination],"Founded") -> 4 | C92: =COUNTIFS(Results[AOIs],"*Agent Behavior*",Results[Reviewed Date],">="&EOMONTH(TODAY(),-3)+1,Results[Reviewed Date],"<="&EOMONTH(TODAY(),0),Results[Determination],"Partially Founded") -> 0 | D92: =COUNTIFS(Results[AOIs],"*Agent Behavior*",Results[Reviewed Date],">="&EOMONTH(TODAY(),-3)+1,Results[Reviewed Date],"<="&EOMONTH(TODAY(),0),Results[Determination],"Unfounded") -> 0 | E92: =COUNTIFS(Results[AOIs],"*Agent Behavior*",Results[Reviewed Date],">="&EOMONTH(TODAY(),-3)+1,Results[Reviewed Date],"<="&EOMONTH(TODAY(),0),Results[Determination],"Unfounded, coaching opportunities present") -> 2 | F92: =SUM(B92:E92) -> 6
A93: Medicaid Coverage | B93: =COUNTIFS(Results[AOIs],"*Medicaid Coverage*",Results[Reviewed Date],">="&EOMONTH(TODAY(),-3)+1,Results[Reviewed Date],"<="&EOMONTH(TODAY(),0),Results[Determination],"Founded") -> 4 | C93: =COUNTIFS(Results[AOIs],"*Medicaid Coverage*",Results[Reviewed Date],">="&EOMONTH(TODAY(),-3)+1,Results[Reviewed Date],"<="&EOMONTH(TODAY(),0),Results[Determination],"Partially Founded") -> 1 | D93: =COUNTIFS(Results[AOIs],"*Medicaid Coverage*",Results[Reviewed Date],">="&EOMONTH(TODAY(),-3)+1,Results[Reviewed Date],"<="&EOMONTH(TODAY(),0),Results[Determination],"Unfounded") -> 0 | E93: =COUNTIFS(Results[AOIs],"*Medicaid Coverage*",Results[Reviewed Date],">="&EOMONTH(TODAY(),-3)+1,Results[Reviewed Date],"<="&EOMONTH(TODAY(),0),Results[Determination],"Unfounded, coaching opportunities present") -> 1 | F93: =SUM(B93:E93) -> 6
A94: Plan Eligibility | B94: =COUNTIFS(Results[AOIs],"*Plan Eligibility*",Results[Reviewed Date],">="&EOMONTH(TODAY(),-3)+1,Results[Reviewed Date],"<="&EOMONTH(TODAY(),0),Results[Determination],"Founded") -> 1 | C94: =COUNTIFS(Results[AOIs],"*Plan Eligibility*",Results[Reviewed Date],">="&EOMONTH(TODAY(),-3)+1,Results[Reviewed Date],"<="&EOMONTH(TODAY(),0),Results[Determination],"Partially Founded") -> 2 | D94: =COUNTIFS(Results[AOIs],"*Plan Eligibility*",Results[Reviewed Date],">="&EOMONTH(TODAY(),-3)+1,Results[Reviewed Date],"<="&EOMONTH(TODAY(),0),Results[Determination],"Unfounded") -> 0 | E94: =COUNTIFS(Results[AOIs],"*Plan Eligibility*",Results[Reviewed Date],">="&EOMONTH(TODAY(),-3)+1,Results[Reviewed Date],"<="&EOMONTH(TODAY(),0),Results[Determination],"Unfounded, coaching opportunities present") -> 0 | F94: =SUM(B94:E94) -> 3
A95: Total | B95: =SUBTOTAL(109,Table14[Founded]) -> 90 | C95: =SUBTOTAL(109,Table14[Partially Founded]) -> 26 | D95: =SUBTOTAL(109,Table14[Unfounded]) -> 3 | E95: =SUBTOTAL(109,Table14[Unfounded, coaching opportunities present]) -> 21 | F95: =SUBTOTAL(109,Table14[Total]) -> 140

Sheet Results
A1: Agent | B1: Manager | C1: AMS Link | D1: Application Date | E1: Complaint Date | F1: Due Date | G1: Reviewed Date | H1: Complaint Source | I1: Name of Carrier Enrolled | J1: Allegations | K1: Allegation Topic | L1: Determination | M1: AOIs | N1: Rationale | O1: Summary Link | P1: Coached | Q1: Date
A2: Christina Nguyen | B2: Nesia Jefferies | C2: https://app.agencybloc.com/individuals/72332476/detail | D2: 45992 | E2: 46035 | G2: 46048.428 | H2: Member Services | I2: Aetna Inc. | J2: The member states that they were misled about the food card. They state that they were that they would be getting $210. | K2: •SSBCI Benefits •Benefit Misinformation | L2: Founded | M2: •SSBCI Benefits •Benefit Misinformation •Drugs - Cost or Coverage | N2: Christina initially quotes the OTC benefit correctly. However, at approximately 48:01 into the call, she tells the member that there is actually a “bonus that they are adding on” of $30, which brings the amount to $210. That additional $30 is only available if the member uses a primary care provider that Aetna designates as a “High Value Provider (HVP)”. When the member asks what the additional $30 is from, Christina again repeated that it is a “bonus added on”. Additionally, it is never discussed on the call that the member would need to verify their chronic condition with Aetna to be eligible to use the Extra Supports wallet. Coaching: Christina tells the member that they currently have a supplement plan. This is likely because they are only showing a PDP in Marx. They would have been enrolled in a PDP because they have LIS. In most cases, it is illegal to sell a Supplement plan to someone who has Medicaid. Christina seems to have supplement and PDPs interchanged. | O2: https://mypolicypoint.sharepoint.com/:w:/r/sites/PolicyPointSalesCenter/Shared%20Documents/Member%20Services%20Call%20Flows,%20SOPs,%20and%20docs/Performance/Complaint%20Tracking/CNguyen%2012.01.2025.docx?d=wffea6c23cc3f4fc989aeb54c2c3ff3e5&csf=1&web=1&e=El3dEN
A3: Sandra Stillwell | B3: JT Tellez | C3: https://app.agencybloc.com/individuals/72308257/detail | D3: 45990 | E3: 46045 | G3: 46048.643 | H3: Member Services | I3: Cigna | J3: Member states that they were not told that they would have to pay a deductible for their Mounjaro. | K3: •Drugs - Cost or Coverage | L3: Founded | M3: •Drugs - Cost or Coverage •Benefit Misinformation | N3: At approximately 35:19 into the call, Sandra begins to go over the drug costs. The call was breaking up and the member asked her to repeat herself. Sandra tells the member “drug deductible, tier 1 and tier 2…” and the call cuts in and out. She does say something along the lines of “brand 615” but it is hard to hear on the recording. The member again states that she cannot hear or understand Sandra. Sandra does not repeat any previous information or ask the member what the last thing she heard or understood. Sandra tells the member at approximately 36:40 that she won’t pay more than $47 dollars for her injection. Also, it appears that Sandra seems to think that this is an insulin. Additionally, Sandra sells the plan on a formulary exception for the two drugs that were not on the formulary. We should never sell a plan based on a formulary exception as we cannot guarantee coverage and it sets the incorrect expectation. | O3: https://mypolicypoint.sharepoint.com/:w:/r/sites/PolicyPointSalesCenter/Shared%20Documents/Member%20Services%20Call%20Flows,%20SOPs,%20and%20docs/Performance/Complaint%20Tracking/SStillwell%2011.29.2025.docx?d=w396e9903ad0d4f2683c45da351c5f699&csf=1&web=1&e=ORGHNK
A4: Anthony Boyle | B4: JT Tellez | C4: https://app.agencybloc.com/individuals/71888252/detail | D4: 45968 | E4: 46049 | G4: 46055.653 | H4: Member Services | I4: Humana | J4: Member was under the impression that he would be getting a grocery allowance and that he was qualified for it. | K4: •SSBCI Benefits •Benefit Misinformation | L4: Partially Founded | M4: •SSBCI Benefits •Benefit Misinformation | N4: Anthony ultimately explained to the member what the food card was and what the qualifications are for them. Anthony was off process for much of this call. He opened the call by telling the member “What I'm going to do today is to make sure that you're receiving all the benefits that you are entitled to as a Medicare beneficiary. What that means is seeing about increases in money back on your Social Security. We're making sure that you have the highest food card available in your area that accepts your doctors, hospitals, and drugs, okay?” This improperly sets expectations in the beginning of the call. While Anthony does ultimately do the QA checklist on the plan he enrolled, he presented benefits from three separate plans in this call all at once. He pitched one plan, the member asked questions, and then he gives benefits for two additional plans. He references a plan that gives a giveback as “this plan”, without clarifying which plan he was referring to. This led to some confusion with the member. | O4: https://mypolicypoint-my.sharepoint.com/:w:/r/personal/mthomas_mypolicypoint_com/Documents/Performance%20Tracking/Complaint%20Tracking/ABoyle%2011.07.2025.docx?d=wac80ebfac4164e0e8c9f2874011f0ec1&csf=1&web=1&e=0ZJPHG
A5: Victor Filimonchuk | B5: John St. Fleurant | C5: https://app.agencybloc.com/individuals/73086139/detail | D5: 46029 | E5: 46050 | G5: 46058.661 | H5: Member Services | I5: Gold Kidney Health Plan | J5: The member’s daughter states that she has POA for the member and that the member should not have been allowed to enroll. | K5: •Plan Eligibility •Enrollment Consent | L5: Partially Founded | M5: •Plan Eligibility •Enrollment Consent •Providers - Ancillary •Drugs - Cost or Coverage •Benefit Misinformation | N5: While the member did not indicate that her daughter was POA, she did give indication that another party may provide assistance. On the initial call, Vic asks the member if she makes her own healthcare decisions. She responds “Somewhat”. When Vic probes further, he asks “Do you have someone who is a legal power of attorney who makes these decisions for you?” The member responds with “I can make the decision, but my husband usually, he’s usually there and he’ll tell me ‘yes’ or ‘no’.” Vic then asks if the husband is available and when told no, continues with the process. On the initial call, Vic discusses the member’s current plan. He tells the member that “..in looking at your current level of coverages you you basically have basic coverage meaning exam cleanings x-ray and fluoride treatment it's kind of a basic basic plan as far as coverages are concerned.” This is incorrect. The member’s UHC plan covers both routine and comprehensive dental with a $0 copay. Additionally, there is no benefit maximum on the member’s current plan for these services. This misinformation is repeated at least two other times on this call. On the second call, when Vic is pitching the plan, he states “your doctors is in the plan, your scripts are in the plan.” Vic should have specified the doctor’s name, as he was not able to find one of the providers. Additionally, When Vic was going over prescription drug costs, he did not go through the member’s drugs and let them know about the tiers, quantity limits, or step therapy. Vic refers to an urgent care as a “mini hospital”, which is misleading and inaccurate language. Vic quoted the vision benefit as “$200 for routine eyewear, including lenses, frames, and contact lenses”. The benefit is $200 for lenses and frames and $115 for contact lenses. | O5: https://mypolicypoint-my.sharepoint.com/:w:/r/personal/mthomas_mypolicypoint_com/Documents/Performance%20Tracking/Complaint%20Tracking/VFilimonchuk%2001.07.2026.docx?d=wc70b7eba4d4d48cc910471ffa1e8b941&csf=1&web=1&e=aHWMuV
A6: Tasia Clark | B6: Nesia Jefferies | C6: https://app.agencybloc.com/individuals/73450699/detail | D6: 46043 | E6: 46057 | G6: 46059.676 | H6: Member Services | I6: Devoted Health | J6: The member states that she was not told about the qualifications for the SSBCI benefit. | K6: •SSBCI Benefits •Benefit Misinformation | L6: Founded | M6: •SSBCI Benefits •Providers - Ancillary •Benefit Misinformation | N6: When Tasia asked the member about chronic conditions, the member states “No, I am as healthy as a horse”. When she asked the member about the primary care doctor or specialists, the member indicates that they do not see any doctors. The member also indicates that they do not take any prescriptions. These should have all been flags that the member does not have any current chronic conditions. When Tasia pitches the plan, she calls out that the member states that she is healthy and then pitches the SSBCI benefit. Additionally, in pitching the plan, the Tasia states that the proposed plan increases the dental. However, the member’s plan does not have a maximum benefit limit and the Devoted has a maximum benefit of $2000. | O6: https://mypolicypoint-my.sharepoint.com/:w:/r/personal/mthomas_mypolicypoint_com/Documents/Performance%20Tracking/Complaint%20Tracking/TClark%2001.21.2026.docx?d=w52b0da9210c84b799fe21d66907dd8db&csf=1&web=1&e=F920cI
A7: Kylie DeMarino | B7: JT Tellez | C7: https://app.agencybloc.com/individuals/73086180/detail | D7: 46029 | E7: 46050 | G7: 46063.496 | H7: Member Services | I7: Devoted Health | J7: Member states that they were unaware that they were enrolling in a new plan, did not agree, and did not want to change. | K7: •Enrollment Consent | L7: Unfounded | M7: •Enrollment Consent | N7: In listening to this call, the member indicated that they make their own healthcare decisions when asked. The member appeared to be lucid and actively engaged in the call throughout its entirety. Kylie completed the process compliantly and got the necessary agreements. | O7: https://mypolicypoint-my.sharepoint.com/:w:/r/personal/mthomas_mypolicypoint_com/Documents/Performance%20Tracking/Complaint%20Tracking/KDeMarino%2001.07.2026.docx?d=w7ce1fe0d067f4e54b55c31f0b0bd9ea4&csf=1&web=1&e=5ADbti
A8: Duane Kipp | B8: Nesia Jefferies | C8: https://app.agencybloc.com/individuals/72075385/detail | D8: 45980 | E8: 46059 | G8: 46064.49 | H8: Member Services | I8: United Healthcare | J8: The member indicated that they had three brain tumors and does not remember the enrollment. | K8: •Plan Eligibility •Enrollment Consent | L8: Founded | M8: •Plan Eligibility •Enrollment Consent •Providers - Medical | N8: In listening to the two calls that comprised this enrollment, there were more than 15 instances where the member mentioned memory loss, inability to understand, or confusion. While the member did not indicate that they had a POA these instances call into question the member’s capacity to understand and consent to enrollment compliantly. At approximately 50:26 into the second call, for example, the member states “My brain isn’t letting me remember things right now.” At approximately 1:01:28 into the second call when Duane asks the member if they understand the benefits prior to starting the application, she responds “I can’t remember them because of those tumors. But I’m sure it’s good.” During the disclaimers, she states “I’m I’m kind of getting confused a little bit.” After Duane had completed the enrollment, the member states “I’ll look at UnitedHealthcare, and I’ll figure out which one I want” which is an indicator that she did not understand that she had been enrolled. Throughout the call, there were additional indicators that the member was not understanding or in a capacity to complete the enrollment compliantly. After the first call dropped and Duane called her back immediately, she stated she had no idea what he was talking about. At approximately 1:03:50 on the second call, the member was unable to answer if Louise was her middle name or part of her first name. At approximately 1:10:14 into the second call, she states, “I’m going to get hollered at by my son” and at 1:10:26 goes on to say “He’s very protective because he knows that I’ve been through, and he knows I don’t understand a lot of this stuff.” At approximately 1:03:50 into the second call, the member was unable to answer if Louise was her middle name or part of her first name. After Duane had completed the enrollment, the member states “I’ll look at UnitedHealthcare, and I’ll figure out which one I want” which is an indicator that she did not understand that she had been enrolled. Additionally, when Duane pitched this plan he told the member that her doctor, Dr. Hundley, was in-network. I am not showing this provider to be in-network on Sunfire or on the carrier’s portal. There are also concerns about rapid disenrollment on this call. At approximately 1:34:16 on the second call the member asks, “Let’s say I get all the information and dI read it and then I change my mind. I don’t want to do it”. Duane explains to her to call him at that time, rather than reaffirm the plan benefits. The member asks again at 1:50:27 “If I go over this and I decide to change my mind, will I be free?”. Duane again tells her to call him. At 1:51:06 into the call, Duane tells the member “There is what’s called OEP. So, you’re able to update the policies then as well. It gives you a one-chance redo when you come through annual enrollment. So, that is an option, okay?”. | O8: https://mypolicypoint-my.sharepoint.com/:w:/r/personal/mthomas_mypolicypoint_com/Documents/Performance%20Tracking/Complaint%20Tracking/DKipp%2011.19.2025.docx?d=wfd2c46ce9d444e0188a9cf5d5c388137&csf=1&web=1&e=S6sitM
A9: Lauren Wyke | B9: Michelle Thomas | C9: https://app.agencybloc.com/individuals/72084054/detail | D9: 46050 | E9: 46050 | G9: 46064.693 | H9: Member Services | I9: Gold Kidney Health Plan | J9: Member states that Lauren’s behavior towards the Gold Kidney Member Services team was inappropriate. | K9: •Agent Behavior | L9: Unfounded | M9: •Agent Behavior | N9: Lauren called Gold Kidney with the member on the line to discuss multiple concerns. She asked the Gold Kidney agent if the chronic condition was verified. The GK agent Sima gave conflicting information which led Lauren to be more firm with the agent. She was not aggressive or inappropriate. The member became very frustrated and Lauren attempted to de-escalate. The member became escalated at other points in the call and Lauren appropriately de-escalates. In the call with AndMore at approximately 43:40, the AndMore agent states “we don’t have any record, like, well on my screen. I’m not gonna say he didn’t do it so don’t go like this, don’t go there”. Lauren politely said “Sir, we don’t need to say things like that.” The AndMore agent’s behavior just continues to deteriorate. The agent becomes very condescending and starts to shout at her. Lauren unintentionally had misgendered the AndMore representative, and she sincerely apologized. The AndMore agent continues to escalate the situation, but Lauren was ultimately able to resolve it and move the call forward. | O9: https://mypolicypoint-my.sharepoint.com/:w:/r/personal/mthomas_mypolicypoint_com/Documents/Performance%20Tracking/Complaint%20Tracking/LWyke%2001.28.2026.docx?d=w476c6fd712de499496b12b81263ace61&csf=1&web=1&e=2gXVCk
A10: Sara Jarrell | B10: JT Tellez | C10: https://app.agencybloc.com/individuals/73995608/detail | D10: 46056 | E10: 46070 | G10: 46073.657 | H10: Member Services | I10: WellCare | J10: As per the member’s response to a Verse Text: “I do not want your insurance. I have told 3 people that work for you and left messages! I am communicating with my previous insurance insurance!!! PLEASE do not contact me again. I am thinking of reporting your company to the Insurance Commissioner!!!!!” The member’s root concern appears to be that her doctor is not in network. | K10: •Providers - Medical | L10: Founded | M10: •Providers - Medical •Benefit Misinformation | N10: Due to the member’s frustration and mention of the DOI, I have listened to the calls associated with this enrollment. Additionally, I looked at notes within AMS. The member’s root concern appears to be that her doctor is not in network. When asked, the member provided Sara with her primary care doctor of Dr. Benjamin Fitch and states that she does not want to switch her doctor. Sara asks a few questions to find the doctor and the member indicates that he is at the Lake Cumberland clinic. This doctor does not pull up in Sunfire. This is because the doctor is a second-year resident working under another doctor. Sara does properly inform the member that she is not showing him as in network when she pitches the plan. At the end of the pitch and prior to transferring to Kylie, Sara attempts to find another doctor for the member. The member states that she will just continue to see Dr. Fitch and pay out-of-pocket for the visits. Sara just acknowledges this by saying “yeah, you end up paying him”. She does not properly educate the member. There should have been some level of ATR, re-education, or cause Sara to pause and re-evaluate plan options. After the call is transferred, Kylie goes over the QA checklist. When she discusses the HMO portion of the checklist the member states “My doctor is Dr. Benjamin Fitch, F-I-T-C-H, and he's not in the network, but I told her that it does not matter to me. I still want to see Dr. Fitch.” Kylie also did not ATR, re-educate, or pause to re-evaluate plan selection | O10: https://mypolicypoint-my.sharepoint.com/:w:/r/personal/mthomas_mypolicypoint_com/Documents/Performance%20Tracking/Complaint%20Tracking/SJarrell%2002.03.2026.docx?d=wdcaa4cba743c4644a34afd3cc4603def&csf=1&web=1&e=7dZ3qQ
A11: Kylie DeMarino | B11: JT Tellez | C11: https://app.agencybloc.com/individuals/73995608/detail | D11: 46056 | E11: 46070 | G11: 46073.657 | H11: Member Services | I11: WellCare | J11: As per the member’s response to a Verse Text: “I do not want your insurance. I have told 3 people that work for you and left messages! I am communicating with my previous insurance insurance!!! PLEASE do not contact me again. I am thinking of reporting your company to the Insurance Commissioner!!!!!” The member’s root concern appears to be that her doctor is not in network. | K11: •Providers - Medical | L11: Founded | M11: •Providers - Medical •Benefit Misinformation | N11: Due to the member’s frustration and mention of the DOI, I have listened to the calls associated with this enrollment. Additionally, I looked at notes within AMS. The member’s root concern appears to be that her doctor is not in network. When asked, the member provided Sara with her primary care doctor of Dr. Benjamin Fitch and states that she does not want to switch her doctor. Sara asks a few questions to find the doctor and the member indicates that he is at the Lake Cumberland clinic. This doctor does not pull up in Sunfire. This is because the doctor is a second-year resident working under another doctor. Sara does properly inform the member that she is not showing him as in network when she pitches the plan. At the end of the pitch and prior to transferring to Kylie, Sara attempts to find another doctor for the member. The member states that she will just continue to see Dr. Fitch and pay out-of-pocket for the visits. Sara just acknowledges this by saying “yeah, you end up paying him”. She does not properly educate the member. There should have been some level of ATR, re-education, or cause Sara to pause and re-evaluate plan options. After the call is transferred, Kylie goes over the QA checklist. When she discusses the HMO portion of the checklist the member states “My doctor is Dr. Benjamin Fitch, F-I-T-C-H, and he's not in the network, but I told her that it does not matter to me. I still want to see Dr. Fitch.” Kylie also did not ATR, re-educate, or pause to re-evaluate plan selection | O11: https://mypolicypoint-my.sharepoint.com/:w:/r/personal/mthomas_mypolicypoint_com/Documents/Performance%20Tracking/Complaint%20Tracking/SJarrell%2002.03.2026.docx?d=wdcaa4cba743c4644a34afd3cc4603def&csf=1&web=1&e=7dZ3qQ
A12: Robert Lang | B12: Nesia Jefferies | C12: https://app.agencybloc.com/individuals/73629732/detail | D12: 46049 | E12: 46078 | G12: 46080.482 | H12: Member Services | I12: Humana | J12: Member states that they were told that they could get implants with their new policy, but has found out that they are excluded. | K12: •Providers - Ancillary •Benefit Misinformation | L12: Founded | M12: •Providers - Ancillary •Benefit Misinformation •Medicaid Coverage | N12: Robert told the member at least three times throughout the call that implants and “snap ins” were covered with a $0 copay. However, these are specifically excluded as per the Evidence of Coverage. Robert also provided misinformation on copays and deductibles for medical services. He informed the member at multiple points in the call that Extra Help will pay for the medical deductible and copays. For example, at 1:07:44 into the call he states “They’re paying your copays and your deductibles and your monthly premium. Your medical deductible is $283. Who pays that? Extra Help, right?” He goes on to say “So your primary care doctor’s zero copay, specialist is $0-$20, but guess who pays that copay? Extra Help.” When it came to the premium payment section, Robert informs the member “extra help is paying your co-pays, Pamela, so we're going to leave it on social security so they can pay it for you.” He gives the member the premium payment options, but selects one for the member. | O12: https://mypolicypoint-my.sharepoint.com/:w:/r/personal/mthomas_mypolicypoint_com/Documents/Performance%20Tracking/Complaint%20Tracking/RLang%2001.27.2026.docx?d=wa35a620d80a943ffbdf7019217292b52&csf=1&web=1&e=ONceNZ
A13: Lauren Wyke | B13: Michelle Thomas | C13: https://app.agencybloc.com/individuals/73444737/detail | D13: 46066 | E13: 46080 | G13: 46083.347 | H13: Member Services | I13: Humana | J13: Member was under the impression that Lauren was supposed to cancel her Humana plan and reinstate her previous PPO plan when she spoke to her on 2/13/2026 | K13: •Enrollment Consent •Benefit Misinformation | L13: Unfounded | M13: •Enrollment Consent •Providers - Medical | N13: In listening to Lauren’s calls prior to the complaint, cancellation was not discussed. The call with the member and Lauren on 2/13/2026 was the Post Effective Welcome call. In that call, it was discussed that the member’s provider is not accepting the plan. Lauren reviews the doctor’s information on Humana’s website and shows them as in network. They conference in Humana, who also sees that the doctor is in network. They discuss that it is the provider’s responsibility to update the information if they decide not to take the plan. That call is left without any mention of cancellation, and the member decides to speak to the provider’s office directly. In listening to the calls on 2/27/2026, the member first spoke with Rob. They contacted Humana, and the member indicated that she called on her own after the conversation with Lauren. It was later in that call that Lauren was brought up, and it was by our agent. | O13: https://mypolicypoint-my.sharepoint.com/:w:/r/personal/mthomas_mypolicypoint_com/Documents/Performance%20Tracking/Complaint%20Tracking/LWyke%202.13.2026.docx?d=wd392cbbbe9a64719946c92bab0eed246&csf=1&web=1&e=TNiCfH
A14: Kylie DeMarino | B14: JT Tellez | C14: https://app.agencybloc.com/individuals/74435208/detail | D14: 46071 | E14: 46085 | G14: 46085.646 | H14: Member Services | I14: Humana | J14: The member stated he had previously had a PPO and switched to this PPO on the basis that he was told his provider, Dr. Kipker, was in-network | K14: •Providers - Medical | L14: Founded | M14: •Providers - Medical •Benefit Misinformation •Enrollment Consent | N14: The member provided his primary care provider at approximately 8:40 into the call. He provides his PCP as Dr. Nathaniel Kipker and provides the address he sees him at. At approximately 16:43 into the call Kylie tells the member states, “…all of your doctors would still accept it. Veronica still accepts their HMO version. Med still accepts their HMO version. Same with the primary care doctor. Sorry, I'll go back, verifying that. As well, let me triple check. Nathan Kipker also accepts HMO.” Because the member was concerned about HMO vs. PPO, Kylie told the member she would check again at about 27:35 into the call. At 32:21 into the call she tells the member again that he is in network. At approximately 42:11 into the call Kylie tells the member that she is adding Dr. Kipker as the primary care provider on the application. However, the application download in AMS shows a Dr. Aliyah Ahmed as the primary care provider. This is not a provider that the member mentioned, although it is close to Dr. Ahmed Ali’s name. Dr. Kipker’s name is not showing in Sunfire. Additionally, Dr. Kipker does not pull up in Humana’s site. Dr. Kipker is a second-year medical student being supervised by Dr. Monica Thipparthi. Dr. Thipparthi was not discussed on this call and is not in-network. I was able to identify this when I searched the provider’s name in Google and asked the member to confirm who the supervising provider was. When Kylie posted this in the SNP channel for review, she did not have anything on Dr. Kipker. Therefore, when it was approved, it was done without any indication of this provider. There are also no screenshots posted in the AMS account to indicate where she found Dr. Kipker. | O14: https://mypolicypoint-my.sharepoint.com/:w:/r/personal/mthomas_mypolicypoint_com/Documents/Performance%20Tracking/Complaint%20Tracking/KDeMarino%2002.18.2026.docx?d=we9e5d0636f214cbd8c2116deabb37554&csf=1&web=1&e=RYkLH7 | P14: Yes | Q14: 46087
A15: Sara Jarrell | B15: JT Tellez | C15: https://app.agencybloc.com/individuals/73235663/detail | D15: 46035 | E15: 46084 | G15: 46090.554 | H15: Member Services | I15: Humana | J15: Member states that they were manipulated to enroll in this plan. | K15: •Benefit Misinformation •Enrollment Consent | L15: Founded | M15: •Providers - Medical •Drugs - Cost or Coverage •Providers - Ancillary •Benefit Misinformation | N15: While it is hard to determine manipulation, this call had multiple instances of incorrect information that were likely key factors in the member’s enrollment. The member mentioned that his provider was Directions for Living, where he obtained his injections for a mental health condition. Sara tells the member multiple times throughout the call that this provider is a non-profit organization and therefore they do not accept insurance. This is not correct. This group does still accept insurance but also has a sliding scale for patients that do not. When discussing pharmacy, the member states that he gets the medications from the clinic. The member had mentioned that he was on an inhaler for his asthma, an injectable medication for the mental health condition, and a medication for movement disorders related to Parkinsons. He does not immediately know the names of the medications and Sara does not do much more probing. Instead, Sara again tells the member that they won’t take money from him. While this clinic does have an onsite pharmacy, it is run by another company and is just housed within the clinic. This pharmacy is not a non-profit and the member would be responsible for applicable copays. This could also lead to some additional high costs for the member as there is not a guarantee his medications will be covered under the formulary. One of the member’s needs was dentures. Sara sold this plan on the basis that he could get a complete set of dentures (upper and lower) once every five years. However, the benefit on this plan is one upper complete/partial or 1 lower complete/partial denture every 5 years. | O15: https://mypolicypoint-my.sharepoint.com/:w:/r/personal/mthomas_mypolicypoint_com/Documents/Performance%20Tracking/Complaint%20Tracking/SJarrell%2001.13.2026.docx?d=w36e820dec35e4f83a7c8eff52d91497c&csf=1&web=1&e=UuRS6S
A16: Tonja Howard | B16: Brian Henderson | C16: https://app.agencybloc.com/individuals/74795245/detail | D16: 46080 | E16: 46094 | G16: 46094.64 | H16: Member Services | I16: United Healthcare | J16: The member states that they were told that they could continue to see their provider with this plan, and that they could see out-of-network providers. | K16: •Providers - Medical •Benefit Misinformation | L16: Founded | M16: •Providers - Medical •Benefit Misinformation | N16: In reviewing this call, the member gave a nurse practitioner as their primary care provider. That nurse practitioner, Jennifer Santiago, is not in-network with this plan. Tonja tells the member several times on this call that Ms. Santiago is in-network. She also states that the reason the member has another doctor on their current UHC card is because Ms. Santiago is a nurse practitioner. The member informs her that the doctor on her card is one that she has not seen in quite some time because they are in another city that she lived in prior to moving to the assisted living facility she currently resides in. The member indicates to Tonja that this provider is not affiliated with Ms. Santiago. Additionally, at 1:10:07 into the call, Tonja tells the member that because this plan is an HMO-POS, “So you can see providers in and out of network and your doctors that we have listed accept this coverage.” At 1:10:59 Tonja again states “But your doctors do accept the HMO POS plan”. I have verified through the UHC website that Ms. Santiago is not in-network with this member’s plan. Ms. Santiago does not practice under a supervising physician as she is not required to in the state of Florida. It should also be noted that the provider the member gave as their ENT, Dr. Jayesh Patel, was initially not listed correctly in Sunfire. The provider listed was an eye doctor. This has since been updated. The member’s retina specialist, Dr. Mazzari, is also not listed in Sunfire. I was unable to find any information on this provider. For the majority of the doctors, Tonja did not get additional identifying information such as address. Tonja also does not gather prescriptions for this member, as the member states she lets the facility handle it. The member states that they pick them up and administer them, but she still pays a copay. It is important to still gather this information as the proposed plan’s formulary will still be applicable when filling medications. | O16: https://mypolicypoint-my.sharepoint.com/:w:/r/personal/mthomas_mypolicypoint_com/Documents/Performance%20Tracking/Complaint%20Tracking/THoward%2002.27.2026.docx?d=w469b1a9f35494905990e8d88b63852c6&csf=1&web=1&e=AgfVTd
A17: Ryan Lefler | B17: Brian Henderson | C17: https://app.agencybloc.com/individuals/74881946/detail | D17: 46084 | E17: 46100 | G17: 46101.342 | H17: Member Services | I17: Humana | J17: Caller stated that they are not the member’s POA, the member only speaks Spanish, but that they were able to complete the enrollment | K17: •Enrollment Consent •Plan Eligibility | L17: Founded | M17: •Enrollment Consent •Plan Eligibility | N17: The member’s cousin, Maria, called in to discuss the member’s Medicare benefits. Ryan specifically asked if the member made his own healthcare decisions and was told that he does. He asked the member if he was able to speak to Maria on his behalf, and was told “Yeah”. However, it is unsure if the member understood what was being asked. Ryan then completes the entire needs analysis, pitch, QA checklist, and disclaimers with the family member. The family member does not then relay that information to the member. For the agreement, Ryan does ask for the member to come back on the line to state their name, date of birth, and agreement. However, because they were not present or informed of the benefits, they were not aware of what they were agreeing to. It is part of the Medicare 2024 Final Rule that family members may not serve as interpreters for these interactions. Any language services must be completed by a qualified professional interpreter. | O17: https://mypolicypoint-my.sharepoint.com/:w:/r/personal/mthomas_mypolicypoint_com/Documents/Performance%20Tracking/Complaint%20Tracking/RLefler%2003.19.2026.docx?d=wf0527622ed8a45f49af8b25ff70e2b90&csf=1&web=1&e=EuaDkv
A18: Robert Lang | B18: Nesia Jefferies | C18: https://app.agencybloc.com/individuals/74784480/detail | D18: 46079 | E18: 46100 | G18: 46101.409 | H18: Member Services | I18: Humana | J18: Member states he was not informed that he could not use his OTC card in a store, as it has to be done via OTC catalog. | K18: •SSBCI Benefits •Benefit Misinformation | L18: Founded | M18: •SSBCI Benefits •Providers - Ancillary •Benefit Misinformation | N18: In Sunfire, the over-the-counter benefits specifically reads “$175 quarterly allowance to buy approved over-the-counter health and wellness products available through our OTC Mail Order provider.” It is important when pitching a benefit to the member that full and accurate information is provided. Additionally, when Robert is going through the QA checklist, he does not fully read other benefits as listed. For example, for dental he states “Zero copay for routine exams for your teeth and zero copay for complete or partial dentures, bridges, crowns, the whole nine yards. Zero copay. So, and there's no limit.” However, there are limits to dental services. | O18: https://mypolicypoint-my.sharepoint.com/:w:/r/personal/mthomas_mypolicypoint_com/Documents/Performance%20Tracking/Complaint%20Tracking/RLang%2002.26.2026.docx?d=w686e59bfde8d4eb5bd7e6c7a194e4be7&csf=1&web=1&e=kgLknq
A19: Tonja Howard | B19: Brian Henderson | C19: https://app.agencybloc.com/individuals/72104512/detail | D19: 45981 | E19: 46106 | G19: 46111.476 | H19: Carrier | I19: Humana | J19: The Beneficiary expressed dissatisfaction towards the Sales Agent who enrolled them into CarePlus Health Plans (CPHP). Beneficiary reports that he was assured by the sales agent at the time of enrollment that his vision coverage would be similar or better, but now finds it significantly reduced, with only a $200 annual allowance for contact lenses, which does not meet his needs. Beneficiary states he also had an optometrist and Primary Care Physician (PCP) for years and was assured he could continue seeing them; however, he is now finding they are not in the CPHP network. | K19: •Providers - Medical •Providers - Ancillary •Benefit Misinformation | L19: Partially Founded | M19: •Providers - Medical •Providers - Ancillary •Drugs - Cost or Coverage •SSBCI Benefits •Benefit Misinformation •Plan Eligibility | N19: In review of the call, the portion on the providers is unfounded. The member did not give an optometrist’s or any other specialist’s name. The member’s PCP, Dr. Irving Bratt, is in network with the member’s plan, as verified through CarePlus’s website. For the portion of the complaint on the vision, that is founded. The member’s benefits for vision did go up to $200 where they were previously $100. However, at approximately 28:11 into the call, Tonja gives the benefit as “$200 each year to go towards a pair of glasses or contacts, and it would allow you up to 2, pair of glasses if you choose, or, enough contacts to last you per year…” when there is no way that we can guarantee this would cover his contacts in their entirety. In the RX review, Tonja does not ask for formulation of the meds. It is possible that they were already listed in SF, but we would still want to verify. Additionally, the member mentions offhandedly a medication that is not added and no additional questions were asked. Another medication was omitted entirely. When she discusses that benefits, she states “Your drug deductible would have been $615”. This member does not have LIS and would therefore be responsible for that drug deductible as applicable. When discussing the over-the-counter/food card, she states “these benefits don't expire…”. While they do roll over month-to-month, they do expire if the member were to leave the plan. Additionally, she gave the member the total monthly and yearly, which can be misleading. In the chronic condition questions, the member answers “No” to all the questions. However, Tonja marks “Yes” to one. Tonja asked the member “And do you have a problem with your heart, had a heart attack, or have you been told that you had a heart attack?” and he responds with “No, no, I had, some minor strokes and then, and then they did open heart surgery on me, so.” While this member’s doctor ultimately confirmed the chronic condition, there should have been some follow up questions asked. In the needs analysis when Tonja asks the member about dental he states, “Yeah, probably I could use some work on my teeth, yeah, for sure.” Tonja does not ask any additional questions about what his needs were. When she goes over the dental, she does not list out the services listed in Sunfire. She simply states “Now for your dental you have a $0 copay for preventative and comprehensive services.” | O19: https://mypolicypoint-my.sharepoint.com/:w:/p/mthomas/IQCmeJ3LGy3iRb7NVDAzMqRwAbJ9V4KBXuyandBIRuceijU?e=iJdyph
A20: Gabriela Rivera | B20: Nesia Jefferies | C20: https://app.agencybloc.com/individuals/73490689/detail | D20: 46044 | E20: 46108 | G20: 46111.664 | H20: CTM | I20: Humana | J20: Caller feels misled because she did not give consent to change her plan and didn’t want to cancel her old plan. | K20: •Enrollment Consent •Benefit Misinformation | L20: Partially Founded | M20: •Enrollment Consent •Plan Eligibility •Providers - Medical •Providers - Ancillary •Drugs - Cost or Coverage •SSBCI Benefits •Benefit Misinformation | N20: Consent to enroll was received. The member was given the disclaimers as part of this enrollment. At 1:32:52 into the call, the disclaimer was given that indicates that the current Medicare Advantage plan would be cancelled when the Humana plan starts. At 1:35:08 the member provides her name, date of birth, and the “I agree” statement. At 1:35:33 Gabby tells the member “You will not bein the Humana until February 1st. From right now until the end of January, January 31st, you are still with United Health”. In review of this call, concerns about the member’s eligibility for the chronic condition have been identified. At 8:48 into the call, Gabby asks the member if they are managing any chronic conditions. The member replies that they have chronic pain (9:00), and a degenerative bone disease (9:03). Gabby asks the member if they have high blood pressure or cholesterol (9:46) and they answer yes. High blood pressure and high cholesterol are SSBCI qualifiers, but not CSNP. The member does indicate that they had a stroke (11:58) and Gabby asks further questions. When Gabby begins to ask the CSNP qualifying questions (1:21:19), the member answers “No” to all of them. She asks the member about swelling in her legs due to her heart (1:21:48) and the member answers “I just, I do have it, but swelling in my feet and legs, and I don't know why.” (1:21:59). Gabby tells the member “OK, so then I'm not sure if you would be answering yes to one of these, Do you have a problem with your heart? So I'm guessing you might need to answer yes for one of these, Ms. Caroline.” (1:23:15) She goes on to coach the member that a stroke would be related to a heart attack or problem with her heart. (1:23:34). As of most recently available information from Humana, this member has been determined as ineligible for the plan based off provider submitted documentation. When going through the needs analysis, the member indicates that they have an appointment with a dentist coming up in April. Gabby does not ask for the dentist’s name to verify if they are in-network with the proposed plan. (22:06) During the call, the member mentions that they see a pain specialist (49:53). Gabby does not ask who that provider is. The member mentions a pain specialist again at another point, but no effort is made to get that doctors name (53:14). When Gabby quotes the transportation benefit, she quotes it as 18 trips per year to the doctors. This was not presented correctly. The benefit is 36 one way trips with a 75 mile per trip limit. (58:59) Dental benefits were quoted as “a credit of up to $2000 per year towards the dental services”. No copay amounts or benefit limitations were given. (59:11) Vision benefits were also not given compliantly. Gabby states that the member will have $400 a year towards vision services. She does not state that the member must see a Humana Insight provider or the benefit will only be $300. (59:53) Gabby tells the member that the plan is “through our sponsor from Humana”. (1:01:17) This is non-compliant language as it misrepresents Gabby’s relationship with Humana. Multiple times throughout the call, Gabby refers to the member’s primary care provider as “Dr. Elizabeth Becker”. However, the provider is a physician’s assistant and no further questions were asked to verify who they are practicing under. (10:08, 10:21,10:46,14:03, 42:48, 1:00:09, 1:01:43,1:09:52, 1:26:05) When going through the QA checklist Gabby did not cover worldwide urgent care (1:10:52). In the review of the prescriptions, several were misquoted. Gabby tells the member that Gabapentin does not have a quantity limit, when it has a limit of 180 tablets per 30 days (1:13:41). She does not provide the quantity limit for the Lidocaine patch, which is 90 patches per 30 days (1:14:48). Additionally, Gabby does not provide the member the drug deductible if they were to lose the low income subsidy (1:11:49). The costs that she provides do not ma | O20: https://mypolicypoint-my.sharepoint.com/:w:/p/mthomas/IQCyFI49q8hwSJJv7cS4kxtlAdyGoeFRuMa9QGvP7TBIl1k?e=8xeAzg | P20: Yes | Q20: 46112
A21: Kylie DeMarino | B21: JT Tellez | C21: https://app.agencybloc.com/individuals/72891806/detail | D21: 46028 | E21: 46108 | G21: 46112.518 | H21: Carrier | I21: Humana | J21: The member, Lois M. Turner, alleges that the Humana sales agent provided inaccurate and misleading information during the enrollment process. The member states that the agent assured her she would receive $90 added to her Social Security check each month, that the plan would include over-the-counter (OTC) benefits, and that it would cover a partial dental denture. After enrollment, the member discovered the plan does not include OTC benefits and does not cover partial dentures, resulting in her paying $750 out-of-pocket. | K21: •Providers - Ancillary •SSBCI Benefits •Medicaid Coverage •Benefit Misinformation | L21: Partially Founded | M21: •Providers - Ancillary •SSBCI Benefits •Medicaid Coverage •Drugs - Cost or Coverage •Benefit Misinformation | N21: Upon review of this call, the member specifically identified at 6:52 that he wanted a plan that covered partial dentures. At 12:02 into the call, Kylie informs the member that the dental benefit remains the same on the proposed plan as it does on the new plan. At 12:11 she states “And it does actually cover partials”. At 13:14 she states that she doublechecked and that it does cover partials. At 14:10 she provides the member a $0 copay for the partials. This plan does not cover full or partial dentures as per the Summary of Benefits and the Evidence of Coverage. If she searched these documents for the word “partial”, it would show coverage for partial bridges, but not partial dentures. This portion of the complaint is founded. Kylie did present the member with the $90 giveback as per the Summary of Benefits at approximately 11:7 into the call. Eligibility look ups do not show any Medicaid for this member. This was prior to additional language about Part B givebacks being added to scripting. This part of the complaint is unfounded. At 11:51 into the call, Kylie tells the member “So instead of the card, you actually get an additional $90 right on your Social Security Check, and you can use that however you want”. She states this because the member previously had an OTC benefit. This part of the complaint is unfounded, although clearer language could have been used. There were additional concerns on this call outside of those listed in the complaint. At 15:23 into the call, the member specifically asks “That’s the ony thing that increases that, that’s all?” after Kylie informs him that the specialist office visit copay increased from $15 to $40. She answers the member with “Yes”. She does highlight that the emergency room copay goes down as does the urgent care copay. However, she does not state that a medical deductible is added, the maximum out-of-pocket is increased, and that the hospital stay copay is also increased. Additionally, at 17:28 into the call Kylie tells the member that if a doctor prescribes his Vitamin D it would be a $0 copay. She tells the member at 17:40 that “it's showing if a doctor does prescribe it to you it would be $0 to get it prescribed.” However, it is showing as non-formulary in Sunfire and on Humana’s website. When Kylie is reading the benefits for vision, she does not state that the member must see an Insight provider or the benefits will be reduced by $75. When going through the QA checklist, Kylie did not provide the in and out-of-network benefits. | O21: https://mypolicypoint-my.sharepoint.com/:w:/p/mthomas/IQBBi6CritcZSLvWlbFjCrilARxc9bz-3EguTXgwYe0dJY0?e=4X7OMj
A22: Aleccia Wright | B22: Brian Henderson | C22: https://app.agencybloc.com/individuals/74784644/detail | D22: 46059 | E22: 46094 | F22: 46113 | G22: 46112.569 | H22: CTM | I22: Gold Kidney Health Plan | J22: Caller feels misled because beneficiary did not authorize anyone to change her plan and does not know why her plan was changed without her knowing. | K22: •Enrollment Consent | L22: Founded | M22: •Enrollment Consent •Providers - Ancillary •SSBCI Benefits •Drugs - Cost or Coverage •Benefit Misinformation | N22: This complaint is founded upon call review. At 47:00 in the call, AJ Wright begins the application portion of the call. She completes the pre-qualification portion and demographic information. At 1:06:47 the consent for disclosure is read. At 1:12:48 AJ informs Ms. Lick that she will be reading some disclaimers and asking for a signature. At 1:13:02, the disclaimers are read. AJ does not read the disclaimers verbatim or in their entirety, most relevantly the portion about the previous plan ending when the Gold Kidney becomes effective. At 1:14:14 AJ asks for agreement to enroll, and the member asks a follow up question. AJ asks again at 1:16:11 “So if you agree to complete the application now, please state your name, your date of birth, and that you agree.” Ms. Lick responds with “yes”, her name, and her address. She never states “I agree” or provides her date of birth. She asks some additional follow-up questions and at 1:19:41 AJ provides the confirmation number for the enrollment. Additionally, there were other concerns identified with this enrollment. When AJ went through the providers, she did not gain full addresses for all of them. This may impact participation status. At 13:30 into the call, the member mentions that their dental need for the moment is crowns. When she quoted crowns, she did not provide any copay or limitations. Additionally, she quoted the dental benefit multiple times as $4,000 when it was actually $5000 (30:55 into the call and 31:16) At 15:44 she asks the member about their vision needs, and the member indicates that they wear glasses. At 31:59 AJ tells the member “With a $200 allowance for prescription eyewear, so you would be able to go $0 copay for your routine eye exams and you'll have up to $200 each year to spend on purchasing glasses if your prescription changes or if you need to update your eyeglasses each year.” The benefit for vision is actually a $300 allowance for frames or $115 for contact lenses in lieu of glasses. At 16:22 into the call the member indicates that they are currently wearing hearing aids. The benefit for hearing aids was never presented or discussed. AJ presents the benefit for grocery at 29:56 into the call. She states that it is a $150 a month allowance. She repeats this again at 30:02. However, the benefit is $200. It is not until the end of the call at 1:18:25, after the application is complete, that the correct amount is given. At 30:37 into the call, AJ quotes the benefit for the over-the-counter. The benefit is $100 per quarter. She states ” you're gonna have $33 extra each month or $100 loaded once a quarter to purchase those items as well, OK?” This phrasing can be misleading or confusing, as it is just loaded once per quarter. AJ begins the QA checklist at 32:40 into the call. She did not go over the premium until the application portion. She did not cover the deductible, maximum out-of-pocket, hearing, or out-of-network coverage amounts (or worldwide coverage for urgent care). AJ misquotes the copay for specialist as $20, when it is actually $15 (33:58). At 34:16 she tells the member “If you see a heart specialist or if you see a diabetes management specialist, those doctors are actually covered at a $0 copay.” This is a misleading statement, as it should be endocrinologist not “diabetes management specialist”. When AJ goes through the pharmacy costs, she does not go over the estimated full drug costs. She begins the discussion at 35:38 by gathering the member’s medications. She incorrectly listed one in Sunfire as 30 days when the member stated every 90 days. When she quotes benefits for copays at 45:04, she states “OK, so tier one preferred generics, at a 30 day supply with the standard retail pharmacy is a $0 copay and tier two generics are only $5”. However, the duloxetine would only be $4 and not $5. When AJ is in the application, at 1:01:01 she asks the member if the Zepbound is the medication she takes | O22: https://mypolicypoint-my.sharepoint.com/:w:/p/mthomas/IQDLdvRDhbTLTYrOO82mIloSAU4ovf_MKdtzWqemDzfL_kw?e=XkOyYN
A23: Vidal Fakondo | B23: Brian Henderson | C23: https://app.agencybloc.com/individuals/76234157/detail | D23: 46105 | E23: 46113 | F23: 46115 | G23: 46113.687 | H23: Member Services | I23: Zing Health | J23: Member states that they were told that their primary care provider, Catherine McGinnis, is in network with the plan. However, they are now being told that the provider is not. Please note: The member stated they have also spoken to Medicare, so this may also become a CTM. | K23: •Providers - Medical •Benefit Misinformation | L23: Founded | M23: •Providers - Medical •Providers - Ancillary •Drugs - Cost or Coverage •Enrollment Consent •Benefit Misinformation | N23: In review of this call, the member provided the primary care provider of Catherine Mcginness at 6:57 into the call. The member indicates that it is incredibly important to keep this provider. Additionally, the member provides their cardiologist Dr. Alan Goldberg (7:58), oncologist Dr. Audrey Kam (9:00), surgeon Marissa Andersen (9:41), urologist Dr. Alysen Demzik (10:15), oncologist Dr. Matthew Dixon (11:10), and a plastic surgeon Dr. Krista Hardy (11:53). At 42:08 into the call Vidal tells the member that they would be able to see Dr. McGinness as their PCP with this plan at an $0 copay. At 42:24 the member specifically asks if he will be able to continue to see his current care team. Vidal answers the member with “Yes, absolutely” at 48:33. He then individually lists the providers that the member gave and states that they are all in network. However, Dr. Catherine McGinness and Dr. Alan Goldberg are not in-network with this plan, as verified through the Zing provider search online. When Vidal completed the primary care provider portion of the application at 1:02:48 he stated that he would be putting Dr. McGinness as the primary care provider. However, on the application it has a Dr. Patricia Martinez. This was not discussed or disclosed to the member. There were additional concerns on this call as well. In the needs analysis, the member mentions that he needs dental surgery (14:53) and at least three dental implants (15:31). When Vidal pitched the dental benefit at 36:03, he specifically mentions the implants. However, Vidal did not specifically state that implants are not covered. Instead, he pitches it as if the $2,500 would cover the implants. Additionally, he does not give the limitations on the fluoride, xrays, or cleanings that he presented. He again gives dental benefits at 41:55 and misses limitations there as well. When Vidal give the transportation benefit, which was identified as a need, he does not tell the member the milage limitation. At 29:31 into the call, Vidal begins to gather the medications. The member provides Vidal with Amox-CLAV at 31:59 into the call. The medication listed in Sunfire and quoted was the standard amoxicillin, which is a tier 1 medication. The one the member is on is actually a Tier 2. When he goes over the atorvastatin calcium at 45:47, he states “30 tablets for 30 days”, but does not specifically state this is the quantity limit. As Vidal is going into the application, the member asks “You’re enrolling me into what all the different types of programs you mentioned?” at 47:11. Vidal answers “I am enrolling you into that Zing plan with all those increased benefits that I mentioned.” The member still seemed confused and asked at 47:32 “I’ll still be with United Healthcare, correct?”. Vidal responds with “Zing is the carrier that provides those those benefits for you, right?”. Vidal should have used stronger language to indicate that the plan would be changed. This is especially important because the member indicated at the beginning of the call that they did not want to change their plan. The member had questions about Extra Help at 1:05:06 into the call. Vidal answered with “So please note that if you had extra help, if you had extra, basically if you have Medicaid,[MT44.1] but you don't have Medicaid, if you have Medicaid and enrolling in a plan with drug coverage, your premium or copay may change if your extra help changes, all right.” However, Medicaid and LIS are not interchangeable. | O23: https://mypolicypoint-my.sharepoint.com/:w:/p/mthomas/IQBGGQOgk39dQKJgePkcdMVMAQkdxvimvVAUJPEfaNP7inQ?e=HpaVZB
A24: Whitney Dantzler | B24: Nesia Jefferies | C24: https://app.agencybloc.com/individuals/75950577/overview | D24: 46093 | E24: 46107 | F24: 46119 | G24: 46114 | H24: Member Services | I24: United Healthcare | J24: The member stated he never moved to Texas, and that they told the original agent they were just visiting. | K24: •Benefit Misinformation | L24: Unfounded, coaching opportunities present | M24: •Drugs - Cost or Coverage •Medicaid Coverage •Benefit Misinformation | N24: The member confirmed that their zip code is 76549 (0:29) and that they are in Bell County (044). At 0:52 in the call the member specifically states “I just moved down here from Florida about, about two weeks ago…. So I don’t know if if that matters or not”. Whitney does a great job of confirming the move and the timeline (1:13). As Whitney is looking into plan options, she asks the member “What prompted your move from Florida to Texas?” (13:03). The member again acknowledges that he moved in his response (13:40). The member asked questions about coverage while travelling (15:28) and Whitney informs the member that he may be covered while travelling but not for permanent moves with his previous plan. At 27:56 the member indicates that he is living with a friend but is looking at getting a permanent address. Whitney asked follow-up questions, and the member indicates he should have his permanent address in Texas in a month or a month and a half (28:25). At 55:06, Whitney reminds the member to contact Social Security to update their address. At 58:20 into the call the member indicates that he plans on working part time once he “gets settled here”. While overall this call was very well done, there was an area of opportunity related to drug coverage and LIS. Whitney quotes the premium on this plan as $0 because the member has LIS. However, Sunfire and UHC’s website reflects the adjusted premium as $16.20. Additionally, Whitney does not provide the drug deductible should the member lose their LIS. | O24: https://mypolicypoint-my.sharepoint.com/:w:/p/mthomas/IQBXqSo92wsmTrzirQ-S8WJvAXiNS26X8f9xRGhYEl48Pwg?e=VbX1wV
A25: Gabriela Rivera | B25: Nesia Jefferies | C25: https://app.agencybloc.com/individuals/71187259/overview | D25: 45957 | E25: 46121 | F25: 46125 | G25: 46122 | H25: Carrier | I25: Aetna Inc. | J25: Carrier found concerns in a routine audit of calls from October to February of 2026. | K25: •Providers - Medical •Providers - Ancillary •Drugs - Cost or Coverage •Benefit Misinformation | L25: Founded | M25: •Providers - Medical •Providers - Ancillary •Drugs - Cost or Coverage •Medicaid Coverage •Benefit Misinformation | N25: • PROVIDER PARTICIPATION STATUS: Enrollee informed agent she goes to Monarch Dental. Agent failed to educate enrollee on Monarch Dental OON status. • BENEFIT ACCESS THROUGH NETWORK/VENDOR: Agent failed to specify restrictions or vendors for Dental/Vision/Hearing. • IMPORTANCE OF RX: Enrollee decline to review RX. Agent failed to educate enrollee that she may have to pay full price for RX if its not covered under the plan formulary. • PREMIUM AND DEDUCTIBLES: Agent failed to educate enrollee on plan Part B premium reduction. • BENEFIT ACCURACY: Agent misinformed enrollee that the MOOP is $0. | Q25: 46112
A26: Victor Filimonchuk | B26: JT Tellez | C26: https://app.agencybloc.com/individuals/71059121/overview | D26: 46316 | E26: 46121 | F26: 46125 | G26: 46122 | H26: Carrier | I26: Aetna Inc. | J26: Carrier found concerns in a routine audit of calls from October to February of 2026. | K26: •Providers - Ancillary •Drugs - Cost or Coverage •Enrollment Consent •Benefit Misinformation | L26: Founded | M26: •Providers - Ancillary •Drugs - Cost or Coverage •Enrollment Consent •Benefit Misinformation | N26: • Benefit access through network/vendor was not provided for hearing, dental, transportation, or eyewear benefits • RX Request/Formulary status: Agent did not advise member of medications not in formulary • Responsive to Needs and Questions: Enrollee asked about cancellation and the agent did not advise on the cancellation process. • Enrollment: Did not state that EOC can be found on Aetna’s website or by calling customer service • Enrollment Confirmation: Did not provide the confirmation number to the member
A27: Anthony Boyle | B27: JT Tellez | C27: https://app.agencybloc.com/individuals/73825323/detail | D27: 46052 | E27: 46077 | F27: 46121 | G27: 46113 | H27: CTM | I27: Humana | J27: Caller was misled by Anthony Boyle on 1/30/2026 which is from power point company was providing benefits about humana was giving falsely information regarding they have better benefits than UHC she had prior they were in network with providers but when went to pain management they had needed a referral and turned out they were not in network after speaking with Anthony Boyle for more than an hour bene came to the thought she did not want humana and wanted to cancel but mr anthony boyle never picked up nor called back. Even left a voicemail for a call back and nothing. Till a mr [agent name redacted] called bene on 2/2/2026 back regarding to switch back to UHC and disenroll from humana and he sent disenrollment documents to bene for the disenrollment. | K27: •Providers - Medical •Agent Behavior •Benefit Misinformation | L27: Partially Founded | M27: •Providers - Medical •Benefit Misinformation | N27: Case is Founded. Upon validating the enrollment recording, the member provided her pain management doctor, Dr. Rita Azzo. The agent verified and informed the member that all of her doctors were covered. However, upon validating the PAR status, Dr. Rita Azzo was found to be out of network. Therefore, the agent provided incorrect information regarding the member’s pain management doctor. Case is Unfounded. Its is evident that the member spoke with the agent and provided verbal consent telephonically agreeing to enroll in the described Humana plan. The member was aware that she was enrolling in the new Humana plan and did not show any dissatisfaction. Case is Unfounded. The agent did not provide any false information regarding the plan. At the time of enrollment, the agent did not inform the member that the Humana plan had better benefits than UHC. Instead, the agent presented the Humana Gold Plus SNP DE HMO plan and informed the member, “We are going to increase the food card benefit, and it will be an actual debit card. The amount will increase from $229 to $250." Case is Dismissed. The allegation concerning, "she did not want humana and wanted to cancel but mr anthony boyle never picked up nor called back. Even left a voicemail for a call back and nothing.” Is on post enrollment and does not fall under SRM Scope. | Q27: 46121
A28: Kylie DeMarino | B28: JT Tellez | C28: https://app.agencybloc.com/individuals/72496895/detail | D28: 45997 | E28: 46065 | F28: 46121 | G28: 46113 | H28: Carrier | I28: Humana | J28: The beneficiary expressed dissatisfaction with the sales agent who sold her the CareComplete Platinum plan, alleging the agent misrepresented prescription copays. She states the agent told her that her medication copays would not change from her previous plan, but after enrollment, all copays increased. The beneficiary indicates they reviewed all her medications, and the agent assured her she would not be paying more, yet her oxycodone copay is now $21 instead of $15 and the desvenlafaxine succinate will be more expensive as well. | K28: •Drugs - Cost or Coverage •Benefit Misinformation | L28: Founded | M28: •Drugs - Cost or Coverage •Benefit Misinformation | N28: Case is Founded. Upon receipt, SRM conducted a review in accordance with our internal processes. Upon reviewing the enrollment recording, the agent asked the member about her medications. The member responded she is taking, Vitamin D2 50,000 IU (12 per month), Desvenlafaxine 100 mg (30 per month), Carisoprodol 350 mg (90 per month), Repatha 140 mg every two weeks, Buspirone 15 mg (90 per month), Hydroxyzine Pamoate 50 mg capsules, Zenpep pancreatic enzyme supplement, Trazodone 300 mg (30 per month), and Oxycodone 10 mg (90 per month). The agent informed the member that Oxycodone is not on the CarePlus plan formulary and requires a formulary exception. The agent also advised the following estimated costs, Hydroxyzine Pamoate (Tier 3) $4.01/month, Oxycodone 10 mg (Tier 3) $7.40/month, Desvenlafaxine 100 mg (Tier 2) $9.56/month, Buspirone 15 mg (Tier 1) $14.81/month, Trazodone 300 mg (Tier 3, prior authorization required) $281.12/month, and Zenpep 40,000 units (Tier 4) $474.49/month. The agent told the members the costs would remain the same. However, this was incorrect. According to the Summary of Benefits Tier 3 Preferred Brand is $30 for a 30-day supply and $90 for a 100-day supply, Tier 2 is $0 for a 30 day or 100-day supply, Tier 4 Non Preferred Drug is 50% coinsurance for both 30 day and 100 day supplies, and Tier 5 is 25% for a 30 day supply. | P28: Yes
A29: Kylie DeMarino | B29: JT Tellez | C29: https://app.agencybloc.com/individuals/74804901/detail | D29: 46080 | E29: 46087 | G29: 46118 | H29: Carrier | I29: Devoted Health | J29: This Mbr is upset that he was signed up on Devoted without his consent/ Mbr is stating that he might file a law suit for being signed up without his consent | K29: •Enrollment Consent | L29: Unfounded, coaching opportunities present | M29: •Enrollment Consent •SSBCI Benefits •Agent Behavior •Benefit Misinformation | N29: Sales leadership is to coach the agent on the following: 1. Strengthen the sales presentation by reviewing all they key benefits and cost shares as outlined in the Summary of Benefits for medical and prescription drug benefits including the laboratory services copay, explaining the prescription drug tiers, and confirming whether or not the beneficiary’s providers are in-network or out-of-network with the plan. 2. When presenting additional benefits such as the $361 per month grocery/benefits card, clearly state that this is a plan benefit delivered via a plan card (not cash), and briefly describe that it can be used only for eligible items, to avoid any misunderstanding. 3. After reading the standard CMS enrollment script, add a plain-language confirmation such as, "Can you confirm you understand this Devoted plan will replace your current Humana Medicare Advantage plan?" to further reduce the risk of future "did not consent" complaints. 4. When positioning the new plan as an improvement, avoid absolute statements like "the most money you can get" and instead frame it as "higher benefits than your current Humana plan among the plans I represent," to stay clearly within CMS marketing guidance. 5. Avoid language that could be perceived as disparaging other plans or implying only you are trustworthy (for example, saying other callers are "just going to try to get you to come back"). Reframe to neutral language such as, "You may also hear from Humana about your options; if you have questions, you can always call me back." 6. When asking the member to respond to post-call texts, be careful to emphasize that honest feedback is appreciated rather than suggesting a specific type of positive comment, so the member does not feel pressured. 7. Where possible, prioritize using the Medicare Beneficiary Identifier (MBI) over the Social Security number for eligibility verification to align with best practices for protecting sensitive personal information, unless SSN use is explicitly required by the plan or system. 8. Read all CMS enrollment disclaimers including informing the beneficiary of their right to cancel the enrollment | P29: Yes | Q29: 46122
A30: Gabriela Rivera | B30: Nesia Jefferies | C30: https://app.agencybloc.com/individuals/71187259/detail | D30: 45957 | E30: 46121 | G30: 46121 | H30: Carrier | I30: Aetna Inc. | J30: Found in a routine audit of calls | K30: •Providers - Medical •Providers - Ancillary •Drugs - Cost or Coverage •Benefit Misinformation | L30: Founded | M30: •Providers - Medical •Providers - Ancillary •Drugs - Cost or Coverage •Medicaid Coverage •Benefit Misinformation | N30: • PROVIDER PARTICIPATION STATUS: Enrollee informed agent she goes to Monarch Dental. Agent failed to educate enrollee on Monarch Dental OON status. • BENEFIT ACCESS THROUGH NETWORK/VENDOR: Agent failed to specify restrictions or vendors for Dental/Vision/Hearing. • IMPORTANCE OF RX: Enrollee decline to review RX. Agent failed to educate enrollee that she may have to pay full price for RX if its not covered under the plan formulary. • PREMIUM AND DEDUCTIBLES: Agent failed to educate enrollee on plan Part B premium reduction. • BENEFIT ACCURACY: Agent misinformed enrollee that the MOOP is $0.
A31: Victor Filimonchuk | B31: JT Tellez | C31: https://app.agencybloc.com/individuals/71059121/detail | D31: 45951 | E31: 46121 | G31: 46121 | H31: Carrier | I31: Aetna Inc. | J31: Found in a routine audit of calls | K31: •Providers - Ancillary •Drugs - Cost or Coverage •Enrollment Consent •Benefit Misinformation | L31: Founded | M31: •Providers - Ancillary •Drugs - Cost or Coverage •Enrollment Consent •Benefit Misinformation | N31: • Benefit access through network/vendor was not provided for hearing, dental, transportation, or eyewear benefits • RX Request/Formulary status: Agent did not advise member of medications not in formulary • Responsive to Needs and Questions: Enrollee asked about cancellation and the agent did not advise on the cancellation process. • Enrollment: Did not state that EOC can be found on Aetna’s website or by calling customer service • Enrollment Confirmation: Did not provide the confirmation number to the member
A32: Angelica Furlow | B32: Nesia Jefferies | C32: https://app.agencybloc.com/individuals/74802082/detail | D32: 46080 | E32: 46097 | G32: 46126 | H32: Carrier | I32: Devoted Health | J32: Member stated when enrolling the sales agent told her the plan would be the same that she previously had but with more benefits. Member stated she later found out she no longer has a dual complete plan. | K32: •Benefit Misinformation •Medicaid Coverage | L32: Unfounded, coaching opportunities present | M32: •Agent Behavior •Drugs - Cost or Coverage •Enrollment Consent •Benefit Misinformation | N32: Sales leadership is to review the complaint with the agent, and coach them on the following: • Coach the agent to soften language that could be perceived as discouraging member choice, e.g., instead of saying “do not make any plan changes” and to “ignore” calls/letters from the prior carrier, advise her to tell members they may receive outreach and that they can contact her, the plan, or 1 800 MEDICARE if they have questions. • Reinforce avoiding pejorative characterizations of other plans’ communications (e.g., calling them “tactics to scare you into staying”); focus instead on factual education about member rights and options. • Emphasize clear, unambiguous articulation of premium amounts (e.g., “seventeen dollars per month”) to avoid any potential confusion, even when the member’s net premium is $0 due to Medicaid/Extra Help. • When conducting a Health Risk Assessment immediately after enrollment, remind the agent to state explicitly that the assessment is optional, does not affect enrollment or benefits, and can be declined or stopped at any time. • Remind the agent that when she states she represents “all the top carriers” her statements must remain consistent with the required disclaimer that she does not offer every plan in the area; coaching can help keep this phrasing compliant and precise. • Review the Laboratory Services Copay, Prescription Drug Deductible and Prescription Drug Copays on the SOB • Informed the beneficiary of their right to cancel this enrollment.
A33: Whitney Benoit | B33: Brian Henderson | C33: https://app.agencybloc.com/individuals/76046473/overview | D33: 46113 | E33: 46119 | F33: 46129 | G33: 46126 | H33: Member Services | I33: Humana | J33: Member spoke to Whitney and stated she had informed him of the participation status of one of his doctors incorrectlu. The member stated that the surgeon Armaghan Mostafvi is not in-network. | K33: •Providers - Medical | L33: Founded | M33: •Providers - Medical •Providers - Ancillary •Drugs - Cost or Coverage •SSBCI Benefits •Benefit Misinformation | N33: At 01:02:16 into the call as Whitney was beginning the enrollment the member remembered the name of his surgeon. He provided the name of Amy Mostafavi. Whitney adds the provider but does not indicate if the provider is in or out of network. Additionally, there are other concerns on this call. When Whitney quoted the dental benefits, she stated “including unlimited extractions for free…”. She also does not accurately quote any of the necessary limitations of coverage on dental. When Whitney read off the prescriptions that were listed in Sunfire, she did not verify formulation. When Whitney was in the QA checklist, she did not give the benefit amounts for worldwide coverage. She simply tells the member “you have worldwide emergency coverage and transportation.” Whitney tells the member “it doesn’t expire until December 31st. As long as you use it all up before December 31st, you’re good to go” regarding the flex card. Sunfire should be read and states “Any unused amount rolls over each month and expires at the end of the plan year or upon disenrollment, whichever occurs first.” | O33: https://mypolicypoint-my.sharepoint.com/:w:/r/personal/mthomas_mypolicypoint_com/Documents/Performance%20Tracking/Complaint%20Tracking/WBenoit%2004.01.2026.docx?d=we6ca7b0fcfb848f88e468a561b4d9ff4&csf=1&web=1&e=6mDvn4
A34: Robin O'Quin | B34: Brian Henderson | C34: https://app.agencybloc.com/individuals/76356743/detail | D34: 46108 | E34: 46118 | F34: 46133 | G34: 46128 | H34: Carrier | I34: Devoted Health | J34: Member is confused about the prescription drug coverage and states that they were told the medications would be $12. Robin applied for LIS for the member and told her that the prescription will be $12 | K34: •Drugs - Cost or Coverage •Benefit Misinformation | L34: Founded | M34: •Drugs - Cost or Coverage •Medicaid Coverage •Benefit Misinformation | N34: At 39:52 Robin gathers prescriptions at 46:41 into the call. When she discusses coverage for the medications at 1:15:20 into the call, she states “it’ll bring that down to zero dollars. It’ll bring your medications all the way down to, well, if its just level one ow income subsidy, the most you’ll pay for a generic is $5.10. And the most you’ll pay for a brand name drug would be $12.60.” She tells the member at 1:33:46 “Like I said, it'll run about the same as the drug costs you were spending on your Humana plan there”. However, the cost for the Eliquis specifically is substantially higher. It isn’t until 1:41:40 into the call where she gives the benefits on the plan for the prescriptions as listed. However, she states “So for tier one, on this plan, the deductible applies to the initial coverage level. Tier two, that's $18. For tier two, generics, that's $19. For tier three, preferred brand generics, that's up to 21 percent, 21 percent, yes. The tier four, 33 percent, tier five, 25 percent, and tier six, that is $0. And like once again, I don't want you to be afraid about those medications because once that low-income subsidy steps in, that's going to be changed a whole lot”. Additionally, she states at 1:41:59 that tiers 1 and 2 would be $0 with LIS. Additionally, there were times that made it sound as if LIS was a guaranteed benefit and language was used that could make it appear that it would be contingent upon enrolling with her. For example, at 1:32:27 she states “So once I put you on this plan and I sign you up for your low income subsidy”, at 1:35:44 Robin states “But I'm gonna, like I said, wipe with this low income subsidy. I'm gonna wipe all that out for you so you will not be paying nearly this amount of money because that is just too much”. | O34: https://mypolicypoint-my.sharepoint.com/:w:/r/personal/mthomas_mypolicypoint_com/Documents/Performance%20Tracking/Complaint%20Tracking/ROQuin%2003.27.2026.docx?d=w2e0a9171715e47dd8271561bc770e106&csf=1&web=1&e=eIAac4
A35: Kylie DeMarino | B35: JT Tellez | C35: https://app.agencybloc.com/individuals/72028554/notes-attachments | D35: 45978 | E35: 46128 | F35: 46134 | G35: 46132 | H35: Carrier | I35: Humana | J35: The member alleges that their insurance agent and plan misrepresented benefits and failed to provide proper representation and assistance, leaving them without a local agent, unable to use expected benefits such as utility assistance, and confused about accessing covered services like transportation to medical appointments. | K35: •Providers - Medical •SSBCI Benefits •Benefit Misinformation | L35: Founded | M35: •Providers - Ancillary •SSBCI Benefits •Benefit Misinformation | N35: Kylie asked the client if he had any “dental, vision, hearing, or transportation needs,” but the question was presented in a broad and unstructured manner, limiting the depth of information gathered. The client disclosed a key dental issue, including a deteriorated tooth from childhood that ultimately fell out, along with gum line deterioration—indicating a likely need for implants. Under the Humana Dual Integrated (HMO D-SNP) H1036-340 plan, the $5,000 dental allowance does not cover implants, fluoride, or cosmetic services. The call was led by highlighting the flex allowance ($350 monthly) before fully developing and confirming all of the client’s healthcare needs. Kylie identified value by improving the client’s copay for Kamal Patel compared to their previous plan; however, the dental need was not aligned with plan coverage, resulting in a missed opportunity. Vision, transportation, and hearing needs were identified but only at a surface level, without deeper exploration or confirmation of how the member would access and utilize these benefits. | O35: Sending findings for coaching opportunity by email. | P35: Yes | Q35: 46135
A36: Ryan Lefler | B36: Brian Henderson | C36: https://app.agencybloc.com/individuals/73646586/notes-attachments | D36: 46050 | E36: 46129 | F36: 46136 | G36: 46133 | H36: Carrier | I36: Humana | J36: The beneficiary contacted CarePlus Health Plans regarding a bill for $735.75 for an injection, which he did not expect based on prior experience with Humana Gold Plus. The beneficiary stated that the sales agent who assisted with his CarePlus enrollment did not disclose or explain the higher copay for injections and assured him that the plan benefits would be "exactly the same" as his previous Humana plan. Upon receiving the bill, the beneficiary felt misled and expressed dissatisfaction with the agent's lack of education on plan details, particularly as he had never incurred such high costs with his prior coverage. | K36: •Drugs - Cost or Coverage •Benefit Misinformation | L36: Founded | M36: •Drugs - Cost or Coverage •Benefit Misinformation | N36: Medication Review & Gaps The $735.75 injection was not discussed during the call. Two medications listed in Sunfire (Amlodipine Besylate and Lisinopril) were not addressed. The agent did not verify whether the client was still taking these medications or inquire about additional prescriptions outside those initially provided. There was a missed opportunity to offer outreach to the pharmacy or prior carrier (Humana) to ensure a complete medication list. This gap in medication discovery likely contributed to the omission of the injection and other prescriptions. Medication Probing Opportunities While the agent asked for medication names and dosages, they did not consistently ask: Frequency of use Refill cadence Monthly quantity These questions are critical to accurately evaluating cost exposure and plan fit. | O36: Sending findings for coaching opportunity by email.
A37: Tonja Howard | B37: Brian Henderson | C37: https://app.agencybloc.com/individuals/74174174/detail | D37: 46063 | E37: 46106 | G37: 46136 | H37: Carrier | I37: Humana | J37: Humana received the following allegation: The member states the agent was told member qualified for $250 per month in spending allowance benefits and was not informed that enrolling would change his existing plan. The member further asserts that he did not intend to change plans, did not understand that a new application was being submitted on his behalf, and was unaware that he was being switched from his previous Care Needs Platinum plan (which offered $250) to the Care Complete plan (which offers only $25 per month). The member states he would not have agreed to downgrade his benefits and believes the plan change was completed through misrepresentation and misleading information. | K37: •SSBCI Benefits •Enrollment Consent •Benefit Misinformation | L37: Unfounded, coaching opportunities present | M37: •SSBCI Benefits •Enrollment Consent •Drugs - Cost or Coverage •Benefit Misinformation | N37: Sales leadership is to review the complaint with the agent, and coach them on the following: • The agent did not inform the member that he would receive $250 per month on a spending account card. Instead, the agent clearly stated that the Care Complete plan included a $25 monthly grocery allowance and a $20 monthly over-the-counter (OTC) benefit. • Enrollment Quality: The agent did not explain the Pharmacy Part D deductible to the member, which is a mandatory requirement per the sales script.
A38: Robert Lang | B38: Nesia Jefferies | C38: https://app.agencybloc.com/individuals/75541005/detail | D38: 46091 | E38: 46136 | F38: 46143 | G38: 46140 | H38: CTM | I38: Cigna | J38: Caller feels misled because unknown agent told beneficiary that heart doctor was in network turns out that is untrue beneficiary now cannot get pacemaker worked on which puts her in serious jeopardy | K38: •Providers - Medical | L38: Founded | M38: •Providers - Medical •Providers - Ancillary •Drugs - Cost or Coverage •Benefit Misinformation | N38: At approximately 11:47 into the call, the member indicated that her heart doctor does not take Cigna/HealthSprings and that this led her to changing her plan previously. At 14:10 into the call she provides Robert with the name of her cardiologist, Dr. James Towery. She indicated to Robert that it is very important that she keep this provider. At 30:52 in the call Robert indicates to the member that he does not see Dr. Towery in the network and that he needs to doublecheck. He indicates that he will check Dr. Towery’s website to see if they accept the plan. At 40:46 Robert tells the member “I don’t think Towery takes Cigna or Healthsprings. Let’s find out the name of the building or the name of the group that he serves in.” It is identified at 41:33 that he is affiliated with Birmingham Heart. At 45:52 Robert gives the name of another cardiologist, Dr. Joshua Cockrell, at that same location. He asks the member if that would be okay but does not specifically tell them that they would be replacing Dr. Towery with Dr. Cockrell. At 54:35 Robert does tell the member “Your doctors are in, where we found you a cardiologist in that same office as your old one. And then for services from providers outside the network, you must pay out of pocket. So just get your doctor to refer you. They should be able to take care of that.” This language was not direct and clear that Dr. Towery does not accept the plan and that the member would need to start to see Dr. Cockrell. Additionally, it made it sound as if the member would be covered for out-of-network providers if they were referred from their doctor. When Robert was reviewing other providers, he did not get clear locations for Dr. Bryan Flanagan. This doctor had multiple locations and only one of them was in-network. When Robert begins the dental portion of the QA checklist at approximately 51:46 into the call, he tells the member that “it covers, let's see, prophylaxis, which is dentures, zero copay, restorative, zero copay, implant services, zero copay, max facial surgery, everything”. Use of the word “everything” is not an accurate statement, as there are exclusions for cosmetic procedures. At approximately 57:23 into the call Robert asks the member for their prescriptions. The member does not have them available. He asks if they remember any off of the top of their head, and the member states that they do not. No prescriptions were gathered during this call. However, he tells her at multiple points that he believes that those costs will go down. He does not provide the member with any information on prescription drug deductibles or copays. The deductible is increased on this plan, as is the copay for Tier 1 medications and the coinsurance for tier 4. He also does not tell the member if their pharmacy is a preferred or standard retail pharmacy. | O38: https://mypolicypoint-my.sharepoint.com/:w:/r/personal/mthomas_mypolicypoint_com/Documents/Performance%20Tracking/Complaint%20Tracking/RLang%2003.10.2026.docx?d=wde7e5a37b930460e9417dec99b75cf46&csf=1&web=1&e=xd448y
A39: Gary Johnson | B39: Nesia Jefferies | C39: https://app.agencybloc.com/individuals/76268508/detail | D39: 46106 | E39: 46139 | F39: 46145 | G39: 46145 | H39: Carrier | I39: Devoted Health | J39: **INFO ONLY, no coaching needed***Caller feels misled because on 3/25/26 the Bene told the agent that he did not want to change and that he was happy where he was at. The agent just kept on and kept on. | K39: •Agent Behavior •Enrollment Consent | L39: Unfounded | M39: •Enrollment Consent | N39: Gary completed a needs analysis and compliantly covered all aspects of the compliance checklist prior to starting the enrollment. At approximately 53:46 in the call, Gary lets the member know that he will be enrolling into a new plan. A 54:18 into the call the member states “April 1st being the changes over to this plan that we’re discussing”, which indicates an understanding of the enrollment. At 1:02:54 Gary asks the member “Do I have your permission to record this enrollment?” to which the member responds affirmatively. Gary proceeds to read all application questions and provide the member with the necessary disclaimers. At 1:31:21 Gary states “So Columbus, if you want to enroll now, just go ahead and say your name, your date of birth, and that you agree to it.” At 1:31:30 responds with “Okay, my name is Columbus Butler. Date break is April 10th, 1551, and I agree to enroll in this coverage.” | O39: https://mypolicypoint-my.sharepoint.com/:w:/p/mthomas/IQAKJ5jqmp6xQaPdlWAROUrlAbkcGSPkpzr_L_-QlQOYhQY?e=aFA6KQ
A40: Duane Kipp | B40: Nesia Jefferies | C40: https://app.agencybloc.com/individuals/74775903/detail | D40: 46079 | E40: 46119 | F40: 46150 | G40: 46145 | H40: Member Services | I40: Gold Kidney Health Plan | J40: Member was told that dentist Dr. Timothy Evans was an INN dentist. | K40: •Providers - Ancillary | L40: Unfounded, coaching opportunities present | M40: •Providers - Ancillary •Benefit Misinformation | N40: Duane identifies the member’s dental needs at 30:44 into the call. The member mentions that the current plan does not cover his dental and he only has preventative needs. At approximately 1:11:05 into the call the dentist is identified as Dr. Evans. The member and Duane search for the provider and the provider is identified as Dr. Travis Evans at 1:14:48. At 1:25:52 Duane tells the member that “I am not seeing them in network. It does not mean necessarily that they won’t bill it. So let me double-check that.” At 1:27:16 Duane tells the member “I have somebody hunting that down. I’m looking at the network myself. I’m not seeing him.” While Duane did well with explaining the dentist was out-of-network, he made statements that may lead the member to believe that they would be covered at a higher rate for OON services. At 1:37:38 Duane tells the member “Out of network Medicare covered preventative dental services. The co-insurance for Medicare covered preventative dental is 20 percent for out of network. So that may be – if it is having to be out of network and for like that preventative, it may save you – if they'll bill it, you know, it would be at the non-out of network at 20 percent rather than paying full price. You know, if it does happen to be the case, he's out of network, okay?” Medicare only pays for dental services if it is covered as part of a larger treatment plan. | O40: https://mypolicypoint-my.sharepoint.com/:w:/p/mthomas/IQD5e9-I-NqJQY9UyE1hb_bHAQeAapbZyZ3VJKLd2hUhZPw?e=b8UM1f
A41: Gary Johnson | B41: Nesia Jefferies | C41: https://app.agencybloc.com/individuals/77335815/detail | D41: 46128 | E41: 46146 | F41: 46147 | G41: 46147 | H41: Member Services | I41: Devoted Health | J41: Member called in and stated that they were told that their home health care provider, Trinity Care Providers, was in network. She had the provider in her home and they are stating they are out-of-network. | K41: •Providers - Medical •Agent Behavior | L41: Founded | M41: •Providers - Medical •Agent Behavior •Benefit Misinformation | N41: The member’s home healthcare provider is not showing in network on Sunfire or on Devoted’s portal. The member mentions that she receives home health care services and identifies the provider as Trinity at 10:15 into the call. She mentions the provider again at 11:38 into the call. At 12:16 she states again that her home health care through Trinity is a necessity. She reiterates this at 16:58 in the call. At 33:02 Gary tells the member “I did check Trinity Health is already covered, so we don't got to worry about that as well.” At 40:08, the member asks what Trinity would need to do to be covered, and Gary responds that all they will need to do is provide the updated insurance card. At 40:32, Gary tells the member “Whenever you you're going to receive your home health care or whenever you receive your new member ID card just give Trinity a call let them your update in your insurance they do accept the new insurance. That is a zero dollar copay as well, you just have to let them know…” At 45:48 the member asks specifically if there will be a lapse in payment to her home health care provider, and Gary answers “No, ma’am.” He again states that they are in network when asked at approximately 46:41 and 47:11 into the call. Additionally, there was a concerning statement on the second call. At 2:17, Gary states, “If she was a good doctor, respectfully, she would notice that you have diabetes and you're only on a dual advantage plan, not a chronic special needs plan that would give you more, have you pay less. So that’s just my opinion, my professional opinion.” While we do want to work to overcome objections, this is not complaint with CMS guidelines. CMS regulations and most carrier guidelines explicitly prohibit agents from making negative or disparaging comments about a member's current providers. Saying "if she was a good doctor" is a direct attack on the member's physician's competence. Additionally, this could be perceived as him evaluating the quality of the member’s medical care. | O41: https://mypolicypoint-my.sharepoint.com/:w:/p/mthomas/IQC8Why86zw7SJp_DjDfY5ExAW5vZNbBctM9D8sCep65TsA?e=FegzKD | P41: Yes | Q41: 46148
A42: Kevin Ortega | B42: JT Tellez | C42: https://app.agencybloc.com/individuals/76325511/detail | D42: 46107 | E42: 46125 | F42: 46149 | G42: 46147 | H42: Member Services | I42: United Healthcare | J42: Member stated that he was told by AOR at time of enrollment that Dr. Steven Christensen (ophthalmologist) was INN. | K42: •Providers - Medical •Providers - Ancillary | L42: Founded | M42: •Providers - Medical •Providers - Ancillary •Benefit Misinformation | N42: Kevin originally pitched a plan with HealthSprings. When he pitched that, the provider was in network. However, Kevin changed plans to cover more dental to an AARP plan. It was never discussed that Dr. Steven Christensen would be out-of-network on that plan. The only reference to his doctor’s after the pitch change is at 1:06:53 when Kevin states “You’ll be able to go to your doctor still”. Additionally, there were some concerns about provider search on this call. At 20:12 the member identifies the doctor as “Dr. Christensen” with Southern Colorado Eye Specialists. At 24:20 it is mentioned that it is Steven Christensen. The doctor that is entered into Sunfire is Dr. Steven Christiansen. Dr. Christiansen doesn’t show affiliated with a Southern Colorado Eye Specialists. There was not any probing questions about the address to doublecheck. The member stated that he did not see any specialists, but mentioned that he is on methadone for pain management. He provides the name of the group as Denver Health Group. There were no additional probing questions on this facility/doctor. At 1:11:57 Kevin tells the member that he’ll be able to see “that spinal guy you were talking about”. When going through the needs assessment, it is identified that the member was in the process of getting dental implants. It was not specifically called out that these services, and any related services, would not be covered on the plan. Transportation was also identified as a need, but it was not discussed that it is not covered on this plan. When Kevin went through the QA checklist, he did not provide the emergency room copay. When he provided benefits for the hearing, he did not clearly state that the amounts of $199 to $1249 were the member’s copays. | O42: https://mypolicypoint-my.sharepoint.com/:w:/p/mthomas/IQAS-_oMDR2aQ46t4vcEiWElAYEBB6jVEa2spKLxflnY6JY?e=pR3RNH
A43: Whitney Benoit | B43: Brian Henderson | C43: https://app.agencybloc.com/individuals/76215284/detail | D43: 46104 | E43: 46133 | F43: 46150 | G43: 46147 | H43: Member Services | I43: Gold Kidney Health Plan | J43: Member was told at time of enrollment that most of her providers were in network, specifically Dr. Shahzad Shadmany, her endocrinologist. Member has now found that 5 of the 8 providers are out-of-network. | K43: •Providers - Medical | L43: Founded | M43: •Providers - Medical •Providers - Ancillary •Benefit Misinformation | N43: The member provided Dr. Shahzad Shadmany as her endocrinologist, Dr. Christopher Carpenter as her optometrist, and Dr. Aaron Latowsky as her urologist. Both of these providers are out-of-network. At 29:28 into the call, Whitney tells the member that “nephrologist cardiologist and endocrinologist on this plan have a zero dollar co-pay whether they're in network or out of network”. This is inaccurate as it is a 20% coinsurance for non-participating providers, regardless of specialty type. At 45:24 the member states “And you said that all the doctors that I've given you names for all are listed as being in-network. Well, you said it doesn't matter if a little nephrologist, or a cardiologist, my PCP, or my endocrinologist, anyway” to which Whitney responds “Right”. The member was told the incorrect information regarding copays and coverage for out-of-network specialists multiple times throughout this call. For the vision, the member was also told that they could see out-of-network vision providers for routine vision. However, routine vision is not covered out-of-network. Additionally, at 32:49 Whitney tells the member that she can still see out-of-network dental providers at a higher out-of-pocket cost. However, the plan does not cover dental out-of-network | O43: https://mypolicypoint-my.sharepoint.com/:w:/p/mthomas/IQCaMhU3RzjuT7z8SF_DtlQBAcKIKYoTZD87GvhJiUK1pjM?e=EpyhNu
A44: Christina Nguyen | B44: Nesia Jefferies | C44: https://app.agencybloc.com/individuals/74405733/detail | D44: 46070 | E44: 46135 | F44: 46150 | G44: 46147 | H44: Member Services | I44: WellCare | J44: Member states that they did not agree to enroll in a new plan, and only thought they were getting additional benefits. | K44: •Enrollment Consent | L44: Unfounded, coaching opportunities present | M44: •Enrollment Consent •SSBCI Benefits •Drugs - Cost or Coverage •Benefit Misinformation | N44: Christina compliantly completed the application and all necessary disclaimers. The member provided their name, date of birth, and “I agree” at 1:07:11 into the call. There were opportunities identified in how Christina presented the OTC benefit. She told the member twice on the call that they would be able to use the $71 benefit on healthy foods, utilities, etc because they had a chronic condition. This happened at 29:43 as part of the plan pitch and again at 41:33 as part of the QA checklist. Additionally, Christina provided misinformation on the member’s prescription drug coverage. She informed the member twice that her copays for the medications were a $0. However, the member’s pharmacy shows up as a standard retail and not preferred. Therefore, she would have copays. This info was given at 44:07 as part of QA and 32:39 as part of the pitch. | O44: https://mypolicypoint-my.sharepoint.com/:w:/p/mthomas/IQCtiTOWe6hyRoBFLMWIR2ggAbu-ook_5RjJPkhFdnj2qK8?e=1jkvp0 | P44: Yes | Q44: 46148
A45: Christina Nguyen | B45: Nesia Jefferies | C45: https://app.agencybloc.com/individuals/74729560/detail | D45: 46078 | E45: 46139 | F45: 46150 | G45: 46148 | H45: Member Services | I45: United Healthcare | J45: Member stated that the policy change caused issues with her doctors and she had to wait a month for treatment. | K45: •Providers - Medical •Benefit Misinformation | L45: Founded | M45: •Providers - Medical •Benefit Misinformation | N45: The member provided her primary care provider as Jessica Bennett and a specialist of Dan Cheney. At 29:47 into the call, Christina informs the member that her PCP is in network. However, the screenshot that is included in AMS shows the provider in Tennessee and not at the location in Kentucky that the member sees them at. Additionally, Dr. Cheney is also not in-network through the carrier portal. Christina called the provider and they stated that they do not accept PPO plans only HMO. However, the member insisted that they had to be on a PPO previously to see this provider. It is important to go by what is on the carrier portal as that is what they carrier uses to process the claims. Additionally, Christina told the member in the QA checklist that they can still see out-of-network providers because this plan is HMO-POS. This plan only includes out-of-network benefits for dental services. | O45: https://mypolicypoint-my.sharepoint.com/:w:/p/mthomas/IQDdXIS9T81eS74425f4En5KAQmqceZYn3PFALhqmREnSEA | P45: Yes | Q45: 46148
A46: Gabriela Rivera | B46: Nesia Jefferies | C46: https://app.agencybloc.com/individuals/77063400/detail | D46: 46121 | E46: 46146 | F46: 46150 | G46: 46148 | H46: Member Services | I46: Devoted Health | J46: Mr. Godwin says he told Gabriela he needs transportation benefits. This plan does not include transportation | K46: •Benefit Misinformation | L46: Founded | M46: •Benefit Misinformation | N46: Gabriela asks the member about their transportation needs at 23:16. The member indicates that they currently use Uber. At 24:11 she asks the member which benefit is most important for them, and they respond that all but hearing. At 57:51 Gabriela explains the benefit of Will Ride, which appears to be a third-party ride service. While this may be helpful to the member, she does not explicitly tell the member that this is not covered through their plan. Additionally, there is a charge for this service. For educational purposes, the member is on Medicaid so they will have non-emergency medical transportation through Medicaid. | O46: https://mypolicypoint-my.sharepoint.com/:w:/p/mthomas/IQD7KhiZEJL2TJO-_l3fX4IIAakXcuutysG8DMwAkhFxMQY?e=IIr8a1
A47: Robert Lang | B47: Nesia Jefferies | C47: https://app.agencybloc.com/individuals/73762594/detail | D47: 46051 | E47: 46139 | F47: 46150 | G47: 46148 | H47: Member Services | I47: United Healthcare | J47: Member is upset because she is still not getting her Part B giveback. Member is on Medicaid. Member is very upset and states that she was lied to or misled. | K47: •Medicaid Coverage •Benefit Misinformation | L47: Founded | M47: •Medicaid Coverage •Agent Behavior •Drugs - Cost or Coverage •Benefit Misinformation | N47: *This may have already been coached, as there was discussion in the SNP Channel regarding this call*The member refused to provide their MBI at the beginning of the call and stated that they were unsure if they still had Medicaid at approximately 3:04 into the call. It was identified that they do have a chronic condition. At 28:20, Robert pitches a Devoted plan with a $184 giveback but then switches to a Cigna plan with a $100 giveback. After gaining the member’s Medicare information, he determines at 37:03 into the call that the member does in fact have Medicaid. Robert does not inform the member at any point in the call after finding out that they have Medicaid that they will not be eligible for the giveback. Robert discusses the giveback benefit as if the member were eligible at least 5 times after that point (53:30, 53:51,1:04:03, 1:05:48, 1:19:09). Additionally, there were other areas of opportunity identified on this call. Robert used disparaging language towards the carrier’s agents. The member asked Robert why no one else found this plan for her. At 35:35 he states “You know it's just all a matter of when you talk to somebody from Health Spring they're kind of like they have a different attitude. I've not explained it but they don't try that hard. If they would have looked a little bit deeper they would have found this one.” At 36:07 he again states “Yeah it's because they didn't try.” During the QA portion of the call, he tells the member at 1:19:26 “So if you have an emergency situation or urgent care, they all have to take you.” While this is true of emergency rooms, it is not true with urgent care centers. At 1:21:40 Robert tells the member “All of your prescriptions should be exactly the same because it's still Cigna, and you have extra help. They're helping you with the co-pays. So I'm glad we're able to help you get covered.” Robert did not go over the medications listed in Sunfire or ask for any information on their prescriptions. Two of the medications listed are non-formulary. One, Ozempic, was mentioned by the member specifically. Additionally, he did not go over any of the quantity limits or restrictions. | O47: https://mypolicypoint-my.sharepoint.com/:w:/p/mthomas/IQB0OdhMJGFyQ5s6u_HCQIRKAXC0j8NAG8m3DKeGIfUSSYU?e=OsFb07
A48: Christina Nguyen | B48: Nesia Jefferies | C48: https://app.agencybloc.com/individuals/76297283/detail | D48: 46106 | E48: 46142 | F48: 46150 | G48: 46148 | H48: Member Services | I48: Zing Health | J48: The member states that she was told her pcp, Dr. Erica Pohlman, was in network. However, she has found out that the provider is not. | K48: •Providers - Medical | L48: Founded | M48: •Providers - Medical •Providers - Ancillary •Benefit Misinformation | N48: The member identifies Dr. Erica Pohlman at 11:19 into the call and states that it is very important to keep her. Christina calls the provider at 29:10 in the call to verify if they accept Zing plans. She does not differentiate between Elite or Select and the provider states that they do. At 35:19, Christina tells the member that their provider is in network. She again tells the member that the provider is in network at 51:06. When Christina began filling out the application, she asked the member if they wanted to list Dr. Pohlman on the application at approximately 1:09:06 into the call. However, at 1:10:05 she reads the verbiage on the application for when it is selected that they do now want to specify a PCP. Dr. Pohlman would not have been able to be listed as she is not participating with this plan. The member’s PCP is participating with the standard Zing plans and not the Elite plans. Screenshot below shows Sunfire’s indication. Screenshot in AMS is from the Zing provider search, but Christina did not select “Zing PSP Network” when checking. Additionally, there were concerns with QA checklist. When going over the dental at 51:53, Christina does not go over the required coverage limitations. At 52:04 when going over specialists, she does not specify which provider types are a $0 copay. She also does not provide the limitations for worldwide urgent or emergent care, just the copay amounts. In hospital coverage at 53:25 she states is it $350 from days one to six but does not state per day. | O48: https://mypolicypoint-my.sharepoint.com/:w:/p/mthomas/IQDRQgEPqSOyQ48X6EECGK2pAa2hJDz7nXznSktsgKJwV3I?e=pu3ONt
A49: Whitney Benoit | B49: Brian Henderson | C49: https://app.agencybloc.com/individuals/74292148/detail | D49: 46065 | E49: 46147 | F49: 46153 | G49: 46148 | H49: Carrier | I49: Humana | J49: Member was told at time of enrollment that Dr. Nazrah Franco was INN. However, member found out after going to his annual physical with Dr. Franco that they are not INN. Member complaint to Humana about being told that Dr. Franco was INN when they are not. Additionally, the member was told that all other providers were in network, but his dermatologist is not. | K49: •Providers - Medical | L49: Partially Founded | M49: •Providers - Medical •Benefit Misinformation | N49: The member’s PCP is identified as Dr. Franco Narzrah at 7:41 in the second call. Their dermatologist is identified as Dr. Harb at 2:29 in the third call. At 27:33 in the third call, Whitney informs the member that their primary care doctor is not in network. The member indicates that they can change the primary care provider. At 30:40, Whitney begins the process of finding another provider for the member. When Whitney tells the member that their primary care provider is not in-network, she specifically states “But the other places, the dermatology clinic and the new oncology clinic, and doctors, they are in network.” However, the member’s dermatologist is not in-network. | O49: https://mypolicypoint-my.sharepoint.com/:w:/p/mthomas/IQCuysf31d99RZTYn46VaNn-AU94dxyLQ4-A7dnaBqgblE8?e=Y9Euwn
A50: Lauren Wyke | B50: Michelle Thomas | C50: https://app.agencybloc.com/individuals/76504511/detail | D50: 46146 | E50: 46146 | F50: 46149 | G50: 46148 | H50: Member Services | I50: Member Services Call | J50: Member states that they had called in regard his rx, and noted that the previous person he was talking to was rude to him | K50: •Agent Behavior | L50: Founded | M50: •Agent Behavior | N50: There were multiple instances throughout this call where Lauren would not allow the member to ask questions or speak. It should be the priority of the agent to answer the member’s questions thoroughly. When he attempts to interject, she threatens to disconnect the call at two points in the call. This actually escalates the situation with the member. | O50: https://mypolicypoint-my.sharepoint.com/:w:/p/mthomas/IQBLhmJH_7_6TaEb0csbq0CcAVxEvt-PLWbINAgMMruoiKA?e=xISloW | P50: Yes | Q50: 46150
A51: Lauren Wyke | B51: Michelle Thomas | C51: https://app.agencybloc.com/individuals/76114404/detail | D51: 46114 | E51: 46121 | F51: 46150 | G51: 46149 | H51: Member Services | I51: Gold Kidney Health Plan | J51: Member stated that the conversation was very contentious and she did like Lauren’s attitude or tone. She said that she had questions about her plan and that Lauren refused to answer them and told her that she had a job to do and if she did not go over her script she was going to get into trouble | K51: •Agent Behavior | L51: Founded | M51: •Agent Behavior | N51: There were multiple instances throughout this call where Lauren would not allow the member to ask questions or speak. Lauren tells the member at multiple times throughout the call that she has a list of things to go through, or a process to go through. For example, at 15:44 she tells the member “Give me a moment, I’m trying to make sure I’ve touched on certain things with you”. At 25:36 she tells the member “I’m here to help answer your questions and I have a list of things that I have to talk about.” At 31:06 she tells the member “…But I havn’t finished all the things I want to tell you. So, let’s finish that up and this will answer your question.” These instances cause the member to feel that Lauren is not listening to her or allowing her to speak. The member mentions needing doctors and Lauren states that we usually do that on another call. It should be the priority of the agent to answer the member’s questions thoroughly on the call rather than following up at another time, unless that is the insistence of the member. | O51: https://mypolicypoint-my.sharepoint.com/:w:/r/personal/mthomas_mypolicypoint_com/Documents/Performance%20Tracking/Complaint%20Tracking/LWyke%2004.02.2026.docx?d=w6ae1238aff714eb1950d6fee08bdd2a6&csf=1&web=1&e=HfAQMy | P51: Yes | Q51: 46150
A52: Kylie DeMarino | B52: JT Tellez | C52: https://app.agencybloc.com/individuals/76603201/detail | D52: 46115 | E52: 46148 | F52: 46153 | G52: 46150 | H52: Member Services | I52: Zing Health | J52: Member stated that she was told at time of enrollment that her dentist Dr. Divya Bekal was INN. She went to the dentist and was told at the office that they were not INN | K52: •Providers - Ancillary •Providers - Medical | L52: Partially Founded | M52: •Providers - Ancillary •Providers - Medical •Benefit Misinformation | N52: This provider was not directly mentioned on the call. Kylie read the member the providers that were already listed in Sunfire. At approximately 7:02 into the call, she provides the member with Carrie Borland. The member indicates that this is her dentist. This is mentioned again at approximately 29:30. Kylie should have stopped and asked clarifying questions, as this provider is listed as a primary care provider in Sunfire. There were additional concerns, as well. The member mentions another primary care provider, Dr. Thomas Wagner, at approximately 7:12 seconds into the call. At 13:36 into the call Kylie informs the member that they would be able to see both Thomas Wagner and Dr. Borland on this plan. However, this plan is an Elite plan, and Dr. Wagner is not in network as a PCP on this plan. At approximately 40:02 into the call Kylie attempts to add the provider to the application. She states “he's labeled as like a specialist. So I'm going to just put the doctor that, and don't worry, I'm literally on the website, Thomas Wagner, Westwood Primary Care 34960, Center Ridge, North Ridge. I have his address, his phone number. He is covered” and indicates that there will just need to be a different PCP on the card. There were also concerns on the QA checklist. For ambulance, Kylie does not quote coverage for air ambulance. For dental, she does not quote the required coverage limitations. For Urgent care, she tells the member it is a $10 copay, not the $0-$10 as per Sunfire. For eyewear, she also does not quote the required coverage limitations. | O52: https://mypolicypoint-my.sharepoint.com/:w:/p/mthomas/IQD2vaSd9eyhSK0r61rWoWmeASmDZYdILjw6XcqVMyIry44?e=YEsThe
A53: Vidal Fakondo | B53: Brian Henderson | C53: https://app.agencybloc.com/individuals/76471005/detail | D53: 46111 | E53: 46149 | F53: 46155 | G53: 46153 | H53: Member Services | I53: Zing Health | J53: Member states when he enrolled medications would be free | K53: ["Drugs - Cost or Coverage"] | L53: Founded | M53: ["Drugs - Cost or Coverage","Benefit Misinformation"] | N53: Vidal asked the member for their prescriptions at approximately 30:35 into the call. At 38:47 into the call Vidal tells the member that “this plan does accept all your medications, which is a good thing, of course. So your providers are a network, your medications are taken care of…” The prescription portion of the QA checklist begins at 46:06. Vidal goes over the pharmacy deductible and any limitations on the prescriptions, but at no point does he provide the member with the costs associated with the medications. Additionally, when discussing plan benefits, Vidal incorrectly states that the member’s dentures and other dental services will apply to their maximum out-of-pocket. Only services covered under Parts A and B are applied to the maximum out-of-pocket. When Vidal quotes the member’s urgent care benefit, he stated “there is a $10 co-pay for any urgent care services for providers outside of the network, and a $0 co-pay for any primary care physician, urgent care needs.” Because this plan is an HMO, out-of-network providers are not covered. There was also unclear language regarding the member’s hospital copay. At approximately 45:31 in the call he stated that “plan also gives you up to $275 per day for a co-pay for days one to six for any acute hospital services”. The use of “gives you” may be misleading, especially considering the benefits discussed directly prior were vision services where the member has an allowance to use. | O53: https://mypolicypoint-my.sharepoint.com/:w:/p/mthomas/IQDd5oBfwTF6QoEtoU_zcVMtASWxNb110SE3TYGIyHsf3qQ?e=ZWs804
A54: Thomas Sonntag | B54: Brian Henderson | C54: https://app.agencybloc.com/individuals/77530565/detail | D54: 46134 | E54: 46153 | F54: 46156 | G54: 46154 | H54: Member Services | I54: Gold Kidney Health Plan | J54: Member stated that she was told at time of enrollment that Dr. Jay Turner, Alex Bakowski, NP and Barrow Brain and Spine were INN, but has since learned that they are not. | K54: ["Providers - Medical"] | L54: Partially Founded | M54: ["Providers - Medical"] | N54: This enrollment took place over three calls. There were not any references of Dr. Jay Turner, Alex Bakowski, NP or Barrow Brain and Spine. However, there were 2 providers mentioned on the call that were incorrectly identified as INN. At 17:21 in the first call the member states that they see Dr. Saraceni at Ironwood Womens Center on 159th Avenue in Goodyear. At 36:48 in that call Tom states that Dr. Saraceni is in network. However, she is not reflected in SF or on GKs search as in-network at that location. He reaffirms that this doctor is in-network at 52:32 that the provider is in network. At 29:06 in the third call the member mentions that they see a Dr. Chambos for pain management at 13555 W. McDowell Road. Tom informs the member at 30:24 that this provider is in network. However, Sunfire does not reflect this provider INN at that location, nor does the GK provider search. | O54: https://mypolicypoint-my.sharepoint.com/:w:/p/mthomas/IQAkb1mtRL9rQZT8ZQC9qTYpAcnE3-Nc0Zd2Qp6Ef1OHc8o?e=ffQGoU
A55: Tonja Howard | B55: Brian Henderson | C55: https://app.agencybloc.com/individuals/77530933/detail | D55: 46134 | E55: 46144 | F55: 46156 | G55: 46155 | H55: Carrier | I55: Devoted Health | J55: The member was told by agent that signed him up that he would qualify for the Food & Home Card benefit because of his Medicaid coverage and was not explained that he needs a qualifying condition as outlined in the EOC. The member unfortunately does not have a qualifying chronic condition. | K55: ["SSBCI Benefits"] | L55: Founded | M55: ["Providers - Medical","Benefit Misinformation","SSBCI Benefits"] | N55: Tonja asks the member if they have any chronic conditions at approximately 8:38 into the call. The member states “Listen, I'm good with everything. I don't have any problem with my heart with anything.” He goes on to say that he has been told his health is “unbelievable”. When Tonja asks him if he has any specialists, he states “No, not at all. I'm good with everything. My health is 100% good.” The member again indicates that he is in great health when going through the prescription drug coverage. At 26:02 Tonja pitches the SSBCI stating he is eligible. At 33:57 she states “Now, before the benefits start, Devote Health is going to reach out to confirm that you meet Medicare's qualifying condition criteria.” However, she doesn’t probe further or provide the member any additional information. Additionally, at approximately 13:27 into the call the member mentions that he is in the process of getting dental implants. When Tonja pitches the dental benefits, she does not go over any of the required limitations or copays. She also doesn’t specifically call out that implants are not covered on this plan. When Tonja is filling out the application, she indicates that she is listing Dr. Jason Bailey, the member’s PCP mentioned, on the application. However, this provider is an NP. The PCP listed on the application was Dr. Cherilyn Hanna Mahase. This is not discussed during the call or verified that this doctor works with Jason Bailey. It appears that the addresses of the providers are different. | O55: https://mypolicypoint-my.sharepoint.com/:w:/p/mthomas/IQA24N5Rmi8ASZisSv0fR3rbAc66kLd-zF4tagUzUBgtDVE?e=mVjdrh
A56: Robin O'Quin | B56: Brian Henderson | C56: https://app.agencybloc.com/individuals/77674269/detail | D56: 46142 | E56: 46153 | F56: 46156 | G56: 46155 | H56: CTM | I56: Gold Kidney Health Plan | J56: Caller feels misled because the beneficiary was told that she would be getting extra benefits and nothing would change about her coverage. She was told that her doctors accepted this insurance, however they do not. | K56: ["Providers - Medical","Enrollment Consent"] | L56: Founded | M56: ["Providers - Medical","Enrollment Consent","Benefit Misinformation"] | N56: Robin tells the member they are going to start the enrollment process at 1:32:44 and at 1:33:09 she asks “Do I have your permission to record this enrollment?” begins the enrollment attestations at approximately 1:49:26 into the call. She reads the final attestation, but it is not heard on the call her asking for the member to state their name, date of birth, and “I agree”. At 1:52:18 she moves into the HRA. A confirmation number for the enrollment is provided to the member at 2:04:36. Therefore, the member did not consent to enroll. At approximately 9:10 into the call the member provides their PCP as Dr. Michael Alexander on 4th Street. She provides her nephrologist as Dr. Diego Echeverri on Wiles Road at 10:33 into the call. These providers are in network at those locations. At 20:45 the member provides Dr. Mitchell Greenberg, her ophthalmologist, on University Drive. At 34:58, Robin indicates to the member that her doctors are all in network. At 35:29 she states “And so, your doctors do work with this plan”. She reiterates this at 36:58 and 58:48. However, Dr. Greenberg is not in-network at the location provided. The member mentions a hand specialist at 1:01:27 of Dr. Purnell Traverso. Robin accurately states he is out-of-network at 1:03:54. Additionally, the member provides their hospital at 14:43 as Coral Springs. This hospital is not in network for non-emergencies. There was no mention of the facilities participation status. The QA checklist on this call begins at 1:22:24. There were several areas of concern identified here. When quoting the dental and vision benefits, she provides an out-of-network benefit of $15 for these services but does not state that it is for Medicare covered services only. Member had mentioned needing comprehensive dental work done and did not have a provider in mind. Robin mentioned finding her one, but did not. When discussing the specialist copays at 1:25:18 she states “a kidney doctor, a hear doctor, or a doctor for diabetes” as a $0 copay rather than the provider type. There were also concerns in the way the smartphone was discussed. At 1:27:22 she tells the member that “This plan also will provide you a free phone service if you ever need it. The smartphone is free.” She does not indicate that there are eligibility requirements, such as signing up for care management. At 1:27:47, the member asks if it can be used internationally as well. She mentioned earlier in the call that she will be out-of-the country for two months in the summer. Robin responds “Inside and outside. Yes, ma'am. Wherever the T-Mobile service is. It's through T-Mobile.” From all available information, this coverage is only available within the country. | O56: https://mypolicypoint-my.sharepoint.com/:w:/r/personal/mthomas_mypolicypoint_com/Documents/Performance%20Tracking/Complaint%20Tracking/Robin%20OQuinn%2004.30.2026.docx?d=wd677234ac06a448485ea5bb5123de620&csf=1&web=1&e=oxWLVR

Sheet Sheet1
A2: Founded
A3: Unfounded
A4: Partial
A5: Unfounded, coaching opportunities present

Sheet Agent Roster
A1: Agent | B1: New Manager | C1: Manager Email | E1: Manager | F1: Email
A2: Kylie Demarino | B2: JT Tellez | C2: jtellez@mypolicypoint.com | E2: Brian Henderson | F2: bhenderson@mypolicypoint.com
A3: Sara Jarrell | B3: JT Tellez | C3: jtellez@mypolicypoint.com | E3: John St. Fleurant | F3: john.stfleurant@mypolicypoint.com
A4: Christina Nguyen | B4: Nesia Jefferies | C4: Rjefferies@mypolicypoint.com | E4: JT Tellez | F4: jtellez@mypolicypoint.com
A5: Duane Kipp | B5: Nesia Jefferies | C5: Rjefferies@mypolicypoint.com | E5: Michelle Thomas | F5: mthomas@mypolicypoint.com
A6: Robert Lang | B6: Nesia Jefferies | C6: Rjefferies@mypolicypoint.com | E6: Nesia Jefferies | F6: Rjefferies@mypolicypoint.com
A7: Sandra Stillwell | B7: JT Tellez | C7: jtellez@mypolicypoint.com | E7: John Tellez | F7: jtellez@mypolicypoint.com
A8: Tasia Clark | B8: Nesia Jefferies | C8: Rjefferies@mypolicypoint.com
A9: Anthony Boyle | B9: JT Tellez | C9: jtellez@mypolicypoint.com
A10: Victor Filimonchuk | B10: JT Tellez | C10: jtellez@mypolicypoint.com
A11: Lauren Wyke | B11: Michelle Thomas | C11: mthomas@mypolicypoint.com
A12: Aleccia Wright | B12: Brian Henderson | C12: bhenderson@mypolicypoint.com
A13: Amanda Rivas | B13: Michelle Thomas | C13: mthomas@mypolicypoint.com
A14: Andrea Morris | B14: JT Tellez | C14: jtellez@mypolicypoint.com
A15: Angelica Furlow | B15: Nesia Jefferies | C15: Rjefferies@mypolicypoint.com
A16: Asia Vann | B16: Brian Henderson | C16: bhenderson@mypolicypoint.com
A17: Bernie Livingston | B17: Brian Henderson | C17: bhenderson@mypolicypoint.com
A18: Davis Khauka | B18: JT Tellez | C18: jtellez@mypolicypoint.com
A19: Gabriela Rivera | B19: Nesia Jefferies | C19: Rjefferies@mypolicypoint.com
... A22: Katherine Varnum | B22: Michelle Thomas | C22: mthomas@mypolicypoint.com
A23: Mekaylen Wesley
A24: Mitchell LaMont | B24: JT Tellez | C24: jtellez@mypolicypoint.com
A25: Robert Hernandez | B25: Michelle Thomas | C25: mthomas@mypolicypoint.com
A26: Ryan Lefler | B26: Brian Henderson | C26: bhenderson@mypolicypoint.com
A27: Savannah Hollis | B27: Brian Henderson | C27: bhenderson@mypolicypoint.com
A28: Shenekia Nora | B28: Michelle Thomas | C28: mthomas@mypolicypoint.com
A29: Shicora Becton | B29: Nesia Jefferies | C29: Rjefferies@mypolicypoint.com
A30: Thomas Sonntag | B30: Brian Henderson | C30: bhenderson@mypolicypoint.com
A31: Tiera Jones | B31: JT Tellez | C31: jtellez@mypolicypoint.com
A32: Tonja Howard | B32: Brian Henderson | C32: bhenderson@mypolicypoint.com
A33: Trice Foster | B33: Michelle Thomas | C33: mthomas@mypolicypoint.com
A34: Vidal Fakondo | B34: Brian Henderson | C34: bhenderson@mypolicypoint.com
A35: Whitney Benoit | B35: Brian Henderson | C35: bhenderson@mypolicypoint.com
A36: Whitney Dantzler | B36: Nesia Jefferies | C36: Rjefferies@mypolicypoint.com

Sheet Policies
A1: Policy ID | B1: First Name | C1: Last Name | D1: MBI | E1: PhoneNumber | F1: Servicing | G1: Agent | H1: Name | I1: Column3 | J1: App Submit Date | K1: Effective Date | L1: StateAbbrev | M1: Carrier Name | N1: Individual ID
A2: 57354596 | B2: ODELL | C2: DARLING | D2: 3MD6-XG3-GC42 | E2: (513) 464-5780 | F2: Howard | G2: Tonja | I2: Tonja Howard | J2: 45951 | K2: 46023 | L2: OH | M2: Anthem Inc. | N2: 64287864
A3: 57239687 | B3: SHARON | C3: RITCHIE | D3: 9M53-MN3-XP75 | E3: 4196318941 | F3: Clark | G3: Tasia | I3: Tasia Clark | J3: 45945 | K3: 46023 | L3: OH | M3: Devoted Health | N3: 64499654
A4: 57239754 | B4: Danny | C4: Ritchie | D4: 7QX4-NN7-GA87 | F4: Clark | G4: Tasia | I4: Tasia Clark | J4: 45945 | K4: 46023 | L4: OH | M4: Devoted Health | N4: 64500172
A5: 57240382 | B5: Ray | C5: Stephens | D5: 2Y49-NC5-AM52 | F5: Clark | G5: Tasia | I5: Tasia Clark | J5: 45945 | K5: 46023 | L5: OH | M5: Devoted Health | N5: 64696074
A6: 57252177 | B6: MICHAEL | C6: RENNICK | D6: 9UU4-RC9-VT70 | E6: 5738812088 | F6: Clark | G6: Tasia | I6: Tasia Clark | J6: 45945 | K6: 46023 | L6: MO | M6: WellCare | N6: 64723174
A7: 57431596 | B7: TROY | C7: WILCOX | D7: 6AJ6-DU0-NK44 | E7: 3172895565 | F7: Varnum | G7: Katherine | I7: Katherine Varnum | J7: 45953 | K7: 46023 | L7: IN | M7: United Healthcare | N7: 65270924
A8: 57315393 | B8: LC | C8: MCFARLAND JR | D8: 6UA2-M70-TN99 | E8: 2817140411 | F8: Howard | G8: Tonja | I8: Tonja Howard | J8: 45948 | K8: 46023 | L8: TX | M8: Devoted Health | N8: 65289001
A9: 57353195 | B9: JAMES | C9: WILLIAMS JR | D9: 6KF6-HQ3-HX51 | E9: 2512293614 | F9: Boyle | G9: Anthony | I9: Anthony Boyle | J9: 45951 | K9: 46023 | L9: AL | M9: Devoted Health | N9: 65290304
A10: 57256033 | B10: VICKIE | C10: ESSEX | D10: 6VT2-JV7-VN83 | E10: 4346606460 | F10: Howard | G10: Tonja | I10: Tonja Howard | J10: 45945 | K10: 46023 | L10: VA | M10: United Healthcare | N10: 65412104
A11: 57296005 | B11: KENDALL | C11: HUBERT | D11: 3AR1-NU1-GJ38 | E11: 9364332247 | F11: Howard | G11: Tonja | I11: Tonja Howard | J11: 45947 | K11: 46023 | L11: TX | M11: Cigna | N11: 65416056
A12: 58072996 | B12: Kathy | C12: Peyton | D12: 8N66-TR4-AT49 | E12: (540) 905-9420 | F12: Wesley | G12: Mekaylen | I12: Mekaylen Wesley | J12: 45974 | K12: 46023 | L12: VA | M12: United Healthcare | N12: 65437341
A13: 57273343 | B13: ELIZABETH | C13: PINEDO | D13: 8J38-HG6-NQ34 | E13: 5133743239 | F13: Howard | G13: Tonja | I13: Tonja Howard | J13: 45946 | K13: 46023 | L13: OH | M13: Humana | N13: 65444963
A14: 57240767 | B14: ANTHONY | C14: PEARSON | D14: 9F38-QG9-UD34 | E14: 7736208495 | F14: Wesley | G14: Mekaylen | I14: Mekaylen Wesley | J14: 45945 | K14: 46023 | L14: IL | M14: Devoted Health | N14: 65589924
A15: 57281934 | B15: ROY | C15: FARMER | D15: 2F65-J53-UY64 | E15: 4345441922 | F15: DeMarino | G15: Kylie | I15: Kylie DeMarino | J15: 45946 | K15: 46023 | L15: VA | M15: United Healthcare | N15: 65842522
A16: 59727010 | B16: DEBORAH | C16: WILSON | D16: 6G36-R57-RQ44 | E16: 9013053321 | F16: Boyle | G16: Anthony | I16: Anthony Boyle | J16: 46042 | K16: 46054 | L16: TN | M16: Anthem Inc. | N16: 65872806
A17: 57255191 | B17: TIMOTHY | C17: MARQUART | D17: 6YN1-AY4-ND91 | E17: 7022414412 | F17: Clark | G17: Tasia | I17: Tasia Clark | J17: 45945 | K17: 46023 | L17: NV | M17: WellCare | N17: 65881430
A18: 57255237 | B18: Shirleen | C18: Marquart | D18: 5E80-RH2-UH13 | F18: Clark | G18: Tasia | I18: Tasia Clark | J18: 45945 | K18: 46023 | L18: NV | M18: WellCare | N18: 65881735
A19: 58048138 | B19: COLETTE | C19: HILL-EL | D19: 3RD8-YV5-JK49 | E19: 9542180859 | F19: DeMarino | G19: Kylie | I19: Kylie DeMarino | J19: 45973 | K19: 46023 | L19: KY | M19: Devoted Health | N19: 65959738
A20: 57405135 | B20: JULIET | C20: FISHPAW | D20: 6V42-JM7-PV09 | E20: 9044158390 | F20: Waldropt | G20: Gail | I20: Gail Waldropt | J20: 45945 | K20: 46023 | L20: FL | M20: Humana | N20: 66001454
A21: 57236198 | B21: SANDRA | C21: CASMER | D21: 2AU1-JV4-AM23 | E21: 4234264170 | F21: Clark | G21: Tasia | I21: Tasia Clark | J21: 45945 | K21: 46023 | L21: TN | M21: Devoted Health | N21: 66154368
A22: 57236240 | B22: David | C22: Casmer | D22: 1AG8-Q54-YT50 | E22: (423) 607-9507 | F22: Clark | G22: Tasia | I22: Tasia Clark | J22: 45945 | K22: 46023 | L22: TN | M22: Devoted Health | N22: 66155780
A23: 60666031 | B23: WESLEY | C23: WHITE | D23: 7PC9-DN3-UG35 | E23: 5403762795 | F23: DeMarino | G23: Kylie | I23: Kylie DeMarino | J23: 46071 | K23: 46082 | L23: VA | M23: Anthem Inc. | N23: 66288323
A24: 57405291 | B24: GENEVA | C24: KALLIE | D24: 5AE3-CF1-MA11 | E24: 9793477404 | F24: Waldropt | G24: Gail | I24: Gail Waldropt | J24: 45946 | K24: 46023 | L24: TX | M24: WellCare | N24: 66299034
A25: 57251285 | B25: DARLENE | C25: WALKER | D25: 7KT1-QU8-YD05 | E25: 5743181373 | F25: Howard | G25: Tonja | I25: Tonja Howard | J25: 45945 | K25: 46023 | L25: IN | M25: Humana | N25: 66332278
A26: 57241647 | B26: RICHARD T. | C26: SMITH | D26: 8KJ3-X90-DP97 | E26: 7652420365 | F26: DeMarino | G26: Kylie | I26: Kylie DeMarino | J26: 45945 | K26: 46023 | L26: IN | M26: Anthem Inc. | N26: 66341822
A27: 57254096 | B27: Michael | C27: Crane | D27: 1TF8-QE0-FV58 | E27: 4173170729 | F27: Wesley | G27: Mekaylen | I27: Mekaylen Wesley | J27: 45945 | K27: 46023 | L27: KS | M27: Devoted Health | N27: 66356561
A28: 59598620 | B28: MARY | C28: THOMAS | D28: 8GP1-GM3-XY09 | E28: 8176294291 | F28: Boyle | G28: Anthony | I28: Anthony Boyle | J28: 46037 | K28: 46054 | L28: TX | M28: United Healthcare | N28: 66423155
A29: 57253344 | B29: KATHY | C29: SERATT | D29: 4T17-FN4-XD52 | E29: 7312250925 | F29: Howard | G29: Tonja | I29: Tonja Howard | J29: 45945 | K29: 46023 | L29: TN | M29: United Healthcare | N29: 66461119
A30: 57280543 | B30: GERARDO | C30: PEREZ | D30: 8YC3-JP4-AD72 | E30: 2392719322 | F30: Wesley | G30: Mekaylen | I30: Mekaylen Wesley | J30: 45992 | K30: 46023 | L30: FL | M30: Humana | N30: 66570230
A31: 57238768 | B31: JIMMIE | C31: LUCKY | D31: 1UM6-VN8-PY57 | E31: 8438614287 | F31: DeMarino | G31: Kylie | I31: Kylie DeMarino | J31: 45945 | K31: 46023 | L31: SC | M31: Humana | N31: 66624190
A32: 63634463 | B32: MARISSA | C32: DEFILIPPO | D32: 8N53-AV0-AU19 | E32: 9705569257 | F32: Foster | G32: Trice | I32: Trice Foster | J32: 46149 | K32: 46174 | L32: CO | M32: Devoted Health | N32: 66791902
A33: 57404728 | B33: WILFORD | C33: WHITE SR | D33: 5k36-UH5-JA62 | E33: 8328912245 | F33: Waldropt | G33: Gail | I33: Gail Waldropt | J33: 45952 | K33: 46023 | L33: TX | M33: Humana | N33: 66897688
A34: 57239951 | B34: MARY | C34: GRAVESANDE | D34: 9GD8-MJ8-KK68 | E34: 2513037342 | F34: Boyle | G34: Anthony | I34: Anthony Boyle | J34: 45945 | K34: 46023 | L34: AL | M34: Devoted Health | N34: 67030675
... A49: 57252863 | B49: Roberta | C49: kaletta | D49: 2T79-FX8-DA36 | E49: 2602586635 | F49: Clark | G49: Tasia | I49: Tasia Clark | J49: 45945 | K49: 46023 | L49: IN | M49: Anthem Inc. | N49: 68643363
A50: 57251799 | B50: GREGORY | C50: OGLESBY | D50: 1KY9-N73-CY27 | F50: Livingston | G50: Bernie | I50: Bernie Livingston | J50: 45945 | K50: 46023 | L50: NC | M50: Devoted Health | N50: 68665681
A51: 58064154 | B51: BRENDA | C51: THOMAS | D51: 3MG0-HK1-PF08 | E51: 9199248660 | F51: Howard | G51: Tonja | I51: Tonja Howard | J51: 45974 | K51: 46023 | L51: NC | M51: Aetna Inc. | N51: 68852026
A52: 57387235 | B52: SHANNON | C52: FLOYD | D52: 9TT2-G83-UH09 | E52: 4798661293 | F52: Wyke | G52: Lauren | I52: Lauren Wyke | J52: 45952 | K52: 46023 | L52: AR | M52: Aetna Inc. | N52: 68854642
A53: 58196195 | B53: Maria | C53: Sanchez | D53: 7m01-ka9-xu14 | E53: 3184389501 | F53: Livingston | G53: Bernie | I53: Bernie Livingston | J53: 45979 | K53: 46023 | L53: LA | M53: Humana | N53: 68890697
A54: 57251571 | B54: LARAINE | C54: WHITE | D54: 8AW9-Q08-HF59 | E54: 8632661348 | F54: Begley | G54: Chaney | I54: Chaney Begley | J54: 45945 | K54: 46023 | L54: FL | M54: United Healthcare | N54: 68903389
A55: 57291876 | B55: Calvin | C55: Brown | D55: 2GW2-WH0-WQ88 | E55: 9123230559 | F55: Rivera | G55: Gabriela | I55: Gabriela Rivera | J55: 45946 | K55: 46023 | L55: GA | M55: Devoted Health | N55: 68926149
A56: 57279375 | B56: KENNETH | C56: CROWDER | D56: 9P32-J47-FQ14 | E56: 4709655319 | F56: Stillwell | G56: Sandra | I56: Sandra Stillwell | J56: 45946 | K56: 46023 | L56: GA | M56: Aetna Inc. | N56: 68997956
A57: 57467576 | B57: Toby | C57: Estep | D57: 8YA3-KT7-WM78 | E57: 4792128262 | F57: Filimonchuk | G57: Victor | I57: Victor Filimonchuk | J57: 45955 | K57: 46023 | L57: AR | M57: United Healthcare | N57: 69027370
A58: 57238171 | B58: KUNTA | C58: GLADNEY | D58: 1EP6-C27-YW47 | E58: 6364619030 | F58: DeMarino | G58: Kylie | I58: Kylie DeMarino | J58: 45945 | K58: 46023 | L58: MO | M58: Devoted Health | N58: 69060908
A59: 57250098 | B59: JOHNNY | C59: STALLION | D59: 3WU2-RF7-HA94 | E59: 9542976955 | F59: Wesley | G59: Mekaylen | I59: Mekaylen Wesley | J59: 45945 | K59: 46023 | L59: FL | M59: Devoted Health | N59: 69074849
A60: 57361508 | B60: SAMUEL | C60: CLINTON | D60: 8ED8-Q93-HE24 | E60: 6362324528 | F60: Howard | G60: Tonja | I60: Tonja Howard | J60: 45951 | K60: 46023 | L60: MO | M60: Devoted Health | N60: 69078031
A61: 57275232 | B61: THOMAS | C61: WHITNEY | D61: 5K32-TY7-JC02 | E61: 9706439652 | F61: Howard | G61: Tonja | I61: Tonja Howard | J61: 45946 | K61: 46023 | L61: CO | M61: Humana | N61: 69094697
A62: 55935103 | B62: Maria | C62: Estelle | D62: 8JP9-MY8-AT44 | E62: 9412988292 | F62: Filimonchuk | G62: Victor | I62: Victor Filimonchuk | J62: 45945 | K62: 46023 | L62: FL | M62: Devoted Health | N62: 69151249
A63: 57572324 | B63: DARLENE | C63: LEWIS | D63: 9U60-TQ0-ET38 | E63: 5044057770 | F63: Filimonchuk | G63: Victor | I63: Victor Filimonchuk | J63: 45958 | K63: 46023 | L63: LA | M63: United Healthcare | N63: 69189545
A64: 60595538 | B64: Lisa | C64: Brant | D64: 9KX4-W29-QC88 | E64: (229) 269-7864 | F64: Morris | G64: Andrea | I64: Andrea Morris | J64: 46066 | K64: 46082 | L64: GA | M64: Aetna Inc. | N64: 69223261
A65: 57372424 | B65: REBECCA | C65: MINGS | D65: 3cd5-vj4-ng75 | E65: 5024428441 | F65: Stillwell | G65: Sandra | I65: Sandra Stillwell | J65: 45951 | K65: 46023 | L65: KY | M65: Humana | N65: 69223411
A66: 57371625 | B66: GILBERT | C66: MANNING | D66: 2NR4-MT8-NH68 | E66: 9122001356 | F66: Howard | G66: Tonja | I66: Tonja Howard | J66: 45951 | K66: 46023 | L66: GA | M66: Aetna Inc. | N66: 69242594
A67: 57252414 | B67: EMORY | C67: DUCKWORTH | D67: 4JW7-AY2-DN36 | E67: 7706564329 | F67: Begley | G67: Chaney | I67: Chaney Begley | J67: 45945 | K67: 46023 | L67: GA | M67: Devoted Health | N67: 69245528
A68: 57285238 | B68: ZANDEL | C68: WHITE | D68: 3C29-Q56-JP22 | E68: 2706669099 | F68: Stillwell | G68: Sandra | I68: Sandra Stillwell | J68: 45946 | K68: 46023 | L68: KY | M68: WellCare | N68: 69247951
A69: 57255291 | B69: JOHNNY | C69: FORCE | D69: 5YJ2-WT6-DX24 | E69: 8707540656 | F69: Morris | G69: Andrea | I69: Andrea Morris | J69: 45945 | K69: 46023 | L69: AR | M69: Devoted Health | N69: 69249766
A70: 57254249 | B70: FELICIA | C70: LIPSCOMB | D70: 9W07-PF9-VU44 | E70: 9807459099 | F70: Laster | G70: Jessica | I70: Jessica Laster | J70: 45945 | K70: 46023 | L70: NC | M70: Devoted Health | N70: 69276625
A71: 57375153 | B71: CAROL | C71: RAINE | D71: 4FJ7-A46-QU51 | E71: 6603415399 | F71: Filimonchuk | G71: Victor | I71: Victor Filimonchuk | J71: 45951 | K71: 46023 | L71: MO | M71: United Healthcare | N71: 69299651
A72: 57398931 | B72: ROBERT | C72: FORST | D72: 8DX8-E56-CD48 | E72: 9203724325 | F72: Rivera | G72: Gabriela | I72: Gabriela Rivera | J72: 45952 | K72: 46023 | L72: WI | M72: Humana | N72: 69316953
A73: 58070998 | B73: WILLIE | C73: GORDON | D73: 7X80-JC6-ME49 | E73: 9202795030 | F73: Clark | G73: Tasia | I73: Tasia Clark | J73: 45974 | K73: 46023 | L73: WI | M73: Humana | N73: 69354761
A74: 57266141 | B74: SONYA | C74: FELIPE | D74: 7HW3-FT6-TC07 | E74: 2569516661 | F74: Boyle | G74: Anthony | I74: Anthony Boyle | J74: 45946 | K74: 46023 | L74: AL | M74: Devoted Health | N74: 69360500
A75: 57291058 | B75: Lesha | C75: Webster | D75: 8R86-DA5-PK74 | E75: 6206390690 | F75: Curbelo | G75: Janet | I75: Janet Curbelo | J75: 45946 | K75: 46023 | L75: MO | M75: Devoted Health | N75: 69361163
A76: 57279897 | B76: Pamela | C76: Jones | D76: 7H57-F17-AX52 | E76: (502) 262-7095 | F76: Curbelo | G76: Janet | I76: Janet Curbelo | J76: 45946 | K76: 46023 | L76: KY | M76: Devoted Health | N76: 69369841
A77: 57249560 | B77: TINA | C77: SHIRLEY | D77: 7r22-hh1-vk99 | E77: 8167477774 | F77: Maver | G77: Krista | I77: Krista Maver | J77: 45945 | K77: 46023 | L77: MO | M77: Humana | N77: 69407493
A78: 57939809 | B78: RHONDA | C78: HUGHLING | D78: 9F10-J64-YY09 | E78: 4179552250 | F78: Wesley | G78: Mekaylen | I78: Mekaylen Wesley | J78: 45968 | K78: 46023 | L78: MO | M78: Devoted Health | N78: 69411746
A79: 57252529 | B79: SANDRA | C79: RICE | D79: 5uw6-jh0-cp77 | E79: 5737428362 | F79: Maver | G79: Krista | I79: Krista Maver | J79: 45945 | K79: 46023 | L79: MO | M79: Humana | N79: 69416562
A80: 57241066 | B80: ROBERT | C80: BRUCH | D80: 3tu5-uq1-rf78 | E80: 8167191557 | F80: Maver | G80: Krista | I80: Krista Maver | J80: 45945 | K80: 46023 | L80: MO | M80: Devoted Health | N80: 69426912
A81: 57932189 | B81: JEFFREY | C81: MINTON | D81: 1yj7-d82-ud47 | E81: 2564053947 | F81: Nguyen | G81: Christina | I81: Christina Nguyen | J81: 45968 | K81: 46023 | L81: AL | M81: Aetna Inc. | N81: 69429371
A82: 57253418 | B82: MARY | C82: JACKSON | D82: 1PY1-DH0-CT31 | E82: 7066047564 | F82: Filimonchuk | G82: Victor | I82: Victor Filimonchuk | J82: 45945 | K82: 46023 | L82: GA | M82: Humana | N82: 69441584
A83: 57306864 | B83: Debra | C83: Pinkins | D83: 4H31-VP0-DD04 | E83: 5046767575 | F83: Rivera | G83: Gabriela | I83: Gabriela Rivera | J83: 45947 | K83: 46023 | L83: LA | M83: United Healthcare | N83: 69443395
A84: 58579350 | B84: BEVERLY | C84: MCGARY | D84: 2WP0-H60-AA49 | E84: 8167265280 | F84: Morris | G84: Andrea | I84: Andrea Morris | J84: 45993 | K84: 46023 | L84: MO | M84: Devoted Health | N84: 69455711
A85: 57632413 | B85: CONNIE | C85: WILKERSON | D85: 2dn6-hm1-wh74 | E85: 13607229041 | F85: Livingston | G85: Bernie | I85: Bernie Livingston | J85: 45959 | K85: 46023 | L85: FL | M85: Humana | N85: 69489109
